Workbook
Name __max1: 'TRA79'!$S$9
Name _cis1: TRA61_FTA!$Y$33
Name _COM2: Index!$T$2
Name _COM3: Index!$T$3
Name _dts1: 'p2'!$AF$2
Name _FTA1: Notes!$D$3
Name _FTA3: 'TRA18'!$N$13
Name _ftn1: 'TRA90'!$R$22
Name _ftnref1: 'TRA90'!$R$6
Name _INC2: 'TRA18'!$N$15
Name _max1: 'TRA79'!$S$9
Name _nm1: 'p1'!$AJ$3
Name _ref1: 'TRA4'!$C$1
Name _reo1: Index!$C$275
Name _UA2: 'TRA18'!$N$14
Name _ver1: Notes!$S$5
Name _YA1: 'TRA30'!$M$1
Name ab: 'TRA2'!$AO$17
Name activity: Income!$E$12:$N$263
Name adet: 'TRA56'!$T$4
Name assets: 'TRA5'!$B$321:$B$339
Name assets_bpa: 'TRA6'!$B$52:$B$70
Name blanks: Index!$C$273
Name BS: 'TRA135'!$X$3:$X$242
Name bs_date_day: B_Sheet!$C$4
Name bs_date_month: B_Sheet!$D$4
Name cbmer: 'Exchange Rates'!$L$5:$S$38
Name cis: TRA61_FTA!$Z$33
Name ck: 'TRA58'!$AC$4
Name cnt: 'TRA65'!$N$5
Name COM: Index!$T$1
Name conv: 'p1'!$BK$48
Name ctry_list: 'TRA124'!$AB$1:$AB$108
Name cur: 'p1'!$Z$70
Name curr: 'p1'!$F$5
Name cv: TRA9_14!$K$155
Name dat: Index!$C$271
Name date_from: 'p1'!$G$66
Name date_month: 'TRA115'!$AA$2:$AB$13
Name date_to: 'p1'!$M$66
Name dis: 'TRA2'!$AO$19
Name dts: 'p1'!$BE$14
Name efile: Notes!$D$1
Name engagement_1: 'TRA85'!$U$4
Name ER_ya: 'p1'!$BB$48:$BE$72
Name er_ya1: 'p1'!$BB$47:$BD$71
Name eu_countries: 'TRA82'!$AL$60:$AL$86
Name EUR: Notes!$H$5
Name fi: 'TRA4'!$X$5
Name fisc: Index!$F$153
Name FO: 'TRA7'!$W$7
Name ft: 'TRA5'!$CA$3
Name FTA: Notes!$D$2
Name FU: Consolidation!$B$1:$B$51
Name fwt12a: 'TRA53'!$BC$85:$BD$86
Name FWT5A: 'TRA53'!$BC$1:$BD$12
Name ip: 'TRA5'!$CA$4
Name ipc: 'TRA35'!$AA$2
Name kambju: 'Exchange Rates'!$V$5:$W$52
Name LATE: 'TRA42'!$CP$4

Sheet Notes
D1: =IF(fisc<>0,"Electronic filing is mandatory!!","")
B2: Malta Tax & Customs Administration | D2: NOTE THAT TAXED INCOME RELIEVED BY TAX CREDITS IS ALLOCATED TO THE FINAL TAX ACCOUNT
D3: NOTE THAT INCOME SUBJECT TO FINAL WITHHOLDING TAX IS ALLOCATED TO THE FINAL TAX ACCOUNT
B5: ="NOTES ON USING THE COMPANY TAX RETURN FOR Y/A "&ya&" [VERSION CONTROL - " &_ver1 -> NOTES ON USING THE COMPANY TAX RETURN FOR Y/A 2025 [VERSION CONTROL - TA2_e-CO_2025_Ver 1.1] | D5: =F7&"_e-CO_"&ya&"_Ver 1.1" -> TA2_e-CO_2025_Ver 1.1 | F5: Version Control | H5: ="" | S5: =ver&"]" -> TA2_e-CO_2025_Ver 1.1]
B6: I M P O R T A N T to note that this spreadsheet is designed to work on MS Excel 2013 and later versions. Earlier versions of MS Office are no longer supported. | D6: (See DISCLAIMER in NOTES page)
F7: =IF(rafind=1,"TA2","AF2")
B8: GENERAL | D8: MTCA - Malta
B9: This spreadsheet version is intended solely for the electronic filing of company returns. It includes the full set of tax return attachments and the TIFD component.
B11: The exported file must be submitted through the MTCA Website http://www.cfr.gov.mt
B13: PLEASE ENSURE THAT YOU USE THE APPROPRIATE ATTACHMENTS PROVIDED TO REPORT INCOME AND TO CLAIM DEDUCTIONS, TAX CREDITS, RELIEFS, INCENTIVES, ETC. THE RETURN WILL BE CONSIDERED AS INCOMPLETE IF THE REQUIRED INFORMATION IS NOT REPORTED IN THE APPROPRIATE SPACE PROVIDED IN THE TAX RETURN AND ATTACHMENTS.
B15: DISCLAIMER
B16: This spreadsheet is intended to facilitate the filling of the company income tax return. While every effort has been made to ensure the proper functioning of this spreadsheet, the Administration does not accept any liability for erroneous results or non-compliance with legal provisions. Responsibility for the correctness of the self-assessment determination and tax calculation, in accordance with the applicable legal provisions, rests with the person signing the return. Please use the space provided on page 8 of the return to indicate and explain any 'forced' inputs or adjustments to derive a result that diverges from that derived by any automated calculation in the e-return.
B18: OPERATION AND NAVIGATION
B22: Adjust the screen size and layout to your preference.
B24: Use the TAB key to switch from one field to another. Make sure that values are allocated to the proper tax account.
B26: The workbook will not work properly with data being dragged from other cells or with the use of the cut and paste functions.
B28: VALIDATIONS AND CALCULATIONS
B30: Validations are present in all sheets.
B32: Some validations are tied to the extended questionnaire on page 2 and depend entirely on the accuracy, completeness and correctness of the answers given. For example if it is stated that the company does not benefit under the BPA all fields in the tax computation and the tax calculation referring to BPA incentives are dimmed. Any data entry in these fields will be displayed in red. The same applies for the foreign income account and the payment of dividends.
... B48: Make sure that the correct data is inputted under the proper item description. A value for each mandatory field is always required [see TIFD guidelines page 17]. However, two mandatory fields in the Balance Sheet are automatically disactivated in the case of Trusts.
XFC49: final concluded today | XFD49: 43556
B50: The two worksheets containing the TIFD component are protected. They include macros that will restrict the print area to value fields only. If multiple lines of business are present in the income statement you have to indicate the activity number to be printed in cell C 296. Once data input is complete:
B51: - click on the Print set-up button at the bottom of the sheet;
B52: - the worksheets will list only the value fields that need to be printed.
B53: You can now proceed with the print job - the print area has been pre-set. Each worksheet has another button to remove the print set-up. | IV53: 41696
B54: =ver -> TA2_e-CO_2025_Ver 1.1 | IV54: Return_2014d_67_final_3

Sheet p1
A1: =IF(AL2=1,CY2,IF(AL2=2,CZ2,DC2)) | F1: =IF(AL2=1,DA2,IF(AL2=2,DF2,DD2))
V2: =ver -> TA2_e-CO_2025_Ver 1.1 | AJ2: ="Ref: "&reg | AK2: Return / AF2 indicator / Viewing | AL2: 1 | BB2: Arab Emirates Dirham | CA2: 0 | CB2: trust indiator | CY2: TR | CZ2: FR | DA2: Income Tax Return | DC2: View | DD2: RETURN / | DF2: Further Return
F3: =IF(AL2=1,DA3,IF(AL2=2,DF3,DD3)) | AJ3: ="Name: "& NM | BB3: Australian Dollar | DA3: and Self Assessment | DD3: FURTHER RETURN | DF3: Adjustment Form
A4: =IF(AL2=1,CY4,IF(AL2=2,CZ4,"Only")) -> TA2 | V4: =IF(tr=1,"TRUST","") | AJ4: ="Name: "& NM | BB4: Canadian Dollar | CY4: TA2 | CZ4: AF2
A5: Malta Tax & Customs Administration - Malta | F5: on behalf of a Company, a Body Corporate established by Statute, a Foundation or a Trust that made an election in terms of Article 27D(1) or a Trading or Commercial Undertaking operated by an Entity (Article 30) whether resident in Malta or not | BB5: Chinese Yuan
F6: =IF(dts<>3,"NO FIELD IN THIS PART CAN BE LEFT BLANK!","") | BB6: Czech Koruna
BB7: Danish Krona
F8: Ref. No. | L8: =AG8 | Q8: =efile | AI8: =AG8 | AJ8: reposition this formula in L8 | AP8: =IF(37-MOD(MID(L8,1,1)*27+MID(L8,2,1)*32+MID(L8,3,1)*16+MID(L8,4,1)*8+MID(L8,5,1)*4+MID(L8,6,1)*2+MID(L8,7,1)*1,37)<>VALUE(RIGHT(L8,2)),0,1) | BB8: Egyptian Pound | BE8: =IF(ISBLANK(L8),0,1)
BB9: Euro Currency
F10: Name | BB10: Hong Kong Dollar | BE10: =IF(ISBLANK(L10),0,1)
BB11: Hungarian Forint
F12: Year of Assessment | L12: 2025 | BB12: Indian Rupee | BE12: =IF(ISBLANK(ya),0,1)
BB13: Japanese Yen
F14: Basis Year | L14: =IF(ISBLANK(L12),"",ya-1) | BB14: Libyan Dinar | BE14: =SUM(BE8,BE10,BE12)
BB15: New Zealand Dollar
BB16: Norwegian Krona
BB17: Peruvian Nuevo Sol
F18: MAKE SURE THAT THE CORRECT DETAILS ARE ENTERED. DATA WILL BE COPIED TO ALL OTHER PAGES IN THE RETURN. | BB18: Polish Zloty
BB19: Swedish Krona
BB20: Swiss Franc
BB21: Turkish Lira
BB22: UK Sterling
F23: 1 | G23: In pursuance of the provisions of the Income Tax Acts you are hereby required to furnish me on this form with a true and correct declaration of the income of the company, body corporate established by statute, trading or commercial undertaking or a Trust, for the basis year indicated in this return including a self-assessment computation. | BB23: US Dollars
BB24: Mexican Pesos
BB25: South African Rand
F26: 2 | G26: All income of a resident company, body corporate, trading or commercial undertaking or a Trust, accruing in or derived from Malta or elsewhere, and whether received in Malta or not, during the accounting period stated in Part 1 below, must be stated. The word "company", wherever used in this return shall where applicable be construed as a reference to a fiscal unit. | BB26: New Romanian Leu
BB27: Bulgarian lev
BB28: Israeli New Shekel
F29: 3 | G29: Except as provided in Article 68 of the Income Tax Act (Cap. 123), all income of a non-resident company, body corporate or trading or commercial undertaking, accruing in or derived from Malta, whether received in Malta or not, during the accounting period stated in Part 1 below, must be included. | BB29: Qatari Riyal
BB30: Lebanese Pound
BB31: Thai Baht
F32: 4 | G32: Full details, attachments and documentation should be given relating to all matters required to be disclosed in this return. | BB32: Brazilian Real
F33: 5 | G33: A copy of the financial statements audited by a Certified Public Accountant and Auditor MUST be attached to this return. | BB33: Nigerian Naira
F35: 6 | G35: No section of this return is to be left blank. Where there is nothing to report, the word 'NONE' should be entered.
F37: 7 | G37: The term 'Income Tax Acts' used in this return has the meaning assigned to it in Article 2 of the Income Tax Act (Cap. 123) and, unless otherwise stated, the Articles quoted in this return refer to the Income Tax Act (Cap. 123).
F39: 8 | G39: This return is to be completed and forwarded so as to reach the MTCA by not later than the last day of the ninth month following that to which the accounts for the relative financial period are made or the thirty-first March of the relative year of assessment, whichever is the later.
F42: 9 | G42: A company carrying on banking business under the Banking Act or a company carrying on the business of insurance under the Insurance Business Act or a company which is owned and controlled, directly or indirectly, by such companies shall deliver to the Commissioner a paper copy of the audited financial statements within forty-eight hours of filing an electronic tax return.
G43: Malta Tax & Customs Administration
F46: Part 1 - Company Details (Principal Taxpayer's details required in the case of a fiscal unit)
F48: 1 | G48: Partnership Number | T48: 2 | V48: VAT Number | BJ48: =VLOOKUP(cur,er_ya1,3,FALSE) | BK48: =ROUND(BJ48,1)
F50: 3 | G50: Main Trading Activity
F52: 4 | G52: Address
G53: of registered office / place of control, management and administration
N55: Tel. Number | W55: Fax Number
F57: 5 | G57: Names and address/es of establishments from which business activities are carried on | M57: Name | T57: Address
M58: 1 | T58: 1
M59: 2 | T59: 2
M60: 3 | T60: 3
M61: 4 | T61: 4
F63: 6 | G63: Accounting Date
G64: If the basis year in respect of which this return is being made is a period other than the 1st January to 31st December, state the period covered, date and number (if available) of the permit issued by the MTCA
G65: FROM | M65: TO | S65: Permit Number | Y65: Date Issued
S66: 0 | AI66: =DATE(ya-3,1,1) | AJ66: =DATE(ya-1,12,31) | AK66: =DATE(ya-2,1,1) | AL66: =DATE(ya-1,12,31)
Y67: dd/mm/yyyy
F68: 7 | G68: Currency | Z68: =IF(dts<>3,"",IF(Z70<>"","","Choose Currency !"))
G69: State the Currency used in this return and the financial statements in accordance with the | Z69: Currency
G70: denomination of the company's share capital | Y70: =IF($Z$68="","",re) | Z70: Euro Currency

Sheet Index
B1: =_ref1 | E1: =_YA1 | G1: =E17 | K1: Prepared | T1: IS ATTACHMENT COMPLETE [Y or N] ?
R2: Yes | T2: INCOMPLETE !!
R3: No | T3: COMPLETE | CA3: ADAPT TO E-RETURN
T4: [Warning(s) present in TRA] | U4: [Warning(s) present in this page]
C6: The Malta Tax & Customs Administration uses the information provided, to process the tax return in accordance with the Income Tax Acts and subsidiary legislation. We may check information provided by you, or information about you provided by a third party or with other information held by us. We will not disclose information about the company to anyone outside the Malta Tax & Customs Administration unless permitted by law. The Malta Tax & Customs Administration treats your personal information in accordance with the Data Protection Act 2001 (Cap 440) to protect your privacy. Any queries may be addressed to The Data Controller, Malta Tax & Customs Administration, Floriana CMR 03. | G6: warn indicator | I6: name | J6: from | K6: to
C7: =IF(E7=0,0,IF(E7=1,1,IF(E7=100,"x"))) | D7: Balance Sheet | E7: =B_Sheet!G272 | G7: =B_Sheet!I3 | I7: B_Sheet | J7: 6 | K7: 261 | AJ7: value!
C8: =IF(E8=0,0,IF(E8=1,1,IF(E8=100,"x"))) -> 1 | D8: Income Statement | E8: =Income!P298 | I8: Income | J8: 6 | K8: 288 | AJ8: loss ??
B9: TRA 01 | C9: =IF(E9=0,0,IF(E9=1,1,IF(E9=100,"x"))) -> 0 | D9: ITA - Article 14(1)(h) - Scientific Research | E9: ='TRA1'!I60 | F9: =E9 | I9: TRA1 | J9: 231 | K9: 274
B10: TRA 02 | C10: =IF(E10=0,0,IF(E10=1,1,IF(E10=100,"x"))) -> 0 | D10: BPA - Regulation 13 - Incentive for job creation | E10: ='TRA2'!K55 | F10: =E10 | H10: TRA2 | I10: TRA2 | J10: 278 | K10: 300
B11: TRA 03 | C11: =IF(E11=0,0,IF(E11=1,1,IF(E11=100,"x"))) -> 0 | D11: Other statutory inflation of expenditure | E11: ='TRA3'!J35 | F11: =E11 | I11: TRA3 | J11: 304 | K11: 330
B12: TRA 04 | C12: =IF(E12=0,0,IF(E12=1,1,IF(E12=100,"x"))) -> 0 | D12: =IF(G12=1,BA12&warn,BA12) | E12: ='TRA4'!N106 | G12: ='TRA4'!R108 | I12: TRA4 | J12: 334 | K12: 368 | BA12: ITA - Balancing statement
B13: TRA 05 | C13: =IF(E13=0,0,IF(E13=1,1,IF(E13=100,"x"))) -> 1 | D13: =IF(G13=1,BA13&warn,BA13) -> ITA - Capital allowances | E13: ='TRA5'!S307 | G13: ='TRA5'!S309 | H13: TRA5 | I13: TRA5 | J13: 372 | K13: 491 | BA13: ITA - Capital allowances
B14: TRA 06 | C14: =IF(E14=0,0,IF(E14=1,1,IF(E14=100,"x"))) -> 0 | D14: =IF(G14=1,BA14&warn,BA14) -> BPA [Article 7] - Investment Allowance | E14: ='TRA6'!L48 | F14: =E14 | I14: TRA6 | J14: 495 | K14: 523 | BA14: BPA [Article 7] - Investment Allowance
B15: TRA 07 | C15: =IF(E15=0,0,IF(E15=1,1,IF(E15=100,"x"))) -> 0 | D15: =IF(G15=1,BA15&warn,BA15) -> BPA [Article 8] - Accelerated Depreciation | E15: ='TRA7'!P23 | F15: =E15 | G15: ='TRA7'!P25 | H15: TRA7 | I15: TRA7 | J15: 527 | K15: 534 | BA15: BPA [Article 8] - Accelerated Depreciation
B16: TRA 08 | C16: =IF(E16=0,0,IF(E16=1,1,IF(E16=100,"x"))) -> 0 | D16: =IF(G16=1,BA16&warn,BA16) -> ITA - Dividend(s) | E16: ='TRA8'!N105 | F16: ='TRA8'!C90 | G16: ='TRA8'!R3 | H16: TRA8 | I16: TRA8 | J16: 538 | K16: 570 | BA16: ITA - Dividend(s)
B17: TRA 09 | C17: =IF(E17=0,0,IF(E17=1,1,IF(E17=100,"x"))) -> 0 | D17: ITA - Interests | E17: =TRA9_14!I27 | F17: 10000 | I17: TRA9_14 | J17: =IF(AND(L17=0,SUM(M19:O19)>0),re,IF(L17=0,"",IF(L17<4,"All Details!",IF(N17>1,"Multiple Tax Accounts!","")))) | K17: 586 | BA17: ITA - Interest(s)
B18: TRA 10 | C18: =IF(E18=0,0,IF(E18=1,1,IF(E18=100,"x"))) -> 0 | D18: =IF(G18=1,BA18&warn,BA18) -> ITA - Discounts or premiums | E18: =TRA9_14!I57 | G18: =TRA9_14!J57 | H18: TRA10 | I18: TRA9_14 | J18: 587 | K18: 597 | BA18: ITA - Discounts or premiums
B19: TRA 11 | C19: =IF(E19=0,0,IF(E19=1,1,IF(E19=100,"x"))) -> 0 | D19: =IF(G19=1,BA19&warn,BA19) -> ITA - Income from Rent(s) | E19: =TRA9_14!I79 | G19: =TRA9_14!I80 | I19: TRA9_14 | J19: 598 | K19: 609 | BA19: ITA - Income from Rent(s)
B20: TRA 12 | C20: =IF(E20=0,0,IF(E20=1,1,IF(E20=100,"x"))) -> 0 | D20: =IF(G20=1,BA20&warn,BA20) -> ITA - Income from Ground Rent(s) | E20: =TRA9_14!I103 | G20: =TRA9_14!I104 | I20: TRA9_14 | J20: 610 | K20: 618 | BA20: ITA - Income from Ground Rent(s)
B21: TRA 13 | C21: =IF(E21=0,0,IF(E21=1,1,IF(E21=100,"x"))) -> 0 | D21: =IF(G21=1,BA21&warn,BA21) -> ITA - Income from Royalties, etc. | E21: =TRA9_14!I127 | G21: =TRA9_14!I128 | H21: TRA13 | I21: TRA9_14 | J21: 619 | K21: 628 | BA21: ITA - Income from Royalties, etc.
B22: TRA 14 | C22: =IF(E22=0,0,IF(E22=1,1,IF(E22=100,"x"))) -> 0 | D22: =IF(G22=1,BA22&warn,BA22) -> ITA - Other income | E22: =TRA9_14!I153 | G22: =TRA9_14!I154 | I22: TRA9_14 | J22: 629 | K22: 641 | BA22: ITA - Other income
B23: TRA 15 | C23: =IF(E23=0,0,IF(E23=1,1,IF(E23=100,"x"))) -> 0 | D23: ITA - Capital gain/(loss) - Summary | E23: ='TRA15'!K92 | I23: TRA15 | J23: 644 | K23: 651
B24: TRA 16 | C24: =IF(E24=0,0,IF(E24=1,1,IF(E24=100,"x"))) -> 0 | D24: ITA - Capital gain/(loss) - Immovable Property | E24: ='TRA16'!K1036 | I24: TRA16 | J24: 656 | K24: 748
B25: TRA 17 | C25: =IF(E25=0,0,IF(E25=1,1,IF(E25=100,"x"))) -> 0 | D25: ITA - Capital gain/(loss) - Securities | E25: ='TRA17'!Q680 | H25: TRA17 | I25: TRA17 | J25: 751 | K25: 777
B26: TRA 18 | C26: =IF(E26=0,0,IF(E26=1,1,IF(E26=100,"x"))) -> 0 | D26: =IF(G26=1,BA26&warn,BA26) | E26: ='TRA18'!L64 | F26: =E26 | G26: ='TRA18'!L73 | H26: TRA18 | I26: TRA18 | J26: 779 | K26: 805 | BA26: Total Exempt Income
B27: TRA 19 | C27: =IF(E27=0,0,IF(E27=1,1,IF(E27=100,"x"))) -> 0 | D27: =IF(G27=1,BA27&warn,BA27) | E27: ='TRA19'!R40 | G27: ='TRA19'!P36 | H27: TRA19 | I27: TRA19 | J27: 808 | K27: 827 | BA27: ITA - Loss SURRENDERED to group company/companies
B28: TRA 20 | C28: =IF(E28=0,0,IF(E28=1,1,IF(E28=100,"x"))) -> 0 | D28: =IF(G28=1,BA28&warn,BA28) | E28: ='TRA20'!R52 | G28: 0 | H28: TRA20 | I28: TRA20 | J28: 831 | K28: 853 | BA28: ITA - Group loss CLAIMED - current year
B29: TRA 21 | C29: =IF(E29=0,0,IF(E29=1,1,IF(E29=100,"x"))) -> 0 | D29: BPA - Article 5 | E29: 0
B30: TRA 22 | C30: =IF(E30=0,0,IF(E30=1,1,IF(E30=100,"x"))) -> 0 | D30: BPA - Article 5A | E30: 0
B31: TRA 23 | C31: =IF(E31=0,0,IF(E31=1,1,IF(E31=100,"x"))) -> 0 | D31: BPA - Article 6 | E31: =TRA23_24!N42 | F31: =E31 | H31: TRA23 | I31: TRA23_24 | J31: 857 | K31: 874
B32: TRA 24 | C32: =IF(E32=0,0,IF(E32=1,1,IF(E32=100,"x"))) -> 0 | D32: BPA - Article 24B | E32: =TRA23_24!O42 | F32: =E32 -> 0 | G32: 100 | H32: TRA24 | I32: TRA23_24 | J32: 857 | K32: 874
B33: TRA 25 | C33: =IF(E33=0,0,IF(E33=1,1,IF(E33=100,"x"))) -> 0 | D33: BPA - Regulation 4 (Reduced Rates of Income Tax) | BA33: BPA - Regulation 4 (Reduced Rates of Income Tax)
B34: TRA 26 | C34: =IF(E34=0,0,IF(E34=1,1,IF(E34=100,"x"))) -> 0 | D34: BPA - Regulation 6 (Value Added Incentive Scheme)
B35: TRA 27 | C35: =IF(E35=0,0,IF(E35=1,1,IF(E35=100,"x"))) -> 0 | D35: ITA - Article 56(20) (Double Taxation Treaties) | E35: =TRA27_28!M49 | F35: =E35 -> 0 | H35: TRA27 | I35: TRA27_28 | J35: 877 | K35: 909
B36: TRA 28 | C36: =IF(E36=0,0,IF(E36=1,1,IF(E36=100,"x"))) -> 0 | D36: BPA Article 15 (Double Taxation Treaties) | E36: =TRA27_28!M50 | F36: =E36 -> 0 | H36: TRA28 | I36: TRA27_28 | J36: 877 | K36: 909
B37: TRA 29 | C37: =IF(E37=0,0,IF(E37=1,1,IF(E37=100,"x"))) -> 0 | D37: =IF(G37=1,BA37&warn,BA37) | E37: ='TRA29'!J115 | F37: =E37 -> 0 | G37: 2000 | H37: TRA29 | I37: TRA29 | J37: 913 | K37: 920 | BA37: BPA - Regulation 5 (Investment Tax Credit)
B38: TRA 30 | C38: =IF(E38=0,0,IF(E38=1,1,IF(E38=100,"x"))) -> 0 | D38: =IF(G38=1,BA38&warn,BA38) | E38: ='TRA30'!P29 | G38: =IF('TRA30'!H25="",0,1) | H38: TRA30 | I38: TRA30 | J38: 925 | K38: 936 | BA38: Relief of double taxation
B39: TRA 31 | C39: =IF(E39=0,0,IF(E39=1,1,IF(E39=100,"x"))) -> 1 | D39: Tax paid | E39: ='TRA31'!K168 | H39: TRA31 | I39: TRA31 | J39: 940 | K39: 992
B40: TRA 32 | C40: =IF(E40=0,0,IF(E40=1,1,IF(E40=100,"x"))) -> 0 | D40: Investment Income subject to 15% Final Withholding Tax | E40: 0
B41: TRA 33 | C41: =IF(E41=0,0,IF(E41=1,1,IF(E41=100,"x"))) -> 0 | D41: Income subject to reduced rates of tax - Summary | E41: ='TRA33'!L32 | F41: =E41 | H41: TRA33 | I41: TRA33 | J41: 996 | K41: 1012
B42: TRA 34 | C42: =IF(E42=0,0,IF(E42=1,1,IF(E42=100,"x"))) -> 0 | D42: BPA - Regulation 14 - [Training Tax Credit] | E42: ='TRA34'!J54 | F42: =E42 | H42: TRA34 | I42: TRA34 | J42: 1016 | K42: 1036
B43: TRA 35 | C43: =IF(E43=0,0,IF(E43=1,1,IF(E43=100,"x"))) -> 0 | D43: Tax credits utilised during the year - Summary Statement | E43: ='TRA35'!O61 | F43: =E43 | H43: TRA35 | I43: TRA35 | J43: 1038 | K43: 1052
B44: TRA 36 | C44: =IF(E44=0,0,IF(E44=1,1,IF(E44=100,"x"))) -> 0 | D44: BPA - Regulations 31 to 37 - Conversion Scheme [Large Companies] | E44: ='TRA36'!J77 | F44: =E44 | H44: TRA36 | I44: TRA36 | J44: 1056 | K44: 1087
B45: TRA 37 | C45: =IF(E45=0,0,IF(E45=1,1,IF(E45=100,"x"))) -> 0 | D45: BPA - Regulations 38 - Conversion Scheme [SMEs] | E45: ='TRA37'!J41 | F45: =E45 | H45: TRA37 | I45: TRA37 | J45: 1091 | K45: 1110
B46: TRA 38 | C46: =IF(E46=0,0,IF(E46=1,1,IF(E46=100,"x"))) -> 0 | D46: ITA - Reinvestment Tax Credit
B47: TRA 39 | C47: =IF(E47=0,0,IF(E47=1,1,IF(E47=100,"x"))) -> 0 | D47: Tax guideline on bad debts | E47: ='TRA39'!K58 | G47: ='TRA39'!Q55 | H47: TRA39 | I47: TRA39 | J47: 1113 | K47: 1154
B48: TRA 40 | C48: =IF(E48=0,0,IF(E48=1,1,IF(E48=100,"x"))) -> 0 | D48: Written advice of tax professional | E48: ='TRA40'!H36 | H48: TRA40 | I48: TRA40 | J48: 1158 | K48: 1178
B49: TRA 41 | C49: =IF(E49=0,0,IF(E49=1,1,IF(E49=100,"x"))) -> 0 | D49: ITA/ITMA - LN 49 of 2005 - Sale of Agricultural Produce Rules | E49: ='TRA41'!N47 | F49: =E49 | H49: TRA41 | I49: TRA41 | J49: 1182 | K49: 1201
B50: TRA 42 | C50: =IF(E50=0,0,IF(E50=1,1,IF(E50=100,"x"))) -> 0 | D50: ITA - LN 330 of 2005 - Deductions and Tax Credits (R & D Expenditure) | E50: ='TRA42'!L61 | F50: 0 | H50: TRA42 | I50: TRA42 | J50: 1205 | K50: 1241
B51: TRA 43 | C51: =IF(E51=0,0,IF(E51=1,1,IF(E51=100,"x"))) -> 0 | D51: ITA - LN 330 of 2005 - Deductions and Tax Credit [R & D Relevant Qualifications]
B52: TRA 44 | C52: =IF(E52=0,0,IF(E52=1,1,IF(E52=100,"x"))) -> 0 | D52: ITA - LN 330 of 2005 - Tax Credit [R & D Social Security Contributions]
B53: TRA 45 | C53: =IF(E53=0,0,IF(E53=1,1,IF(E53=100,"x"))) -> 0 | D53: ITA - LN 331 of 2005 - Tax Credit [Back Office Operations]
B54: TRA 46 | C54: =IF(E54=0,0,IF(E54=1,1,IF(E54=100,"x"))) -> 0 | D54: ITA - LN 332 of 2005 - Tax Credit [Owners and Operators of Warehouses]
B55: TRA 47 | C55: =IF(E55=0,0,IF(E55=1,1,IF(E55=100,"x"))) -> 0 | D55: ITA - LN 333 of 2005 - Tax Credit [Electronic Commerce] | F55: =E55 | H55: TRA47 | I55: TRA47 | J55: 1245 | K55: 1276
B56: TRA 48 | C56: =IF(E56=0,0,IF(E56=1,1,IF(E56=100,"x"))) -> 0 | D56: ITA - LN 334 of 2005 - Reinvestment Tax Credit [New Scheme] | E56: 0 | F56: =E56 | H56: TRA48 | I56: TRA48 | J56: 1280 | K56: 1320
B57: TRA 49 | C57: =IF(E57=0,0,IF(E57=1,1,IF(E57=100,"x"))) -> 0 | D57: ITA - LN 335 of 2005 - Deductions and Tax Credit [Wages and Tuition Expenses] | E57: ='TRA49'!O186 | F57: =E57 | G57: ='TRA49'!O4 | H57: TRA49 | I57: TRA49 | J57: 1324 | K57: 1417 | BA57: ITA - LN 335 of 2005 - Deductions and Tax Credit [Wages and Tuition Expenses]
B58: TRA 50 | C58: =IF(E58=0,0,IF(E58=1,1,IF(E58=100,"x"))) -> 0 | D58: ITA - LN 335 of 2005 - Tax Credit [Social Security Contributions]
B59: TRA 51 | C59: =IF(E59=0,0,IF(E59=1,1,IF(E59=100,"x"))) -> 0 | D59: MFCA - LN 66 of 2006 - Tax Credit (Audiovisual Infrastructure) | F59: =E59 | H59: TRA51 | I59: TRA51 | J59: 1421 | K59: 1463
B60: TRA 52 | C60: =IF(E60=0,0,IF(E60=1,1,IF(E60=100,"x"))) -> 0 | D60: ITA - LN 266 of 2006 - Donations (National Heritage) Rules, 2006 | E60: ='TRA52'!J55 | H60: TRA52 | I60: TRA52 | J60: 1467 | K60: 1497
B61: TRA 53 | C61: =IF(E61=0,0,IF(E61=1,1,IF(E61=100,"x"))) -> 0 | D61: =IF(G61=1,BA61&warn,BA61) | E61: ='TRA53'!T107 | G61: =IF('TRA53'!AG104<>0,1,0) | H61: TRA53 | I61: TRA53 | J61: 1501 | K61: 1530 | BA61: ITA - Art 5A -Transfer of Immovable Property subject to FWT
B62: TRA 54 | C62: =IF(E62=0,0,IF(E62=1,1,IF(E62=100,"x"))) -> 0 | D62: =IF(G62=1,BA62&warn,BA62) | E62: ='TRA54'!J252 | F62: =E62 | G62: =IF('TRA54'!AC45=0,0,1) | H62: TRA54 | I62: TRA54 | J62: 1534 | K62: 1551 | BA62: ME Act - LN 68 of 2008 - Investment Aid Regulations
B63: TRA 55 | C63: =IF(E63=0,0,IF(E63=1,1,IF(E63=100,"x"))) -> 0 | D63: =IF(G63=1,BA63&warn,BA63) | E63: ='TRA55'!G18 | G63: =IF('TRA55'!AJ16=0,0,1) | H63: TRA55 | I63: TRA55 | J63: 1555 | K63: 1563 | BA63: Apportionment of Accommodation Income [LN 79 of 2008]
B64: TRA 56 | C64: =IF(E64=0,0,IF(E64=1,1,IF(E64=100,"x"))) -> 0 | D64: ITA - LN 159 of 2008 Donations (Sports and Culture) Rules, 2008 [Sports] | E64: ='TRA56'!M33 | G64: =IF('TRA56'!T31=0,0,1) | H64: TRA56 | I64: TRA56 | J64: 1567 | K64: 1584
B65: TRA 57 | C65: =IF(E65=0,0,IF(E65=1,1,IF(E65=100,"x"))) -> 0 | D65: ITA - LN 159 of 2008 Donations (Sports and Culture) Rules, 2008 [Culture] | E65: ='TRA57'!M33 | G65: =IF('TRA57'!T31=0,0,1) | H65: TRA57 | I65: TRA57 | J65: 1588 | K65: 1605
B66: TRA 58 | C66: =IF(E66=0,0,IF(E66=1,1,IF(E66=100,"x"))) -> 0 | D66: ITA - LN 159 of 2008 Donations (Sports and Culture) Rules, 2008 [Artiste] | E66: ='TRA58'!M33 | G66: =IF('TRA58'!T31=0,0,1) | H66: TRA58 | I66: TRA58 | J66: 1609 | K66: 1626
B67: TRA 59 | C67: =IF(E67=0,0,IF(E67=1,1,IF(E67=100,"x"))) -> 0 | D67: ITA - LN 93 OF 2007 - Deductions (Euro related expenditure) Rules, 2007 | BA67: ITA - LN 93 OF 2007 - Deductions (Euro related expenditure) Rules, 2007
B68: TRA 60 | C68: =IF(E68=0,0,IF(E68=1,1,IF(E68=100,"x"))) -> 0 | D68: =IF(G68=1,BA68&warn,BA68) | E68: ='TRA60'!L65 | G68: ='TRA60'!N7 | H68: TRA60 | I68: TRA60 | J68: 1628 | K68: 1652 | BA68: Profit adjustment [supplementing page 3 of the tax return]
B69: TRA 61 | C69: =IF(E69=0,0,IF(E69=1,1,IF(E69=100,"x"))) -> 1 | D69: Allocation to the Final Tax Account | E69: =TRA61_FTA!L54 | H69: TRA61 | I69: TRA61_FTA | J69: 1654 | K69: 1670 | BA69: Allocation to the Final Tax Account
B70: TRA 62 | C70: =IF(E70=0,0,IF(E70=1,1,IF(E70=100,"x"))) -> 1 | D70: =IF(G70=1,BA70&warn,BA70) | E70: =TRA62_IPA!I89 | G70: =IF(TRA62_IPA!H5=TRA62_IPA!BB5,1,0) | H70: TRA62 | I70: TRA62_IPA | J70: 2121 | K70: 2162 | BA70: Allocation to the Immovable Property Account
B71: TRA 62A | C71: =IF(E71=0,0,IF(E71=1,1,IF(E71=100,"x"))) | D71: =IF(G71=1,BA71&warn,BA71) | E71: =TRA62A_IPA!F92 | H71: TRA62A | I71: TRA62A_IPA | J71: 2165 | K71: 2200 | BA71: Second Allocation to the Immovable Property Account
B72: TRA 63 | C72: =IF(E72=0,0,IF(E72=1,1,IF(E72=100,"x"))) -> 1 | D72: =IF(G72=1,BA72&warn,BA72) | E72: =TRA63_MTA_FIA!R57 | G72: =IF(TRA63_MTA_FIA!BA54=0,0,1) | H72: TRA63 | I72: TRA63_MTA_FIA | J72: 1709 | K72: 1734 | BA72: Allocation to the Maltese Taxed Account AND Foreign Income Account
B73: TRA 65 | C73: =IF(E73=0,0,IF(E73=1,1,IF(E73=100,"x"))) -> 0 | D73: =IF(G73=1,BA73&warn,BA73) | E73: ='TRA65'!L59 | F73: =E73 | G73: =IF('TRA65'!M58>0,1,0) | H73: TRA65 | I73: TRA65 | J73: 1737 | K73: 1758 | BA73: ME Act - Assistance for R&D and Innovation Regulations, 2009
B74: TRA 66 | C74: =IF(E74=0,0,IF(E74=1,1,IF(E74=100,"x"))) -> 0 | D74: ITA - LN 171 of 2010 - Deductions and Tax Credits (Pharmacy of your choice) Rules, 2010 | E74: ='TRA66'!N67 | G74: ='TRA66'!S11 | H74: TRA66 | I74: TRA66 | J74: 1762 | K74: 1776
B75: TRA 67 | C75: =IF(E75=0,0,IF(E75=1,1,IF(E75=100,"x"))) -> 0 | D75: ITA - Exemption on Royalties derived from Patents | E75: ='TRA67'!G32 | H75: TRA67 | I75: TRA67 | J75: 1779 | K75: 1788
B76: TRA 68 | C76: =IF(E76=0,0,IF(E76=1,1,IF(E76=100,"x"))) -> 0 | D76: ITA - LN 187 of 2010 - Donations (University research, Innovation & Development) Rules, 2010 | E76: ='TRA68'!K32 | H76: TRA68 | I76: TRA68 | J76: 1790 | K76: 1803
B77: TRA 69 | C77: =IF(E77=0,0,IF(E77=1,1,IF(E77=100,"x"))) -> 0 | D77: ITA - LN 430 of 2010 - Deduction (Childcare Facilities at the Workplace) Rules, 2010 | E77: ='TRA69'!J46 | H77: TRA69 | I77: TRA69 | J77: 1806 | K77: 1817
B78: TRA 70 | C78: =IF(E78=0,0,IF(E78=1,1,IF(E78=100,"x"))) -> 0 | D78: ITA - LN 428 of 2010 - Deduction (Workplace Accessibility) Rules, 2010 | E78: ='TRA70'!J50 | H78: TRA70 | I78: TRA70 | J78: 1820 | K78: 1834
B79: TRA 71 | C79: =IF(E79=0,0,IF(E79=1,1,IF(E79=100,"x"))) -> 0 | D79: ME Act - LN 107 of 2010 - Tax Credit for Micro Enterprises | E79: 0 | H79: TRA71 | I79: TRA71 | J79: 1837 | K79: 1851
B80: TRA 72 | C80: =IF(E80=0,0,IF(E80=1,1,IF(E80=100,"x"))) -> 0 | D80: ME Act - LN 488 of 2010 - Tax Credit for carrying out a creative activity | E80: ='TRA72'!G39 | G80: ='TRA72'!H19 | H80: TRA72 | I80: TRA72 | J80: 2067 | K80: 2079 | BA80: ME Act - LN 488 of 2010 - Tax Credit for carrying out a creative activity
B81: TRA 73 | C81: =IF(E81=0,0,IF(E81=1,1,IF(E81=100,"x"))) -> 0 | D81: ITA - LN 13 of 2011 - Deductions (Electric Vehicles) Rules, 2011 | E81: ='TRA73'!K124 | H81: TRA73 | I81: TRA73 | J81: 2082 | K81: 2096
B82: TRA 74 | C82: =IF(E82=0,0,IF(E82=1,1,IF(E82=100,"x"))) -> 0 | D82: ITA - LN 324 of 2011 - Securitisation Transactions (Deductions) Rules, 2011 | E82: ='TRA74'!K38 | H82: TRA74 | I82: TRA74 | J82: 2099 | K82: 2118
B83: TRA 75 | C83: =IF(E83=0,0,IF(E83=1,1,IF(E83=100,"x"))) -> 0 | D83: ITA - Art 31A - Taxation of rental income from Housing Authority | E83: ='TRA75'!I47 | H83: TRA75 | I83: TRA75 | J83: 2213 | K83: 2225
B84: TRA 76 | C84: =IF(E84=0,0,IF(E84=1,1,IF(E84=100,"x"))) -> 0 | D84: ITA - Art 31B - Taxation of rental income on Housing Authority subsidised rent | E84: ='TRA76'!I47 | H84: TRA76 | I84: TRA76 | J84: 2239 | K84: 2251
B85: TRA 77 | C85: =IF(E85=0,0,IF(E85=1,1,IF(E85=100,"x"))) -> 0 | D85: ITA - Art 31C - Rental income from restored property | E85: ='TRA77'!Q51 | H85: TRA77 | I85: TRA77 | J85: 2261 | K85: 2272
B86: TRA 78 | C86: =IF(E86=0,0,IF(E86=1,1,IF(E86=100,"x"))) -> 0 | D86: ME Act - Enterprise Support Incentives Regulations, 2008 - QUALITY + (Deductions) | E86: ='TRA78'!I38 | H86: TRA78 | I86: TRA78 | J86: 2290 | K86: 2297
B87: TRA 79 | C87: =IF(E87=0,0,IF(E87=1,1,IF(E87=100,"x"))) -> 0 | D87: ITA - LN 23 of 2013 - Donations (Creativity Trust) Rules, 2013 | E87: ='TRA79'!L30 | H87: TRA79 | I87: TRA79 | J87: 2310 | K87: 2320
B88: TRA 80 | C88: =IF(E88=0,0,IF(E88=1,1,IF(E88=100,"x"))) -> 0 | D88: ME Act - LN 456 of 2012 (Rule 14) Tax Credit for restoration works on protected buildings ... | E88: ='TRA80'!L43 | H88: TRA80 | I88: TRA80 | J88: 2330 | K88: 2344
B89: TRA 81 | C89: =IF(E89=0,0,IF(E89=1,1,IF(E89=100,"x"))) -> 0 | D89: ME Act - LN 456 of 2012 (Rule 15) - Tax Credit for digital applications development | E89: 0 | H89: TRA81 | I89: TRA81 | J89: 2360 | K89: 2369
B90: TRA 82 | C90: =IF(E90=0,0,IF(E90=1,1,IF(E90=100,"x"))) -> 0 | D90: Wages Reconciliation | E90: ='TRA82'!L791 | H90: TRA82 | I90: TRA82 | J90: 2380 | K90: 2427
B91: TRA 83 | C91: =IF(E91=0,0,IF(E91=1,1,IF(E91=100,"x"))) -> 0 | D91: ITA - Article 31D - Rental income subject to Final Withholding Tax | E91: ='TRA83'!M99
B92: TRA 84 | C92: =IF(E92=0,0,IF(E92=1,1,IF(E92=100,"x"))) -> 0 | D92: ITA - LN 179 of 2014 - Deduction (Apprentices and Work Placements) Rules, 2014 | E92: ='TRA84'!L69
B93: TRA 85 | C93: =IF(E93=0,0,IF(E93=1,1,IF(E93=100,"x"))) -> 0 | D93: ITA - LN 180 of 2014 - Deduction (Mature Workers) Rules, 2014 | E93: ='TRA85'!P70
B94: TRA 86 | C94: =IF(E94=0,0,IF(E94=1,1,IF(E94=100,"x"))) -> 0 | D94: ME Act - Investment Aid Regulations 2014 - 2020 | E94: ='TRA86'!P436
B95: TRA 87 | C95: =IF(E95=0,0,IF(E95=1,1,IF(E95=100,"x"))) -> 0 | D95: SL 123.162 - Donations (Community Chest Fund) Rules | E95: ='TRA87'!K27
B96: TRA 88 | C96: =IF(E96=0,0,IF(E96=1,1,IF(E96=100,"x"))) -> 0 | D96: ME Act - Enterprise Support Incentives Regulations, 2008 - LN 187 of 2014 - Micro Invest 2014 | E96: ='TRA88'!M209
B97: TRA 89 | C97: =IF(E97=0,0,IF(E97=1,1,IF(E97=100,"x"))) -> 0 | D97: ITA - Article 27G - Transfers of property by a company that has issued debt securities to the public | E97: ='TRA89'!S88
B98: TRA 90 | C98: =IF(E98=0,0,IF(E98=1,1,IF(E98=100,"x"))) -> 0 | D98: ME Act - LN 118 of 2015 (Rule 17) - Tax Credit for Qualifying Certifications | E98: ='TRA90'!H45
B99: TRA 91 | C99: =IF(E99=0,0,IF(E99=1,1,IF(E99=100,"x"))) -> 0 | D99: ME Act - LN 38 of 2015 - Assistance for Research and Development and Innovation (Amendments) Rules, 2015 | E99: ='TRA91'!M47
B100: TRA 92 | C100: =IF(E100=0,0,IF(E100=1,1,IF(E100=100,"x"))) -> 0 | D100: ME Act - LN178 of 2016 - Assistance for Knowledge Transfer Regulations, 2016 | E100: ='TRA92'!M48
B101: TRA 93 | C101: =IF(E101=0,0,IF(E101=1,1,IF(E101=100,"x"))) -> 0 | D101: ME Act - LN179 of 2016 - Investment Aid for High Efficiency Cogeneration Regulations, 2016 | E101: ='TRA93'!L44
...

Sheet B_Sheet
A1: a | B1: Back to Index | BA1: =IF('p1'!M66="",DATE(ya-1,12,31),'p1'!M66)
A2: 1 | B2: =_ref1 | E2: =_YA1 | AY2: =IF(AZ2<>BA2,1,0) | AZ2: =C4 | BA2: =DAY(BA1)
A3: 0 | C3: =IF(AND(C4="",D4=""),"",IF(AY4<>0,"Accounting year end does not match MTCA records! Please Rectify.","")) | I3: =IF(C3="",0,1) | AY3: =IF(AZ3<>BA3,1,0) | AZ3: =VLOOKUP(D4,AM6:AN17,2,FALSE) | BA3: =MONTH(BA1)
A4: 1 | B4: Balance Sheet as at | C4: 31 | D4: December | E4: =ya-1 | F4: =IF(ISBLANK(C4),H4,IF(ISBLANK(D4),H4,"")) | G4: =IF(F4="",0,1) | H4: Full date! | AY4: =SUM(AY2:AY3)
A5: 0 | B5: Item Description | C5: Code | E5: Dr ( + ) or Cr ( - )
A6: =COUNT(E6) | B6: Intangible assets | C6: 1000 | F6: =IF(E6<0,"Negative amount!","") | H6: =IF(F6="",0,1) | Z6: =IF(A6=1,SUM($A$6:$A6),0) | AL6: 1 | AM6: January | AN6: 1
A7: =COUNT(E7) | B7: Accumulated amortisation of intangible assets | C7: 1001 | F7: =IF(E7>0,"Positive amount!","") | H7: =IF(F7="",0,1) -> 0 | Z7: =IF(A7=1,SUM($A$6:$A7),0) | AL7: 2 | AM7: February | AN7: 2
A8: =COUNT(E8) -> 0 | B8: Goodwill | C8: 1002 | F8: =IF(E8<0,"Negative amount!","") | H8: =IF(F8="",0,1) -> 0 | Z8: =IF(A8=1,SUM($A$6:$A8),0) | AL8: 3 | AM8: March | AN8: 3
A9: =COUNT(E9) -> 0 | B9: Accumulated amortisation of goodwill | C9: 1003 | F9: =IF(E9>0,"Positive amount!","") | H9: =IF(F9="",0,1) -> 0 | Z9: =IF(A9=1,SUM($A$6:$A9),0) | AL9: 4 | AM9: April | AN9: 4
A10: =COUNT(E10) -> 0 | B10: Formation expenses | C10: 1004 | F10: =IF(E10<0,"Negative amount!","") | H10: =IF(F10="",0,1) -> 0 | Z10: =IF(A10=1,SUM($A$6:$A10),0) | AL10: 5 | AM10: May | AN10: 5
A11: =COUNT(E11) -> 0 | B11: Accumulated amortisation of formation expenses | C11: 1005 | F11: =IF(E11>0,"Positive amount!","") | H11: =IF(F11="",0,1) -> 0 | Z11: =IF(A11=1,SUM($A$6:$A11),0) | AL11: 6 | AM11: June | AN11: 6
A12: =COUNT(E12) -> 1 | B12: Royalties, trademarks, patents, rights, etc. | C12: 1006 | F12: =IF(E12<0,"Negative amount!","") | H12: =IF(F12="",0,1) -> 0 | Z12: =IF(A12=1,SUM($A$6:$A12),0) | AL12: 7 | AM12: July | AN12: 7
A13: =COUNT(E13) -> 1 | B13: Accumulated amortisation of royalties, trademarks, patents | C13: 1007 | F13: =IF(E13>0,"Positive amount!","") | H13: =IF(F13="",0,1) -> 0 | Z13: =IF(A13=1,SUM($A$6:$A13),0) | AL13: 8 | AM13: August | AN13: 8
A14: =COUNT(E14) -> 0 | B14: Research and development (capitalised) | C14: 1008 | F14: =IF(E14<0,"Negative amount!","") | H14: =IF(F14="",0,1) -> 0 | Z14: =IF(A14=1,SUM($A$6:$A14),0) | AL14: 9 | AM14: September | AN14: 9
A15: =COUNT(E15) -> 0 | B15: Accumulated amortisation of research and development | C15: 1009 | F15: =IF(E15>0,"Positive amount!","") | H15: =IF(F15="",0,1) -> 0 | Z15: =IF(A15=1,SUM($A$6:$A15),0) | AL15: 10 | AM15: October | AN15: 10
A16: 1 | B16: Total Intangible assets | C16: 1198 | E16: =SUM(E6,E8,E10,E12,E14) | Y16: 1 | Z16: =IF(A16=1,SUM($A$6:$A16),0) | AL16: 11 | AM16: November | AN16: 11 | CA16: 1
A17: 1 | B17: Total accumulated amortisation of intangible assets | C17: 1199 | E17: =SUM(E7,E9,E11,E13,E15) | Y17: 1 | Z17: =IF(A17=1,SUM($A$6:$A17),0) | AL17: 12 | AM17: December | AN17: 12 | CA17: 1
A18: =COUNT(E18) -> 0 | B18: Land and Buildings | C18: 1200 | F18: =IF(E18<0,"Negative amount!","") | H18: =IF(F18="",0,1) | Z18: =IF(A18=1,SUM($A$6:$A18),0) | AL18: 13
A19: =COUNT(E19) -> 0 | B19: Accumulated depreciation of land and buildings | C19: 1201 | F19: =IF(E19>0,"Positive amount!","") | H19: =IF(F19="",0,1) -> 0 | Z19: =IF(A19=1,SUM($A$6:$A19),0) | AL19: 14
A20: =COUNT(E20) -> 0 | B20: Land improvements | C20: 1202 | F20: =IF(E20<0,"Negative amount!","") | H20: =IF(F20="",0,1) -> 0 | Z20: =IF(A20=1,SUM($A$6:$A20),0) | AL20: 15
A21: =COUNT(E21) -> 0 | B21: Accumulated depreciation of land improvements | C21: 1203 | F21: =IF(E21>0,"Positive amount!","") | H21: =IF(F21="",0,1) -> 0 | Z21: =IF(A21=1,SUM($A$6:$A21),0) | AL21: 16
A22: =COUNT(E22) -> 0 | B22: Industrial Buildings and structures | C22: 1204 | F22: =IF(E22<0,"Negative amount!","") | H22: =IF(F22="",0,1) -> 0 | Z22: =IF(A22=1,SUM($A$6:$A22),0) | AL22: 17
A23: =COUNT(E23) -> 0 | B23: Accumulated depreciation of industrial buildings and structures | C23: 1205 | F23: =IF(E23>0,"Positive amount!","") | H23: =IF(F23="",0,1) -> 0 | Z23: =IF(A23=1,SUM($A$6:$A23),0) | AL23: 18
A24: =COUNT(E24) -> 0 | B24: Non-industrial buildings | C24: 1206 | F24: =IF(E24<0,"Negative amount!","") | H24: =IF(F24="",0,1) -> 0 | Z24: =IF(A24=1,SUM($A$6:$A24),0) | AL24: 19
A25: =COUNT(E25) -> 0 | B25: Accumulated depreciation of non-industrial buildings | C25: 1207 | F25: =IF(E25>0,"Positive amount!","") | H25: =IF(F25="",0,1) -> 0 | Z25: =IF(A25=1,SUM($A$6:$A25),0) | AL25: 20
A26: =COUNT(E26) -> 0 | B26: Parking areas | C26: 1208 | F26: =IF(E26<0,"Negative amount!","") | H26: =IF(F26="",0,1) -> 0 | Z26: =IF(A26=1,SUM($A$6:$A26),0) | AL26: 21
A27: =COUNT(E27) -> 0 | B27: Accumulated depreciation of parking areas | C27: 1209 | F27: =IF(E27>0,"Positive amount!","") | H27: =IF(F27="",0,1) -> 0 | Z27: =IF(A27=1,SUM($A$6:$A27),0) | AL27: 22
A28: =COUNT(E28) -> 0 | B28: Buildings under construction | C28: 1210 | F28: =IF(E28<0,"Negative amount!","") | H28: =IF(F28="",0,1) -> 0 | Z28: =IF(A28=1,SUM($A$6:$A28),0) | AL28: 23
A29: =COUNT(E29) -> 0 | B29: Wasting assets | C29: 1300 | F29: =IF(E29<0,"Negative amount!","") | H29: =IF(F29="",0,1) -> 0 | Z29: =IF(A29=1,SUM($A$6:$A29),0) | AL29: 24
A30: =COUNT(E30) -> 0 | B30: Accumulated depreciation of wasting assets | C30: 1301 | F30: =IF(E30>0,"Positive amount!","") | H30: =IF(F30="",0,1) -> 0 | Z30: =IF(A30=1,SUM($A$6:$A30),0) | AL30: 25
A31: =COUNT(E31) -> 0 | B31: Petroleum and natural gas properties | C31: 1302 | F31: =IF(E31<0,"Negative amount!","") | H31: =IF(F31="",0,1) -> 0 | Z31: =IF(A31=1,SUM($A$6:$A31),0) | AL31: 26
A32: =COUNT(E32) -> 0 | B32: Accumulated depreciation of petroleum and natural gas properties | C32: 1303 | F32: =IF(E32>0,"Positive amount!","") | H32: =IF(F32="",0,1) -> 0 | Z32: =IF(A32=1,SUM($A$6:$A32),0) | AL32: 27
A33: =COUNT(E33) -> 0 | B33: Deferred exploration and development charges | C33: 1304 | F33: =IF(E33<0,"Negative amount!","") | H33: =IF(F33="",0,1) -> 0 | Z33: =IF(A33=1,SUM($A$6:$A33),0) | AL33: 28
A34: =COUNT(E34) -> 0 | B34: Accumulated depreciation of deferred exploration and development charges | C34: 1305 | F34: =IF(E34>0,"Positive amount!","") | H34: =IF(F34="",0,1) -> 0 | Z34: =IF(A34=1,SUM($A$6:$A34),0) | AL34: 29
A35: =COUNT(E35) -> 0 | B35: Quarries | C35: 1306 | F35: =IF(E35<0,"Negative amount!","") | H35: =IF(F35="",0,1) -> 0 | Z35: =IF(A35=1,SUM($A$6:$A35),0) | AL35: 30
A36: =COUNT(E36) -> 0 | B36: Accumulated depreciation of quarries | C36: 1307 | F36: =IF(E36>0,"Positive amount!","") | H36: =IF(F36="",0,1) -> 0 | Z36: =IF(A36=1,SUM($A$6:$A36),0) | AL36: 31
A37: =COUNT(E37) -> 0 | B37: Plant and machinery | C37: 1350 | F37: =IF(E37<0,"Negative amount!","") | H37: =IF(F37="",0,1) -> 0 | Z37: =IF(A37=1,SUM($A$6:$A37),0)
A38: =COUNT(E38) -> 0 | B38: Accumulated depreciation of plant and machinery | C38: 1351 | F38: =IF(E38>0,"Positive amount!","") | H38: =IF(F38="",0,1) -> 0 | Z38: =IF(A38=1,SUM($A$6:$A38),0)
A39: =COUNT(E39) -> 0 | B39: Motor vehicles | C39: 1352 | F39: =IF(E39<0,"Negative amount!","") | H39: =IF(F39="",0,1) -> 0 | Z39: =IF(A39=1,SUM($A$6:$A39),0)
A40: =COUNT(E40) -> 0 | B40: Accumulated depreciation of motor vehicles | C40: 1353 | F40: =IF(E40>0,"Positive amount!","") | H40: =IF(F40="",0,1) -> 0 | Z40: =IF(A40=1,SUM($A$6:$A40),0)
A41: =COUNT(E41) -> 0 | B41: Construction and excavating equipment | C41: 1354 | F41: =IF(E41<0,"Negative amount!","") | H41: =IF(F41="",0,1) -> 0 | Z41: =IF(A41=1,SUM($A$6:$A41),0)
A42: =COUNT(E42) -> 0 | B42: Accumulated depreciation of construction and excavating equipment | C42: 1355 | F42: =IF(E42>0,"Positive amount!","") | H42: =IF(F42="",0,1) -> 0 | Z42: =IF(A42=1,SUM($A$6:$A42),0)
A43: =COUNT(E43) -> 0 | B43: Production machinery and equipment | C43: 1356 | F43: =IF(E43<0,"Negative amount!","") | H43: =IF(F43="",0,1) -> 0 | Z43: =IF(A43=1,SUM($A$6:$A43),0)
A44: =COUNT(E44) -> 0 | B44: Accumulated depreciation of production machinery and equipment | C44: 1357 | F44: =IF(E44>0,"Positive amount!","") | H44: =IF(F44="",0,1) -> 0 | Z44: =IF(A44=1,SUM($A$6:$A44),0)
A45: =COUNT(E45) -> 0 | B45: Tools and dies | C45: 1358 | F45: =IF(E45<0,"Negative amount!","") | H45: =IF(F45="",0,1) -> 0 | Z45: =IF(A45=1,SUM($A$6:$A45),0)
A46: =COUNT(E46) -> 0 | B46: Accumulated depreciation of tools and dies | C46: 1359 | F46: =IF(E46>0,"Positive amount!","") | H46: =IF(F46="",0,1) -> 0 | Z46: =IF(A46=1,SUM($A$6:$A46),0)
A47: =COUNT(E47) -> 0 | B47: Catering Equipment | C47: 1360 | F47: =IF(E47<0,"Negative amount!","") | H47: =IF(F47="",0,1) -> 0 | Z47: =IF(A47=1,SUM($A$6:$A47),0)
A48: =COUNT(E48) -> 0 | B48: Accumulated depreciation of catering equipment | C48: 1361 | F48: =IF(E48>0,"Positive amount!","") | H48: =IF(F48="",0,1) -> 0 | Z48: =IF(A48=1,SUM($A$6:$A48),0)
A49: =COUNT(E49) -> 0 | B49: Cable Infrastructure | C49: 1362 | F49: =IF(E49<0,"Negative amount!","") | H49: =IF(F49="",0,1) -> 0 | Z49: =IF(A49=1,SUM($A$6:$A49),0)
A50: =COUNT(E50) -> 0 | B50: Accumulated depreciation of Cable Infrastructure | C50: 1363 | F50: =IF(E50>0,"Positive amount!","") | H50: =IF(F50="",0,1) | Z50: =IF(A50=1,SUM($A$6:$A50),0)
A51: =COUNT(E51) -> 0 | B51: Pipeline Infrastructure | C51: 1364 | F51: =IF(E51<0,"Negative amount!","") | H51: =IF(F51="",0,1) -> 0 | Z51: =IF(A51=1,SUM($A$6:$A51),0)
A52: =COUNT(E52) -> 0 | B52: Accumulated depreciation of Pipeline Infrastructure | C52: 1365 | F52: =IF(E52>0,"Positive amount!","") | H52: =IF(F52="",0,1) -> 0 | Z52: =IF(A52=1,SUM($A$6:$A52),0)
A53: =COUNT(E53) -> 0 | B53: Communication and Broadcasting Equipment | C53: 1366 | F53: =IF(E53<0,"Negative amount!","") | H53: =IF(F53="",0,1) -> 0 | Z53: =IF(A53=1,SUM($A$6:$A53),0)
A54: =COUNT(E54) -> 0 | B54: Accumulated depreciation of Communication and Broadcasting Equipment | C54: 1367 | F54: =IF(E54>0,"Positive amount!","") | H54: =IF(F54="",0,1) -> 0 | Z54: =IF(A54=1,SUM($A$6:$A54),0)
A55: =COUNT(E55) -> 0 | B55: Medical Equipment | C55: 1368 | F55: =IF(E55<0,"Negative amount!","") | H55: =IF(F55="",0,1) -> 0 | Z55: =IF(A55=1,SUM($A$6:$A55),0)
A56: =COUNT(E56) -> 0 | B56: Accumulated depreciation of Medical Equipment | C56: 1369 | F56: =IF(E56>0,"Positive amount!","") | H56: =IF(F56="",0,1) -> 0 | Z56: =IF(A56=1,SUM($A$6:$A56),0)
A57: =COUNT(E57) -> 0 | B57: Lifts and Escalators | C57: 1370 | F57: =IF(E57<0,"Negative amount!","") | H57: =IF(F57="",0,1) -> 0 | Z57: =IF(A57=1,SUM($A$6:$A57),0)
A58: =COUNT(E58) -> 0 | B58: Accumulated depreciation of Lifts and Escalators | C58: 1371 | F58: =IF(E58>0,"Positive amount!","") | H58: =IF(F58="",0,1) -> 0 | Z58: =IF(A58=1,SUM($A$6:$A58),0)
A59: =COUNT(E59) -> 0 | B59: Air-conditioners | C59: 1372 | F59: =IF(E59<0,"Negative amount!","") | H59: =IF(F59="",0,1) -> 0 | Z59: =IF(A59=1,SUM($A$6:$A59),0)
A60: =COUNT(E60) -> 0 | B60: Accumulated depreciation of Air-conditioners | C60: 1373 | F60: =IF(E60>0,"Positive amount!","") | H60: =IF(F60="",0,1) -> 0 | Z60: =IF(A60=1,SUM($A$6:$A60),0)
A61: =COUNT(E61) -> 0 | B61: Equipment mainly designed or used for the production of water or electricity | C61: 1374 | F61: =IF(E61<0,"Negative amount!","") | H61: =IF(F61="",0,1) -> 0 | Z61: =IF(A61=1,SUM($A$6:$A61),0)
A62: =COUNT(E62) -> 0 | B62: Accumulated depreciation of equipment for the production of water or electricity | C62: 1375 | F62: =IF(E62>0,"Positive amount!","") | H62: =IF(F62="",0,1) -> 0 | Z62: =IF(A62=1,SUM($A$6:$A62),0)
A63: =COUNT(E63) -> 0 | B63: Electrical & Plumbing Installations and Sanitary Fittings | C63: 1376 | F63: =IF(E63<0,"Negative amount!","") | H63: =IF(F63="",0,1) -> 0 | Z63: =IF(A63=1,SUM($A$6:$A63),0)
A64: =COUNT(E64) -> 0 | B64: Accumulated depreciation of Electrical and Plumbing Installations and sanitary fittings | C64: 1377 | F64: =IF(E64>0,"Positive amount!","") | H64: =IF(F64="",0,1) -> 0 | Z64: =IF(A64=1,SUM($A$6:$A64),0)
A65: =COUNT(E65) -> 0 | B65: Exploration equipment | C65: 1378 | F65: =IF(E65<0,"Negative amount!","") | H65: =IF(F65="",0,1) -> 0 | Z65: =IF(A65=1,SUM($A$6:$A65),0)
A66: =COUNT(E66) -> 0 | B66: Accumulated depreciation of exploration equipment | C66: 1379 | F66: =IF(E66>0,"Positive amount!","") | G66: 45078 | H66: =IF(F66="",0,1) -> 0 | M66: 45443 | Z66: =IF(A66=1,SUM($A$6:$A66),0)
A67: =COUNT(E67) -> 0 | B67: Ships and vessels | C67: 1380 | F67: =IF(E67<0,"Negative amount!","") | H67: =IF(F67="",0,1) -> 0 | Z67: =IF(A67=1,SUM($A$6:$A67),0)
A68: =COUNT(E68) -> 0 | B68: Accumulated depreciation of ships and vessels | C68: 1381 | F68: =IF(E68>0,"Positive amount!","") | H68: =IF(F68="",0,1) -> 0 | Z68: =IF(A68=1,SUM($A$6:$A68),0)
A69: =COUNT(E69) -> 0 | B69: Shipping equipment | C69: 1382 | F69: =IF(E69<0,"Negative amount!","") | H69: =IF(F69="",0,1) -> 0 | Z69: =IF(A69=1,SUM($A$6:$A69),0)
A70: =COUNT(E70) -> 0 | B70: Accumulated depreciation of shipping equipment | C70: 1383 | F70: =IF(E70>0,"Positive amount!","") | H70: =IF(F70="",0,1) -> 0 | Z70: =IF(A70=1,SUM($A$6:$A70),0)
A71: =COUNT(E71) | B71: Aircraft | C71: 1384 | F71: =IF(E71<0,"Negative amount!","") | H71: =IF(F71="",0,1) -> 0 | Z71: =IF(A71=1,SUM($A$6:$A71),0)
A72: =COUNT(E72) -> 0 | B72: Accumulated depreciation of aircraft | C72: 1385 | F72: =IF(E72>0,"Positive amount!","") | H72: =IF(F72="",0,1) -> 0 | Z72: =IF(A72=1,SUM($A$6:$A72),0)
A73: =COUNT(E73) -> 0 | B73: Machinery and equipment under construction | C73: 1386 | F73: =IF(E73<0,"Negative amount!","") | H73: =IF(F73="",0,1) -> 0 | Z73: =IF(A73=1,SUM($A$6:$A73),0)
A74: =COUNT(E74) -> 0 | B74: Commercial vehicles | C74: 1387 | F74: =IF(E74<0,"Negative amount!","") | H74: =IF(F74="",0,1) -> 0 | Z74: =IF(A74=1,SUM($A$6:$A74),0)
A75: =COUNT(E75) -> 0 | B75: Accumulated depreciation of commercial vehicles | C75: 1388 | F75: =IF(E75>0,"Positive amount!","") | H75: =IF(F75="",0,1) -> 0 | Z75: =IF(A75=1,SUM($A$6:$A75),0)
A76: =COUNT(E76) -> 1 | B76: Computers and Electronic Equipment | C76: 1389 | E76: =7575+1385 | F76: =IF(E76<0,"Negative amount!","") | H76: =IF(F76="",0,1) -> 0 | Z76: =IF(A76=1,SUM($A$6:$A76),0)
A77: =COUNT(E77) -> 1 | B77: Accumulated depreciation of computers and electronic equipment | C77: 1390 | E77: =-4484-1385 | F77: =IF(E77>0,"Positive amount!","") | H77: =IF(F77="",0,1) -> 0 | Z77: =IF(A77=1,SUM($A$6:$A77),0)
A78: =COUNT(E78) -> 1 | B78: Computer software | C78: 1391 | F78: =IF(E78<0,"Negative amount!","") | H78: =IF(F78="",0,1) -> 0 | Z78: =IF(A78=1,SUM($A$6:$A78),0)
A79: =COUNT(E79) -> 1 | B79: Accumulated depreciation of computer software | C79: 1392 | F79: =IF(E79>0,"Positive amount!","") | H79: =IF(F79="",0,1) -> 0 | Z79: =IF(A79=1,SUM($A$6:$A79),0)
A80: =COUNT(E80) -> 1 | B80: Furniture, Fixtures, Fittings and Soft Furnishings | C80: 1393 | F80: =IF(E80<0,"Negative amount!","") | H80: =IF(F80="",0,1) -> 0 | Z80: =IF(A80=1,SUM($A$6:$A80),0)
A81: =COUNT(E81) -> 1 | B81: Accumulated depreciation of furniture, fixtures, fittings and soft furnishings | C81: 1394 | F81: =IF(E81>0,"Positive amount!","") | H81: =IF(F81="",0,1) -> 0 | Z81: =IF(A81=1,SUM($A$6:$A81),0)
A82: =COUNT(E82) -> 0 | B82: Other plant | C82: 1395 | F82: =IF(E82<0,"Negative amount!","") | H82: =IF(F82="",0,1) | Z82: =IF(A82=1,SUM($A$6:$A82),0)
A83: =COUNT(E83) -> 0 | B83: Accumulated depreciation of other plant | C83: 1396 | F83: =IF(E83>0,"Positive amount!","") | H83: =IF(F83="",0,1) -> 0 | Z83: =IF(A83=1,SUM($A$6:$A83),0)
A84: =COUNT(E84) -> 0 | B84: Other machinery | C84: 1397 | F84: =IF(E84<0,"Negative amount!","") | H84: =IF(F84="",0,1) -> 0 | Z84: =IF(A84=1,SUM($A$6:$A84),0)
A85: =COUNT(E85) -> 0 | B85: Accumulated depreciation of other machinery | C85: 1398 | F85: =IF(E85>0,"Positive amount!","") | H85: =IF(F85="",0,1) -> 0 | Z85: =IF(A85=1,SUM($A$6:$A85),0)
A86: =COUNT(E86) -> 0 | B86: Other tangible assets | C86: 1600 | F86: =IF(E86<0,"Negative amount!","") | H86: =IF(F86="",0,1) -> 0 | Z86: =IF(A86=1,SUM($A$6:$A86),0)
A87: =COUNT(E87) -> 0 | B87: Accumulated depreciation of other tangible assets | C87: 1601 | F87: =IF(E87>0,"Positive amount!","") | H87: =IF(F87="",0,1) -> 0 | Z87: =IF(A87=1,SUM($A$6:$A87),0)
A88: =COUNT(E88) -> 0 | B88: Capital leases - buildings | C88: 1602 | F88: =IF(E88<0,"Negative amount!","") | H88: =IF(F88="",0,1) -> 0 | Z88: =IF(A88=1,SUM($A$6:$A88),0)
A89: =COUNT(E89) -> 0 | B89: Accumulated depreciation of capital leases - buildings | C89: 1603 | F89: =IF(E89>0,"Positive amount!","") | H89: =IF(F89="",0,1) -> 0 | Z89: =IF(A89=1,SUM($A$6:$A89),0)
A90: =COUNT(E90) -> 0 | B90: Capital leases - machinery and equipment | C90: 1604 | F90: =IF(E90<0,"Negative amount!","") | H90: =IF(F90="",0,1) -> 0 | Z90: =IF(A90=1,SUM($A$6:$A90),0)
A91: =COUNT(E91) -> 0 | B91: Accumulated depreciation of capital leases - machinery and equipment | C91: 1605 | F91: =IF(E91>0,"Positive amount!","") | H91: =IF(F91="",0,1) -> 0 | Z91: =IF(A91=1,SUM($A$6:$A91),0)
A92: =COUNT(E92) -> 0 | B92: Capital leases - vehicles | C92: 1606 | F92: =IF(E92<0,"Negative amount!","") | H92: =IF(F92="",0,1) -> 0 | Z92: =IF(A92=1,SUM($A$6:$A92),0)
A93: =COUNT(E93) -> 0 | B93: Accumulated depreciation of capital leases - vehicles | C93: 1607 | F93: =IF(E93>0,"Positive amount!","") | H93: =IF(F93="",0,1) -> 0 | Z93: =IF(A93=1,SUM($A$6:$A93),0)
A94: =COUNT(E94) -> 0 | B94: Capital leases - others | C94: 1608 | F94: =IF(E94<0,"Negative amount!","") | H94: =IF(F94="",0,1) -> 0 | Z94: =IF(A94=1,SUM($A$6:$A94),0)
A95: =COUNT(E95) -> 0 | B95: Accumulated depreciation of capital leases - others | C95: 1609 | F95: =IF(E95>0,"Positive amount!","") | H95: =IF(F95="",0,1) -> 0 | Z95: =IF(A95=1,SUM($A$6:$A95),0)
A96: =COUNT(E96) -> 0 | B96: Leasehold improvements | C96: 1610 | F96: =IF(E96<0,"Negative amount!","") | H96: =IF(F96="",0,1) -> 0 | Z96: =IF(A96=1,SUM($A$6:$A96),0)
A97: =COUNT(E97) -> 0 | B97: Accumulated depreciation of leasehold improvements | C97: 1611 | F97: =IF(E97>0,"Positive amount!","") | H97: =IF(F97="",0,1) -> 0 | Z97: =IF(A97=1,SUM($A$6:$A97),0)
A98: =COUNT(E98) -> 0 | B98: Capital assets under construction | C98: 1612 | F98: =IF(E98<0,"Negative amount!","") | H98: =IF(F98="",0,1) -> 0 | Z98: =IF(A98=1,SUM($A$6:$A98),0)
A99: 1 | B99: Total Tangible Assets | C99: 1698 | E99: =SUM(E98,E96,E94,E92,E90,E88,E86,E84,E82,E80,E78,E76,E74,E73,E71,E69,E67,E65,E63,E61,E59,E57,E55,E53,E51,E49,E47,E45,E43,E41)+SUM(E39,E37,E35,E33,E31,E29,E28,E26,E24,E22,E20,E18) | H99: =SUM(H6:H98) | Y99: 1 | Z99: =IF(A99=1,SUM($A$6:$A99),0) | CA99: 1
A100: 1 | B100: Total accumulated depreciation of tangible assets | C100: 1699 | E100: =SUM(E97,E95,E93,E91,E89,E87,E85,E83,E81,E79,E77,E75,E72,E70,E68,E66,E64,E62,E60,E58,E56,E54,E52,E50,E48,E46,E44,E42)+SUM(E40,E38,E36,E34,E32,E30,E27,E25,E23,E21,E19) | Y100: 1 | Z100: =IF(A100=1,SUM($A$6:$A100),0) | CA100: 1
...

Sheet B_Sheet_Summary
B4: =B_Sheet!B4 -> Balance Sheet as at | C4: =B_Sheet!C4&" "&B_Sheet!D4&" "&B_Sheet!E4
B5: Item Description | C5: Code | D5: Value
B6: =IF(ROW() -5<= MAX(B_Sheet!$Z$6:$Z$263),INDEX(B_Sheet!$B$6:$Z$263,MATCH(ROW()-5,B_Sheet!$Z$6:$Z$263,0),1),"") | C6: =IF(ROW() -5<= MAX(B_Sheet!$Z$6:$Z$263),INDEX(B_Sheet!$B$6:$Z$263,MATCH(ROW()-5,B_Sheet!$Z$6:$Z$263,0),2),"") | D6: =IF(ROW() -5<= MAX(B_Sheet!$Z$6:$Z$263),INDEX(B_Sheet!$B$6:$Z$263,MATCH(ROW()-5,B_Sheet!$Z$6:$Z$263,0),4),"") | G6: =IF(ROW()-5<=MAX(B_Sheet!$Z$6:$Z$263),INDEX(B_Sheet!$B$6:$Z$263,MATCH(ROW()-5,B_Sheet!$Z$6:$Z$263,0),24),"")
B7: =IF(ROW() -5<= MAX(B_Sheet!$Z$6:$Z$263),INDEX(B_Sheet!$B$6:$Z$263,MATCH(ROW()-5,B_Sheet!$Z$6:$Z$263,0),1),"") | C7: =IF(ROW() -5<= MAX(B_Sheet!$Z$6:$Z$263),INDEX(B_Sheet!$B$6:$Z$263,MATCH(ROW()-5,B_Sheet!$Z$6:$Z$263,0),2),"") | D7: =IF(ROW() -5<= MAX(B_Sheet!$Z$6:$Z$263),INDEX(B_Sheet!$B$6:$Z$263,MATCH(ROW()-5,B_Sheet!$Z$6:$Z$263,0),4),"") | G7: =IF(ROW()-5<=MAX(B_Sheet!$Z$6:$Z$263),INDEX(B_Sheet!$B$6:$Z$263,MATCH(ROW()-5,B_Sheet!$Z$6:$Z$263,0),24),"")
B8: =IF(ROW() -5<= MAX(B_Sheet!$Z$6:$Z$263),INDEX(B_Sheet!$B$6:$Z$263,MATCH(ROW()-5,B_Sheet!$Z$6:$Z$263,0),1),"") | C8: =IF(ROW() -5<= MAX(B_Sheet!$Z$6:$Z$263),INDEX(B_Sheet!$B$6:$Z$263,MATCH(ROW()-5,B_Sheet!$Z$6:$Z$263,0),2),"") | D8: =IF(ROW() -5<= MAX(B_Sheet!$Z$6:$Z$263),INDEX(B_Sheet!$B$6:$Z$263,MATCH(ROW()-5,B_Sheet!$Z$6:$Z$263,0),4),"") | G8: =IF(ROW()-5<=MAX(B_Sheet!$Z$6:$Z$263),INDEX(B_Sheet!$B$6:$Z$263,MATCH(ROW()-5,B_Sheet!$Z$6:$Z$263,0),24),"")
B9: =IF(ROW() -5<= MAX(B_Sheet!$Z$6:$Z$263),INDEX(B_Sheet!$B$6:$Z$263,MATCH(ROW()-5,B_Sheet!$Z$6:$Z$263,0),1),"") | C9: =IF(ROW() -5<= MAX(B_Sheet!$Z$6:$Z$263),INDEX(B_Sheet!$B$6:$Z$263,MATCH(ROW()-5,B_Sheet!$Z$6:$Z$263,0),2),"") | D9: =IF(ROW() -5<= MAX(B_Sheet!$Z$6:$Z$263),INDEX(B_Sheet!$B$6:$Z$263,MATCH(ROW()-5,B_Sheet!$Z$6:$Z$263,0),4),"") | G9: =IF(ROW()-5<=MAX(B_Sheet!$Z$6:$Z$263),INDEX(B_Sheet!$B$6:$Z$263,MATCH(ROW()-5,B_Sheet!$Z$6:$Z$263,0),24),"")
B10: =IF(ROW() -5<= MAX(B_Sheet!$Z$6:$Z$263),INDEX(B_Sheet!$B$6:$Z$263,MATCH(ROW()-5,B_Sheet!$Z$6:$Z$263,0),1),"") | C10: =IF(ROW() -5<= MAX(B_Sheet!$Z$6:$Z$263),INDEX(B_Sheet!$B$6:$Z$263,MATCH(ROW()-5,B_Sheet!$Z$6:$Z$263,0),2),"") | D10: =IF(ROW() -5<= MAX(B_Sheet!$Z$6:$Z$263),INDEX(B_Sheet!$B$6:$Z$263,MATCH(ROW()-5,B_Sheet!$Z$6:$Z$263,0),4),"") | G10: =IF(ROW()-5<=MAX(B_Sheet!$Z$6:$Z$263),INDEX(B_Sheet!$B$6:$Z$263,MATCH(ROW()-5,B_Sheet!$Z$6:$Z$263,0),24),"")
B11: =IF(ROW() -5<= MAX(B_Sheet!$Z$6:$Z$263),INDEX(B_Sheet!$B$6:$Z$263,MATCH(ROW()-5,B_Sheet!$Z$6:$Z$263,0),1),"") | C11: =IF(ROW() -5<= MAX(B_Sheet!$Z$6:$Z$263),INDEX(B_Sheet!$B$6:$Z$263,MATCH(ROW()-5,B_Sheet!$Z$6:$Z$263,0),2),"") | D11: =IF(ROW() -5<= MAX(B_Sheet!$Z$6:$Z$263),INDEX(B_Sheet!$B$6:$Z$263,MATCH(ROW()-5,B_Sheet!$Z$6:$Z$263,0),4),"") | G11: =IF(ROW()-5<=MAX(B_Sheet!$Z$6:$Z$263),INDEX(B_Sheet!$B$6:$Z$263,MATCH(ROW()-5,B_Sheet!$Z$6:$Z$263,0),24),"")
B12: =IF(ROW() -5<= MAX(B_Sheet!$Z$6:$Z$263),INDEX(B_Sheet!$B$6:$Z$263,MATCH(ROW()-5,B_Sheet!$Z$6:$Z$263,0),1),"") | C12: =IF(ROW() -5<= MAX(B_Sheet!$Z$6:$Z$263),INDEX(B_Sheet!$B$6:$Z$263,MATCH(ROW()-5,B_Sheet!$Z$6:$Z$263,0),2),"") | D12: =IF(ROW() -5<= MAX(B_Sheet!$Z$6:$Z$263),INDEX(B_Sheet!$B$6:$Z$263,MATCH(ROW()-5,B_Sheet!$Z$6:$Z$263,0),4),"") | G12: =IF(ROW()-5<=MAX(B_Sheet!$Z$6:$Z$263),INDEX(B_Sheet!$B$6:$Z$263,MATCH(ROW()-5,B_Sheet!$Z$6:$Z$263,0),24),"")
B13: =IF(ROW() -5<= MAX(B_Sheet!$Z$6:$Z$263),INDEX(B_Sheet!$B$6:$Z$263,MATCH(ROW()-5,B_Sheet!$Z$6:$Z$263,0),1),"") | C13: =IF(ROW() -5<= MAX(B_Sheet!$Z$6:$Z$263),INDEX(B_Sheet!$B$6:$Z$263,MATCH(ROW()-5,B_Sheet!$Z$6:$Z$263,0),2),"") | D13: =IF(ROW() -5<= MAX(B_Sheet!$Z$6:$Z$263),INDEX(B_Sheet!$B$6:$Z$263,MATCH(ROW()-5,B_Sheet!$Z$6:$Z$263,0),4),"") | G13: =IF(ROW()-5<=MAX(B_Sheet!$Z$6:$Z$263),INDEX(B_Sheet!$B$6:$Z$263,MATCH(ROW()-5,B_Sheet!$Z$6:$Z$263,0),24),"")
B14: =IF(ROW() -5<= MAX(B_Sheet!$Z$6:$Z$263),INDEX(B_Sheet!$B$6:$Z$263,MATCH(ROW()-5,B_Sheet!$Z$6:$Z$263,0),1),"") | C14: =IF(ROW() -5<= MAX(B_Sheet!$Z$6:$Z$263),INDEX(B_Sheet!$B$6:$Z$263,MATCH(ROW()-5,B_Sheet!$Z$6:$Z$263,0),2),"") | D14: =IF(ROW() -5<= MAX(B_Sheet!$Z$6:$Z$263),INDEX(B_Sheet!$B$6:$Z$263,MATCH(ROW()-5,B_Sheet!$Z$6:$Z$263,0),4),"") | G14: =IF(ROW()-5<=MAX(B_Sheet!$Z$6:$Z$263),INDEX(B_Sheet!$B$6:$Z$263,MATCH(ROW()-5,B_Sheet!$Z$6:$Z$263,0),24),"")
B15: =IF(ROW() -5<= MAX(B_Sheet!$Z$6:$Z$263),INDEX(B_Sheet!$B$6:$Z$263,MATCH(ROW()-5,B_Sheet!$Z$6:$Z$263,0),1),"") | C15: =IF(ROW() -5<= MAX(B_Sheet!$Z$6:$Z$263),INDEX(B_Sheet!$B$6:$Z$263,MATCH(ROW()-5,B_Sheet!$Z$6:$Z$263,0),2),"") | D15: =IF(ROW() -5<= MAX(B_Sheet!$Z$6:$Z$263),INDEX(B_Sheet!$B$6:$Z$263,MATCH(ROW()-5,B_Sheet!$Z$6:$Z$263,0),4),"") | G15: =IF(ROW()-5<=MAX(B_Sheet!$Z$6:$Z$263),INDEX(B_Sheet!$B$6:$Z$263,MATCH(ROW()-5,B_Sheet!$Z$6:$Z$263,0),24),"")
B16: =IF(ROW() -5<= MAX(B_Sheet!$Z$6:$Z$263),INDEX(B_Sheet!$B$6:$Z$263,MATCH(ROW()-5,B_Sheet!$Z$6:$Z$263,0),1),"") | C16: =IF(ROW() -5<= MAX(B_Sheet!$Z$6:$Z$263),INDEX(B_Sheet!$B$6:$Z$263,MATCH(ROW()-5,B_Sheet!$Z$6:$Z$263,0),2),"") | D16: =IF(ROW() -5<= MAX(B_Sheet!$Z$6:$Z$263),INDEX(B_Sheet!$B$6:$Z$263,MATCH(ROW()-5,B_Sheet!$Z$6:$Z$263,0),4),"") | G16: =IF(ROW()-5<=MAX(B_Sheet!$Z$6:$Z$263),INDEX(B_Sheet!$B$6:$Z$263,MATCH(ROW()-5,B_Sheet!$Z$6:$Z$263,0),24),"")
B17: =IF(ROW() -5<= MAX(B_Sheet!$Z$6:$Z$263),INDEX(B_Sheet!$B$6:$Z$263,MATCH(ROW()-5,B_Sheet!$Z$6:$Z$263,0),1),"") | C17: =IF(ROW() -5<= MAX(B_Sheet!$Z$6:$Z$263),INDEX(B_Sheet!$B$6:$Z$263,MATCH(ROW()-5,B_Sheet!$Z$6:$Z$263,0),2),"") | D17: =IF(ROW() -5<= MAX(B_Sheet!$Z$6:$Z$263),INDEX(B_Sheet!$B$6:$Z$263,MATCH(ROW()-5,B_Sheet!$Z$6:$Z$263,0),4),"") | G17: =IF(ROW()-5<=MAX(B_Sheet!$Z$6:$Z$263),INDEX(B_Sheet!$B$6:$Z$263,MATCH(ROW()-5,B_Sheet!$Z$6:$Z$263,0),24),"")
... B261: =IF(ROW() -5<= MAX(B_Sheet!$Z$6:$Z$263),INDEX(B_Sheet!$B$6:$Z$263,MATCH(ROW()-5,B_Sheet!$Z$6:$Z$263,0),1),"") | C261: =IF(ROW() -5<= MAX(B_Sheet!$Z$6:$Z$263),INDEX(B_Sheet!$B$6:$Z$263,MATCH(ROW()-5,B_Sheet!$Z$6:$Z$263,0),2),"") | D261: =IF(ROW() -5<= MAX(B_Sheet!$Z$6:$Z$263),INDEX(B_Sheet!$B$6:$Z$263,MATCH(ROW()-5,B_Sheet!$Z$6:$Z$263,0),4),"") | G261: =IF(ROW()-5<=MAX(B_Sheet!$Z$6:$Z$263),INDEX(B_Sheet!$B$6:$Z$263,MATCH(ROW()-5,B_Sheet!$Z$6:$Z$263,0),24),"")

Sheet IRDAddin
A1: Name | B1: CompanyTaxReturn09
A2: Version | B2: 9.2
A3: GUID | B3: 89182126-b648-485f-b910-560b60b5c4da
A4: TP | B4: =reg
A5: Year | B5: =ya
A6: Complete | B6: =IF(Index!E155<>0,1,IF(Index!G155<>0,2,0))

Sheet Consolidation
A1: FU_PRINC | D1: =COUNTA(FU)
A2: FU_MEM_1
A3: FU_MEM_2
A4: FU_MEM_3
A5: FU_MEM_4
A6: FU_MEM_5
A7: FU_MEM_6
A8: FU_MEM_7
A9: FU_MEM_8
A10: FU_MEM_9
A11: FU_MEM_10
A12: FU_MEM_11
A13: FU_MEM_12
... A80: FU_MEM_79

Sheet Income
A1: a | B1: Back to Index | S1: Mandatory | AA1: =IF(ISBLANK(C297),1,C297)
A2: 1
A3: 0 | B3: Number of activities | C3: 1 | D3: =IF(ISBLANK(C3),"REQUIRED!","") | P3: =IF(ISBLANK(C3),1,0)
A4: 1 | B4: =_ref1 | E4: =_YA1 | F4: =_YA1 | G4: =_YA1 | H4: =_YA1 -> Y/A 2025 | I4: =_YA1 -> Y/A 2025 | J4: =_YA1 -> Y/A 2025 | K4: =_YA1 -> Y/A 2025 | L4: =_YA1 -> Y/A 2025 | ... N4: =_YA1 -> Y/A 2025 | U4: =B_Sheet!D4 | V4: =B_Sheet!E4
A5: 1 | B5: ="INCOME STATEMENT FOR THE YEAR ENDED "&B_Sheet!C4&" "&B_Sheet!D4&" "&B_Sheet!E4 | T5: =SUM(U5:V5) | U5: =IF(V4>2002,0,IF(U4="December",1,0)) | V5: =IF(V4=2002,1,IF(V4>2002,2,0))
A6: 1 | B6: NAME OF THE OPERATING ESTABLISHMENT | C6: 4500 | D6: =IF(O6<>C3,"Descriptions!","") | O6: =IF(tr=1,C3,COUNTA(E6:N6)) | Y6: 1 | Z6: =IF(A6=1,SUM($A6:$A$6),0)
A7: 1 | P7: =IF(O6<>C3,1,0) | Y7: 1 | Z7: =IF(A7=1,SUM($A$6:$A7),0)
A8: 1 | B8: OPERATION DESCRIPTION | C8: 4501 | D8: =IF(O8<>C3,"Descriptions!","") | O8: =IF(tr=1,C3,COUNTA(E8:N8)) | Y8: 1 | Z8: =IF(A8=1,SUM($A$6:$A8),0)
A9: 1 | P9: =IF(O8<>C3,1,0) | Y9: 1 | Z9: =IF(A9=1,SUM($A$6:$A9),0)
A10: 1 | B10: ACTIVITY NUMBER | C10: 4502 | E10: =IF($C$3="","",1) | F10: =IF($C$3=1,"",IF(E10="","",IF(E10+1>$C$3,"",E10+1))) | G10: =IF($C$3=1,"",IF(F10="","",IF(F10+1>$C$3,"",F10+1))) | H10: =IF($C$3=1,"",IF(G10="","",IF(G10+1>$C$3,"",G10+1))) | I10: =IF($C$3=1,"",IF(H10="","",IF(H10+1>$C$3,"",H10+1))) | J10: =IF($C$3=1,"",IF(I10="","",IF(I10+1>$C$3,"",I10+1))) | K10: =IF($C$3=1,"",IF(J10="","",IF(J10+1>$C$3,"",J10+1))) | L10: =IF($C$3=1,"",IF(K10="","",IF(K10+1>$C$3,"",K10+1))) | M10: =IF($C$3=1,"",IF(L10="","",IF(L10+1>$C$3,"",L10+1))) | N10: =IF($C$3=1,"",IF(M10="","",IF(M10+1>$C$3,"",M10+1))) | Y10: 1 | Z10: =IF(A10=1,SUM($A$6:$A10),0)
A11: 0 | B11: Item Description | C11: Code | E11: Dr ( + ) or Cr ( - ) | F11: Dr ( + ) or Cr ( - ) | G11: Dr ( + ) or Cr ( - ) | H11: Dr ( + ) or Cr ( - ) | I11: Dr ( + ) or Cr ( - ) | K11: Dr ( + ) or Cr ( - ) | L11: Dr ( + ) or Cr ( - ) | M11: Dr ( + ) or Cr ( - ) | N11: Dr ( + ) or Cr ( - ) | Z11: =IF(A11=1,SUM($A$6:$A11),0)
A12: =IF(OR(E12<>"",F12<>"",G12<>"",H12<>"",I12<>""),1,0) | B12: Sale of goods and rendering of services | C12: 5000 | Z12: =IF(A12=1,SUM($A$6:$A12),0) | AA12: =INDEX(activity,AB12,$AA$1) | AB12: 1
A13: =IF(OR(E13<>"",F13<>"",G13<>"",H13<>"",I13<>""),1,0) | B13: Export Sales | C13: 5001 | Z13: =IF(A13=1,SUM($A$6:$A13),0) | AA13: =INDEX(activity,AB13,$AA$1) | AB13: 2
A14: =IF(OR(E14<>"",F14<>"",G14<>"",H14<>"",I14<>""),1,0) -> 0 | B14: Wholesale Sales | C14: 5002 | Z14: =IF(A14=1,SUM($A$6:$A14),0) | AA14: =INDEX(activity,AB14,$AA$1) -> 0 | AB14: 3
A15: =IF(OR(E15<>"",F15<>"",G15<>"",H15<>"",I15<>""),1,0) -> 0 | B15: Retail Sales | C15: 5003 | Z15: =IF(A15=1,SUM($A$6:$A15),0) | AA15: =INDEX(activity,AB15,$AA$1) -> 0 | AB15: 4
A16: =IF(OR(E16<>"",F16<>"",G16<>"",H16<>"",I16<>""),1,0) -> 0 | B16: Sale of goods to related parties | C16: 5004 | Z16: =IF(A16=1,SUM($A$6:$A16),0) | AA16: =INDEX(activity,AB16,$AA$1) -> 0 | AB16: 5
A17: =IF(OR(E17<>"",F17<>"",G17<>"",H17<>"",I17<>""),1,0) -> 0 | B17: Interdivisional sales | C17: 5005 | Z17: =IF(A17=1,SUM($A$6:$A17),0) | AA17: =INDEX(activity,AB17,$AA$1) -> 0 | AB17: 6
A18: =IF(OR(E18<>"",F18<>"",G18<>"",H18<>"",I18<>""),1,0) -> 0 | B18: Income from production and / or processing - local | C18: 5006 | Z18: =IF(A18=1,SUM($A$6:$A18),0) | AA18: =INDEX(activity,AB18,$AA$1) -> 0 | AB18: 7
A19: =IF(OR(E19<>"",F19<>"",G19<>"",H19<>"",I19<>""),1,0) -> 0 | B19: Income from production and / or processing - foreign | C19: 5007 | Z19: =IF(A19=1,SUM($A$6:$A19),0) | AA19: =INDEX(activity,AB19,$AA$1) -> 0 | AB19: 8
A20: =IF(OR(E20<>"",F20<>"",G20<>"",H20<>"",I20<>""),1,0) -> 0 | B20: Income from production and / or processing - related parties | C20: 5008 | Z20: =IF(A20=1,SUM($A$6:$A20),0) | AA20: =INDEX(activity,AB20,$AA$1) -> 0 | AB20: 9
A21: =IF(OR(E21<>"",F21<>"",G21<>"",H21<>"",I21<>""),1,0) -> 0 | B21: Income from the rendering of services - local | C21: 5009 | Z21: =IF(A21=1,SUM($A$6:$A21),0) | AA21: =INDEX(activity,AB21,$AA$1) -> 0 | AB21: 10
A22: =IF(OR(E22<>"",F22<>"",G22<>"",H22<>"",I22<>""),1,0) -> 0 | B22: Income from the rendering of services - overseas | C22: 5010 | Z22: =IF(A22=1,SUM($A$6:$A22),0) | AA22: =INDEX(activity,AB22,$AA$1) -> 0 | AB22: 11
A23: =IF(OR(E23<>"",F23<>"",G23<>"",H23<>"",I23<>""),1,0) -> 0 | B23: Income from the rendering of services to related parties | C23: 5011 | Z23: =IF(A23=1,SUM($A$6:$A23),0) | AA23: =INDEX(activity,AB23,$AA$1) -> 0 | AB23: 12
A24: =IF(OR(E24<>"",F24<>"",G24<>"",H24<>"",I24<>""),1,0) -> 1 | B24: Total sales of goods and services | C24: 5099 | E24: =SUM(E12:E23) | F24: =SUM(F12:F23) | G24: =SUM(G12:G23) -> 0 | H24: =SUM(H12:H23) -> 0 | I24: =SUM(I12:I23) -> 0 | J24: =SUM(J12:J23) -> 0 | K24: =SUM(K12:K23) -> 0 | L24: =SUM(L12:L23) -> 0 | ... N24: =SUM(N12:N23) -> 0 | Z24: =IF(A24=1,SUM($A$6:$A24),0) | AA24: =INDEX(activity,AB24,$AA$1) -> -681223 | AB24: 13 | CA24: 1
A25: =IF(OR(E25<>"",F25<>"",G25<>"",H25<>"",I25<>""),1,0) -> 0 | B25: Income from Investments | C25: 5100 | Z25: =IF(A25=1,SUM($A$6:$A25),0) | AA25: =INDEX(activity,AB25,$AA$1) -> 0 | AB25: 14 | BA25: =SUM(E25:N25)
A26: =IF(OR(E26<>"",F26<>"",G26<>"",H26<>"",I26<>""),1,0) -> 0 | B26: Interest from Maltese banks | C26: 5101 | Z26: =IF(A26=1,SUM($A$6:$A26),0) | AA26: =INDEX(activity,AB26,$AA$1) -> 0 | AB26: 15 | BA26: =SUM(E26:N26)
A27: =IF(OR(E27<>"",F27<>"",G27<>"",H27<>"",I27<>""),1,0) -> 0 | B27: Interest received or receivable from shareholders and / or directors | C27: 5102 | Z27: =IF(A27=1,SUM($A$6:$A27),0) | AA27: =INDEX(activity,AB27,$AA$1) -> 0 | AB27: 16 | BA27: =SUM(E27:N27) -> 0
A28: =IF(OR(E28<>"",F28<>"",G28<>"",H28<>"",I28<>""),1,0) -> 0 | B28: Interest received or receivable from related parties | C28: 5103 | Z28: =IF(A28=1,SUM($A$6:$A28),0) | AA28: =INDEX(activity,AB28,$AA$1) -> 0 | AB28: 17 | BA28: =SUM(E28:N28) -> 0
A29: =IF(OR(E29<>"",F29<>"",G29<>"",H29<>"",I29<>""),1,0) -> 0 | B29: Loan interest - from local sources | C29: 5104 | Z29: =IF(A29=1,SUM($A$6:$A29),0) | AA29: =INDEX(activity,AB29,$AA$1) -> 0 | AB29: 18 | BA29: =SUM(E29:N29) -> 0
A30: =IF(OR(E30<>"",F30<>"",G30<>"",H30<>"",I30<>""),1,0) -> 0 | B30: Securities interest - from local sources | C30: 5105 | Z30: =IF(A30=1,SUM($A$6:$A30),0) | AA30: =INDEX(activity,AB30,$AA$1) -> 0 | AB30: 19 | BA30: =SUM(E30:N30) -> 0
A31: =IF(OR(E31<>"",F31<>"",G31<>"",H31<>"",I31<>""),1,0) -> 0 | B31: Interest from other Maltese sources | C31: 5106 | Z31: =IF(A31=1,SUM($A$6:$A31),0) | AA31: =INDEX(activity,AB31,$AA$1) -> 0 | AB31: 20 | BA31: =SUM(E31:N31) -> 0
A32: =IF(OR(E32<>"",F32<>"",G32<>"",H32<>"",I32<>""),1,0) -> 0 | B32: Interest from foreign banks | C32: 5107 | Z32: =IF(A32=1,SUM($A$6:$A32),0) | AA32: =INDEX(activity,AB32,$AA$1) -> 0 | AB32: 21 | BA32: =SUM(E32:N32) -> 0 | BD32: =BA32
A33: =IF(OR(E33<>"",F33<>"",G33<>"",H33<>"",I33<>""),1,0) -> 0 | B33: Loan interest - from foreign sources | C33: 5108 | Z33: =IF(A33=1,SUM($A$6:$A33),0) | AA33: =INDEX(activity,AB33,$AA$1) -> 0 | AB33: 22 | BA33: =SUM(E33:N33) -> 0 | BD33: =BA33
A34: =IF(OR(E34<>"",F34<>"",G34<>"",H34<>"",I34<>""),1,0) -> 0 | B34: Securities interest - from foreign sources | C34: 5109 | Z34: =IF(A34=1,SUM($A$6:$A34),0) | AA34: =INDEX(activity,AB34,$AA$1) -> 0 | AB34: 23 | BA34: =SUM(E34:N34) -> 0 | BD34: =BA34
A35: =IF(OR(E35<>"",F35<>"",G35<>"",H35<>"",I35<>""),1,0) -> 0 | B35: Interest from other foreign sources | C35: 5110 | Z35: =IF(A35=1,SUM($A$6:$A35),0) | AA35: =INDEX(activity,AB35,$AA$1) -> 0 | AB35: 24 | BA35: =SUM(E35:N35) -> 0 | BB35: =SUM(BA25:BA35) | BD35: =BA35
A36: =IF(OR(E36<>"",F36<>"",G36<>"",H36<>"",I36<>""),1,0) -> 0 | B36: Dividends from Maltese sources | C36: 5111 | Z36: =IF(A36=1,SUM($A$6:$A36),0) | AA36: =INDEX(activity,AB36,$AA$1) -> 0 | AB36: 25 | BA36: =SUM(E36:N36) -> 0 | BD36: =BA59 | BE36: =SUM(BD32:BD36)
A37: =IF(OR(E37<>"",F37<>"",G37<>"",H37<>"",I37<>""),1,0) -> 0 | B37: Dividends from foreign sources | C37: 5112 | Z37: =IF(A37=1,SUM($A$6:$A37),0) | AA37: =INDEX(activity,AB37,$AA$1) -> 0 | AB37: 26 | BA37: =SUM(E37:N37) -> 0 | BB37: =BA37+BA36
A38: =IF(OR(E38<>"",F38<>"",G38<>"",H38<>"",I38<>""),1,0) -> 0 | B38: Commission Income | C38: 5190 | Z38: =IF(A38=1,SUM($A$6:$A38),0) | AA38: =INDEX(activity,AB38,$AA$1) -> 0 | AB38: 27
A39: =IF(OR(E39<>"",F39<>"",G39<>"",H39<>"",I39<>""),1,0) -> 0 | B39: Commission income on real estate transactions | C39: 5191 | Z39: =IF(A39=1,SUM($A$6:$A39),0) | AA39: =INDEX(activity,AB39,$AA$1) -> 0 | AB39: 28
A40: =IF(OR(E40<>"",F40<>"",G40<>"",H40<>"",I40<>""),1,0) -> 0 | B40: Rental income | C40: 5200 | Z40: =IF(A40=1,SUM($A$6:$A40),0) | AA40: =INDEX(activity,AB40,$AA$1) -> 0 | AB40: 29 | BA40: =SUM(E40:N40)
A41: =IF(OR(E41<>"",F41<>"",G41<>"",H41<>"",I41<>""),1,0) -> 0 | B41: Real estate rental Income | C41: 5201 | Z41: =IF(A41=1,SUM($A$6:$A41),0) | AA41: =INDEX(activity,AB41,$AA$1) -> 0 | AB41: 30 | BA41: =SUM(E41:N41) | BB41: =SUM(BA40:BA41)
A42: =IF(OR(E42<>"",F42<>"",G42<>"",H42<>"",I42<>""),1,0) -> 0 | B42: Income from ground rents and / or laudemium | C42: 5202 | Z42: =IF(A42=1,SUM($A$6:$A42),0) | AA42: =INDEX(activity,AB42,$AA$1) -> 0 | AB42: 31 | BA42: =SUM(E42:N42) | BB42: =BA42
A43: =IF(OR(E43<>"",F43<>"",G43<>"",H43<>"",I43<>""),1,0) -> 0 | B43: Film rental | C43: 5203 | Z43: =IF(A43=1,SUM($A$6:$A43),0) | AA43: =INDEX(activity,AB43,$AA$1) -> 0 | AB43: 32
A44: =IF(OR(E44<>"",F44<>"",G44<>"",H44<>"",I44<>""),1,0) -> 0 | B44: Vehicle leasing | C44: 5204 | Z44: =IF(A44=1,SUM($A$6:$A44),0) | AA44: =INDEX(activity,AB44,$AA$1) -> 0 | AB44: 33
A45: =IF(OR(E45<>"",F45<>"",G45<>"",H45<>"",I45<>""),1,0) -> 0 | B45: Amounts received by non-profit making organisations [NPOs] | C45: 5250 | Z45: =IF(A45=1,SUM($A$6:$A45),0) | AA45: =INDEX(activity,AB45,$AA$1) -> 0 | AB45: 34
A46: =IF(OR(E46<>"",F46<>"",G46<>"",H46<>"",I46<>""),1,0) -> 0 | B46: Membership fees received | C46: 5251 | Z46: =IF(A46=1,SUM($A$6:$A46),0) | AA46: =INDEX(activity,AB46,$AA$1) -> 0 | AB46: 35
A47: =IF(OR(E47<>"",F47<>"",G47<>"",H47<>"",I47<>""),1,0) -> 0 | B47: Donations and gifts received | C47: 5252 | Z47: =IF(A47=1,SUM($A$6:$A47),0) | AA47: =INDEX(activity,AB47,$AA$1) -> 0 | AB47: 36
A48: =IF(OR(E48<>"",F48<>"",G48<>"",H48<>"",I48<>""),1,0) -> 0 | B48: Gross sales and Income from organizational activities | C48: 5253 | Z48: =IF(A48=1,SUM($A$6:$A48),0) | AA48: =INDEX(activity,AB48,$AA$1) -> 0 | AB48: 37
A49: =IF(OR(E49<>"",F49<>"",G49<>"",H49<>"",I49<>""),1,0) -> 0 | B49: Realised Gains or losses on disposal of fixed assets | C49: 5280 | Z49: =IF(A49=1,SUM($A$6:$A49),0) | AA49: =INDEX(activity,AB49,$AA$1) -> 0 | AB49: 38
A50: =IF(OR(E50<>"",F50<>"",G50<>"",H50<>"",I50<>""),1,0) -> 0 | B50: Realised gains or losses on disposal of intangible assets | C50: 5281 | Z50: =IF(A50=1,SUM($A$6:$A50),0) | AA50: =INDEX(activity,AB50,$AA$1) -> 0 | AB50: 39
A51: =IF(OR(E51<>"",F51<>"",G51<>"",H51<>"",I51<>""),1,0) -> 0 | B51: Realised gains or losses on disposal of tangible assets | C51: 5282 | Z51: =IF(A51=1,SUM($A$6:$A51),0) | AA51: =INDEX(activity,AB51,$AA$1) -> 0 | AB51: 40
A52: =IF(OR(E52<>"",F52<>"",G52<>"",H52<>"",I52<>""),1,0) -> 0 | B52: Realised gains or losses on disposal of immovable property | C52: 5283 | Z52: =IF(A52=1,SUM($A$6:$A52),0) | AA52: =INDEX(activity,AB52,$AA$1) -> 0 | AB52: 41
A53: =IF(OR(E53<>"",F53<>"",G53<>"",H53<>"",I53<>""),1,0) -> 0 | B53: Realised gains or losses on sale of investments | C53: 5284 | Z53: =IF(A53=1,SUM($A$6:$A53),0) | AA53: =INDEX(activity,AB53,$AA$1) -> 0 | AB53: 42
A54: =IF(OR(E54<>"",F54<>"",G54<>"",H54<>"",I54<>""),1,0) -> 1 | B54: Other Income | C54: 5300 | Z54: =IF(A54=1,SUM($A$6:$A54),0) | AA54: =INDEX(activity,AB54,$AA$1) -> -53618 | AB54: 43
... A58: =IF(OR(E58<>"",F58<>"",G58<>"",H58<>"",I58<>""),1,0) -> 0 | B58: Realisation of deferred Income | C58: 5304 | Z58: =IF(A58=1,SUM($A$6:$A58),0) | AA58: =INDEX(activity,AB58,$AA$1) -> 0 | AB58: 47
A59: =IF(OR(E59<>"",F59<>"",G59<>"",H59<>"",I59<>""),1,0) -> 0 | B59: Income from royalties, patents, rights, etc. | C59: 5305 | Z59: =IF(A59=1,SUM($A$6:$A59),0) | AA59: =INDEX(activity,AB59,$AA$1) -> 0 | AB59: 48 | BA59: =SUM(E59:N59) | BB59: =BA59
A60: =IF(OR(E60<>"",F60<>"",G60<>"",H60<>"",I60<>""),1,0) -> 0 | B60: Management and administration fees | C60: 5306 | Z60: =IF(A60=1,SUM($A$6:$A60),0) | AA60: =INDEX(activity,AB60,$AA$1) -> 0 | AB60: 49
A61: =IF(OR(E61<>"",F61<>"",G61<>"",H61<>"",I61<>""),1,0) -> 0 | B61: Consultancy fees | C61: 5307 | Z61: =IF(A61=1,SUM($A$6:$A61),0) | AA61: =INDEX(activity,AB61,$AA$1) -> 0 | AB61: 50
A62: =IF(OR(E62<>"",F62<>"",G62<>"",H62<>"",I62<>""),1,0) -> 0 | B62: Subsidies and grants | C62: 5308 | Z62: =IF(A62=1,SUM($A$6:$A62),0) | AA62: =INDEX(activity,AB62,$AA$1) -> 0 | AB62: 51
A63: =IF(OR(E63<>"",F63<>"",G63<>"",H63<>"",I63<>""),1,0) -> 0 | B63: Insurance recoveries | C63: 5309 | Z63: =IF(A63=1,SUM($A$6:$A63),0) | AA63: =INDEX(activity,AB63,$AA$1) -> 0 | AB63: 52
A64: =IF(OR(E64<>"",F64<>"",G64<>"",H64<>"",I64<>""),1,0) -> 0 | B64: Waiver of amounts payable | C64: 5310 | Z64: =IF(A64=1,SUM($A$6:$A64),0) | AA64: =INDEX(activity,AB64,$AA$1) -> 0 | AB64: 53
A65: =IF(OR(E65<>"",F65<>"",G65<>"",H65<>"",I65<>""),1,0) -> 0 | B65: Bad debt recoveries | C65: 5311 | W65: =SUM(E65:I65) | Z65: =IF(A65=1,SUM($A$6:$A65),0) | AA65: =INDEX(activity,AB65,$AA$1) -> 0 | AB65: 54
A66: =IF(OR(E66<>"",F66<>"",G66<>"",H66<>"",I66<>""),1,0) -> 1 | B66: Total revenue from other sources | C66: 5498 | E66: =SUM(E25:E65) | F66: =SUM(F25:F65) | G66: =SUM(G25:G65) -> 0 | H66: =SUM(H25:H65) -> 0 | I66: =SUM(I25:I65) -> 0 | J66: =SUM(J25:J65) -> 0 | K66: =SUM(K25:K65) -> 0 | L66: =SUM(L25:L65) -> 0 | ... N66: =SUM(N25:N65) -> 0 | Z66: =IF(A66=1,SUM($A$6:$A66),0) | AA66: =INDEX(activity,AB66,$AA$1) -> -53618 | AB66: 55 | CA66: 1
A67: 1 | B67: TOTAL REVENUE | C67: 5499 | D67: =IF(O67<>$C$3,man,IF(Q67<>Q68,"Check!","")) | E67: =E68 | O67: =COUNT(E67:N67) | P67: =IF(D67<>"",1,0) | Q67: =SUM(E67:N67) | Y67: 1 | Z67: =IF(A67=1,SUM($A$6:$A67),0) | AA67: =INDEX(activity,AB67,$AA$1) -> -734841 | AB67: 56 | CA67: 1 | CB67: 1
A68: 0 | E68: =E66+E24 | F68: =F66+F24 | G68: =G66+G24 -> 0 | H68: =H66+H24 -> 0 | I68: =I66+I24 -> 0 | J68: =J66+J24 -> 0 | K68: =K66+K24 -> 0 | L68: =L66+L24 -> 0 | ... N68: =N66+N24 -> 0 | Q68: =SUM(E68:N68) | Z68: =IF(A68=1,SUM($A$6:$A68),0) | AA68: =INDEX(activity,AB68,$AA$1) -> -734841 | AB68: 57
A69: =IF(OR(E69<>"",F69<>"",G69<>"",H69<>"",I69<>""),1,0) -> 0 | B69: Opening stock | C69: 5500 | Z69: =IF(A69=1,SUM($A$6:$A69),0) | AA69: =INDEX(activity,AB69,$AA$1) -> 0 | AB69: 58
A70: =IF(OR(E70<>"",F70<>"",G70<>"",H70<>"",I70<>""),1,0) -> 0 | B70: Opening stock of raw materials and / or semi-finished goods | C70: 5501 | Z70: =IF(A70=1,SUM($A$6:$A70),0) | AA70: =INDEX(activity,AB70,$AA$1) -> 0 | AB70: 59
A71: =IF(OR(E71<>"",F71<>"",G71<>"",H71<>"",I71<>""),1,0) -> 0 | B71: Opening Stock of Work-in-Progress | C71: 5502 | Z71: =IF(A71=1,SUM($A$6:$A71),0) | AA71: =INDEX(activity,AB71,$AA$1) -> 0 | AB71: 60
A72: =IF(OR(E72<>"",F72<>"",G72<>"",H72<>"",I72<>""),1,0) -> 0 | B72: Opening Stock of Finished Goods | C72: 5503 | Z72: =IF(A72=1,SUM($A$6:$A72),0) | AA72: =INDEX(activity,AB72,$AA$1) -> 0 | AB72: 61
A73: =IF(OR(E73<>"",F73<>"",G73<>"",H73<>"",I73<>""),1,0) -> 0 | B73: Property held for Development & Resale at beginning of period | C73: 5504 | Z73: =IF(A73=1,SUM($A$6:$A73),0) | AA73: =INDEX(activity,AB73,$AA$1) -> 0 | AB73: 62
A74: =IF(OR(E74<>"",F74<>"",G74<>"",H74<>"",I74<>""),1,0) -> 0 | B74: Purchases | C74: 5550 | Z74: =IF(A74=1,SUM($A$6:$A74),0) | AA74: =INDEX(activity,AB74,$AA$1) -> 0 | AB74: 63
A75: =IF(OR(E75<>"",F75<>"",G75<>"",H75<>"",I75<>""),1,0) -> 0 | B75: Imports of Raw Materials and / or Semi-Finished Goods | C75: 5551 | Z75: =IF(A75=1,SUM($A$6:$A75),0) | AA75: =INDEX(activity,AB75,$AA$1) -> 0 | AB75: 64
A76: =IF(OR(E76<>"",F76<>"",G76<>"",H76<>"",I76<>""),1,0) -> 0 | B76: Local Purchases of Raw Materials and / or Semi-Finished Goods | C76: 5552 | Z76: =IF(A76=1,SUM($A$6:$A76),0) | AA76: =INDEX(activity,AB76,$AA$1) -> 0 | AB76: 65
A77: =IF(OR(E77<>"",F77<>"",G77<>"",H77<>"",I77<>""),1,0) | B77: Imports of Finished Goods | C77: 5553 | Z77: =IF(A77=1,SUM($A$6:$A77),0) | AA77: =INDEX(activity,AB77,$AA$1) | AB77: 66
A78: =IF(OR(E78<>"",F78<>"",G78<>"",H78<>"",I78<>""),1,0) -> 0 | B78: Freight, Insurance and Duty on Imported Goods | C78: 5554 | Z78: =IF(A78=1,SUM($A$6:$A78),0) | AA78: =INDEX(activity,AB78,$AA$1) -> 0 | AB78: 67
A79: =IF(OR(E79<>"",F79<>"",G79<>"",H79<>"",I79<>""),1,0) -> 0 | B79: Local Purchases of Finished Goods | C79: 5555 | Z79: =IF(A79=1,SUM($A$6:$A79),0) | AA79: =INDEX(activity,AB79,$AA$1) -> 0 | AB79: 68
A80: =IF(OR(E80<>"",F80<>"",G80<>"",H80<>"",I80<>""),1,0) -> 0 | B80: Carriage Inwards | C80: 5556 | Z80: =IF(A80=1,SUM($A$6:$A80),0) | AA80: =INDEX(activity,AB80,$AA$1) -> 0 | AB80: 69
... A82: =IF(OR(E82<>"",F82<>"",G82<>"",H82<>"",I82<>""),1,0) -> 0 | B82: Direct Costs | C82: 5600 | Z82: =IF(A82=1,SUM($A$6:$A82),0) | AA82: =INDEX(activity,AB82,$AA$1) -> 0 | AB82: 71
A83: =IF(OR(E83<>"",F83<>"",G83<>"",H83<>"",I83<>""),1,0) -> 0 | B83: Direct productive wages | C83: 5601 | Z83: =IF(A83=1,SUM($A$6:$A83),0) | AA83: =INDEX(activity,AB83,$AA$1) -> 0 | AB83: 72 | BA83: =SUM(E83:N83)
A84: =IF(OR(E84<>"",F84<>"",G84<>"",H84<>"",I84<>""),1,0) -> 0 | B84: Subcontracting | C84: 5602 | Z84: =IF(A84=1,SUM($A$6:$A84),0) | AA84: =INDEX(activity,AB84,$AA$1) -> 0 | AB84: 73
A85: =IF(OR(E85<>"",F85<>"",G85<>"",H85<>"",I85<>""),1,0) -> 0 | B85: Hire of Machinery & Equipment | C85: 5603 | Z85: =IF(A85=1,SUM($A$6:$A85),0) | AA85: =INDEX(activity,AB85,$AA$1) -> 0 | AB85: 74
A86: =IF(OR(E86<>"",F86<>"",G86<>"",H86<>"",I86<>""),1,0) -> 0 | B86: Rent of factory premises | C86: 5604 | Z86: =IF(A86=1,SUM($A$6:$A86),0) | AA86: =INDEX(activity,AB86,$AA$1) -> 0 | AB86: 75
A87: =IF(OR(E87<>"",F87<>"",G87<>"",H87<>"",I87<>""),1,0) -> 0 | B87: Development expenses | C87: 5605 | Z87: =IF(A87=1,SUM($A$6:$A87),0) | AA87: =INDEX(activity,AB87,$AA$1) -> 0 | AB87: 76
A88: =IF(OR(E88<>"",F88<>"",G88<>"",H88<>"",I88<>""),1,0) -> 0 | B88: Royalty costs | C88: 5606 | Z88: =IF(A88=1,SUM($A$6:$A88),0) | AA88: =INDEX(activity,AB88,$AA$1) -> 0 | AB88: 77
A89: =IF(OR(E89<>"",F89<>"",G89<>"",H89<>"",I89<>""),1,0) -> 0 | B89: Stock write down | C89: 5607 | Z89: =IF(A89=1,SUM($A$6:$A89),0) | AA89: =INDEX(activity,AB89,$AA$1) -> 0 | AB89: 78
A90: =IF(OR(E90<>"",F90<>"",G90<>"",H90<>"",I90<>""),1,0) -> 0 | B90: Depreciation of Industrial Building or Structure | C90: 5608 | Z90: =IF(A90=1,SUM($A$6:$A90),0) | AA90: =INDEX(activity,AB90,$AA$1) -> 0 | AB90: 79 | BB90: =SUM(E90:N90)
A91: =IF(OR(E91<>"",F91<>"",G91<>"",H91<>"",I91<>""),1,0) -> 0 | B91: Depreciation of production machinery and equipment | C91: 5609 | Z91: =IF(A91=1,SUM($A$6:$A91),0) | AA91: =INDEX(activity,AB91,$AA$1) -> 0 | AB91: 80 | BB91: =SUM(E91:N91)
A92: =IF(OR(E92<>"",F92<>"",G92<>"",H92<>"",I92<>""),1,0) -> 0 | B92: Depreciation of Factory Plant | C92: 5610 | Z92: =IF(A92=1,SUM($A$6:$A92),0) | AA92: =INDEX(activity,AB92,$AA$1) -> 0 | AB92: 81 | BB92: =SUM(E92:N92)
A93: =IF(OR(E93<>"",F93<>"",G93<>"",H93<>"",I93<>""),1,0) -> 0 | B93: Overhead expenses allocated to cost of sales | C93: 5611 | Z93: =IF(A93=1,SUM($A$6:$A93),0) | AA93: =INDEX(activity,AB93,$AA$1) -> 0 | AB93: 82
A94: =IF(OR(E94<>"",F94<>"",G94<>"",H94<>"",I94<>""),1,0) -> 0 | B94: Closing stock | C94: 5700 | Z94: =IF(A94=1,SUM($A$6:$A94),0) | AA94: =INDEX(activity,AB94,$AA$1) -> 0 | AB94: 83
A95: =IF(OR(E95<>"",F95<>"",G95<>"",H95<>"",I95<>""),1,0) -> 0 | B95: Closing stock of raw materials and / or semi-finished goods | C95: 5701 | Z95: =IF(A95=1,SUM($A$6:$A95),0) | AA95: =INDEX(activity,AB95,$AA$1) -> 0 | AB95: 84
A96: =IF(OR(E96<>"",F96<>"",G96<>"",H96<>"",I96<>""),1,0) -> 0 | B96: Closing Stock of Work-in-Progress | C96: 5702 | Z96: =IF(A96=1,SUM($A$6:$A96),0) | AA96: =INDEX(activity,AB96,$AA$1) -> 0 | AB96: 85
A97: =IF(OR(E97<>"",F97<>"",G97<>"",H97<>"",I97<>""),1,0) -> 0 | B97: Closing Stock of Finished Goods | C97: 5703 | Z97: =IF(A97=1,SUM($A$6:$A97),0) | AA97: =INDEX(activity,AB97,$AA$1) -> 0 | AB97: 86
A98: =IF(OR(E98<>"",F98<>"",G98<>"",H98<>"",I98<>""),1,0) -> 0 | B98: Property held for Development & Resale at end of period | C98: 5704 | Z98: =IF(A98=1,SUM($A$6:$A98),0) | AA98: =INDEX(activity,AB98,$AA$1) -> 0 | AB98: 87
A99: =IF(OR(E99<>"",F99<>"",G99<>"",H99<>"",I99<>""),1,0) -> 1 | B99: COST OF SALES | C99: 5998 | D99: =IF(O99<>$C$3,man,IF(Q99<>Q100,"Check!","")) | E99: =E100 | O99: =COUNT(E99:N99) | P99: =IF(D99<>"",1,0) | Q99: =SUM(E99:N99) | Y99: 1 | Z99: =IF(A99=1,SUM($A$6:$A99),0) | AA99: =INDEX(activity,AB99,$AA$1) -> 0 | AB99: 88 | CA99: 1 | CB99: 1
A100: 0 | E100: =SUM(E69:E98) | F100: =SUM(F69:F98) | G100: =SUM(G69:G98) -> 0 | H100: =SUM(H69:H98) -> 0 | I100: =SUM(I69:I98) -> 0 | J100: =SUM(J69:J98) -> 0 | K100: =SUM(K69:K98) -> 0 | L100: =SUM(L69:L98) -> 0 | ... N100: =SUM(N69:N98) -> 0 | Q100: =SUM(E100:N100) | Z100: =IF(A100=1,SUM($A$6:$A100),0) | AA100: =INDEX(activity,AB100,$AA$1) -> 0 | AB100: 89
A101: =IF(OR(E101<>"",F101<>"",G101<>"",H101<>"",I101<>""),1,0) -> 0 | B101: Gross Profit or loss | C101: 5999 | Z101: =IF(A101=1,SUM($A$6:$A101),0) | AA101: =INDEX(activity,AB101,$AA$1) -> 0 | AB101: 90
A102: =IF(OR(E102<>"",F102<>"",G102<>"",H102<>"",I102<>""),1,0) -> 0 | B102: Advertising and promotion | C102: 6000 | Z102: =IF(A102=1,SUM($A$6:$A102),0) | AA102: =INDEX(activity,AB102,$AA$1) -> 0 | AB102: 91
A103: =IF(OR(E103<>"",F103<>"",G103<>"",H103<>"",I103<>""),1,0) -> 1 | B103: Advertising | C103: 6001 | Z103: =IF(A103=1,SUM($A$6:$A103),0) | AA103: =INDEX(activity,AB103,$AA$1) -> 152403 | AB103: 92
A104: =IF(OR(E104<>"",F104<>"",G104<>"",H104<>"",I104<>""),1,0) -> 0 | B104: Promotion | C104: 6002 | Z104: =IF(A104=1,SUM($A$6:$A104),0) | AA104: =INDEX(activity,AB104,$AA$1) -> 0 | AB104: 93
...

Sheet Income_Summary
L1: =IF(OR(D6<> 0,D8<>0),0,1) | M1: =IF(OR(E6<> 0,E8<>0),0,1) | N1: =IF(OR(F6<> 0,F8<>0),0,1) | O1: =IF(OR(G6<> 0,G8<>0),0,1) | P1: =IF(OR(H6<> 0,H8<>0),0,1)
B4: =Income!B5
B5: Item Description | C5: Code
B6: =IF(ROW() -5<= MAX(Income!$Z$6:$Z$289),INDEX(Income!$B$6:$Z$289,MATCH(ROW()-5,Income!$Z$6:$Z$289,0),1),"") | C6: =IF(ROW() -5<= MAX(Income!$Z$6:$Z$289),INDEX(Income!$B$6:$Z$289,MATCH(ROW()-5,Income!$Z$6:$Z$289,0),2),"") | D6: =IF(ROW() -5<= MAX(Income!$Z$6:$Z$289),INDEX(Income!$B$6:$Z$289,MATCH(ROW()-5,Income!$Z$6:$Z$289,0),4),"") | E6: =IF(ROW() -5<= MAX(Income!$Z$6:$Z$289),INDEX(Income!$C$6:$Z$289,MATCH(ROW()-5,Income!$Z$6:$Z$289,0),4),"") | F6: =IF(ROW() -5<= MAX(Income!$Z$6:$Z$289),INDEX(Income!$D$6:$Z$289,MATCH(ROW()-5,Income!$Z$6:$Z$289,0),4),"") | G6: =IF(ROW() -5<= MAX(Income!$Z$6:$Z$289),INDEX(Income!$E$6:$Z$289,MATCH(ROW()-5,Income!$Z$6:$Z$289,0),4),"") | H6: =IF(ROW() -5<= MAX(Income!$Z$6:$Z$289),INDEX(Income!$F$6:$Z$289,MATCH(ROW()-5,Income!$Z$6:$Z$289,0),4),"") | K6: =IF(ROW() -5<= MAX(Income!$Z$6:$Z$289),INDEX(Income!$B$6:$Z$289,MATCH(ROW()-5,Income!$Z$6:$Z$289,0),24),"")
K7: =IF(ROW() -5<= MAX(Income!$Z$6:$Z$289),INDEX(Income!$B$6:$Z$289,MATCH(ROW()-5,Income!$Z$6:$Z$289,0),24),"")
B8: =IF(ROW() -5<= MAX(Income!$Z$6:$Z$289),INDEX(Income!$B$6:$Z$289,MATCH(ROW()-5,Income!$Z$6:$Z$289,0),1),"") | C8: =IF(ROW() -5<= MAX(Income!$Z$6:$Z$289),INDEX(Income!$B$6:$Z$289,MATCH(ROW()-5,Income!$Z$6:$Z$289,0),2),"") | D8: =IF(ROW() -5<= MAX(Income!$Z$6:$Z$289),INDEX(Income!$B$6:$Z$289,MATCH(ROW()-5,Income!$Z$6:$Z$289,0),4),"") | E8: =IF(ROW() -5<= MAX(Income!$Z$6:$Z$289),INDEX(Income!$C$6:$Z$289,MATCH(ROW()-5,Income!$Z$6:$Z$289,0),4),"") | F8: =IF(ROW() -5<= MAX(Income!$Z$6:$Z$289),INDEX(Income!$D$6:$Z$289,MATCH(ROW()-5,Income!$Z$6:$Z$289,0),4),"") | G8: =IF(ROW() -5<= MAX(Income!$Z$6:$Z$289),INDEX(Income!$E$6:$Z$289,MATCH(ROW()-5,Income!$Z$6:$Z$289,0),4),"") | H8: =IF(ROW() -5<= MAX(Income!$Z$6:$Z$289),INDEX(Income!$F$6:$Z$289,MATCH(ROW()-5,Income!$Z$6:$Z$289,0),4),"") | K8: =IF(ROW() -5<= MAX(Income!$Z$6:$Z$289),INDEX(Income!$B$6:$Z$289,MATCH(ROW()-5,Income!$Z$6:$Z$289,0),24),"")
K9: =IF(ROW() -5<= MAX(Income!$Z$6:$Z$289),INDEX(Income!$B$6:$Z$289,MATCH(ROW()-5,Income!$Z$6:$Z$289,0),24),"")
B10: =IF(ROW() -5<= MAX(Income!$Z$6:$Z$289),INDEX(Income!$B$6:$Z$289,MATCH(ROW()-5,Income!$Z$6:$Z$289,0),1),"") | C10: =IF(ROW() -5<= MAX(Income!$Z$6:$Z$289),INDEX(Income!$B$6:$Z$289,MATCH(ROW()-5,Income!$Z$6:$Z$289,0),2),"") | D10: =IF(ROW() -5<= MAX(Income!$Z$6:$Z$289),INDEX(Income!$B$6:$Z$289,MATCH(ROW()-5,Income!$Z$6:$Z$289,0),4),"") | E10: =IF(ROW() -5<= MAX(Income!$Z$6:$Z$289),INDEX(Income!$C$6:$Z$289,MATCH(ROW()-5,Income!$Z$6:$Z$289,0),4),"") | F10: =IF(ROW() -5<= MAX(Income!$Z$6:$Z$289),INDEX(Income!$D$6:$Z$289,MATCH(ROW()-5,Income!$Z$6:$Z$289,0),4),"") | G10: =IF(ROW() -5<= MAX(Income!$Z$6:$Z$289),INDEX(Income!$E$6:$Z$289,MATCH(ROW()-5,Income!$Z$6:$Z$289,0),4),"") | H10: =IF(ROW() -5<= MAX(Income!$Z$6:$Z$289),INDEX(Income!$F$6:$Z$289,MATCH(ROW()-5,Income!$Z$6:$Z$289,0),4),"") | K10: =IF(ROW() -5<= MAX(Income!$Z$6:$Z$289),INDEX(Income!$B$6:$Z$289,MATCH(ROW()-5,Income!$Z$6:$Z$289,0),24),"")
B11: =IF(ROW() -5<= MAX(Income!$Z$6:$Z$289),INDEX(Income!$B$6:$Z$289,MATCH(ROW()-5,Income!$Z$6:$Z$289,0),1),"") | C11: =IF(ROW() -5<= MAX(Income!$Z$6:$Z$289),INDEX(Income!$B$6:$Z$289,MATCH(ROW()-5,Income!$Z$6:$Z$289,0),2),"") | D11: =IF(ROW() -5<= MAX(Income!$Z$6:$Z$289),INDEX(Income!$B$6:$Z$289,MATCH(ROW()-5,Income!$Z$6:$Z$289,0),4),"") | E11: =IF(ROW() -5<= MAX(Income!$Z$6:$Z$289),INDEX(Income!$C$6:$Z$289,MATCH(ROW()-5,Income!$Z$6:$Z$289,0),4),"") | F11: =IF(ROW() -5<= MAX(Income!$Z$6:$Z$289),INDEX(Income!$D$6:$Z$289,MATCH(ROW()-5,Income!$Z$6:$Z$289,0),4),"") | G11: =IF(ROW() -5<= MAX(Income!$Z$6:$Z$289),INDEX(Income!$E$6:$Z$289,MATCH(ROW()-5,Income!$Z$6:$Z$289,0),4),"") | H11: =IF(ROW() -5<= MAX(Income!$Z$6:$Z$289),INDEX(Income!$F$6:$Z$289,MATCH(ROW()-5,Income!$Z$6:$Z$289,0),4),"") | K11: =IF(ROW() -5<= MAX(Income!$Z$6:$Z$289),INDEX(Income!$B$6:$Z$289,MATCH(ROW()-5,Income!$Z$6:$Z$289,0),24),"")
B12: =IF(ROW() -5<= MAX(Income!$Z$6:$Z$289),INDEX(Income!$B$6:$Z$289,MATCH(ROW()-5,Income!$Z$6:$Z$289,0),1),"") | C12: =IF(ROW() -5<= MAX(Income!$Z$6:$Z$289),INDEX(Income!$B$6:$Z$289,MATCH(ROW()-5,Income!$Z$6:$Z$289,0),2),"") | D12: =IF(ROW() -5<= MAX(Income!$Z$6:$Z$289),INDEX(Income!$B$6:$Z$289,MATCH(ROW()-5,Income!$Z$6:$Z$289,0),4),"") | E12: =IF(ROW() -5<= MAX(Income!$Z$6:$Z$289),INDEX(Income!$C$6:$Z$289,MATCH(ROW()-5,Income!$Z$6:$Z$289,0),4),"") | F12: =IF(ROW() -5<= MAX(Income!$Z$6:$Z$289),INDEX(Income!$D$6:$Z$289,MATCH(ROW()-5,Income!$Z$6:$Z$289,0),4),"") | G12: =IF(ROW() -5<= MAX(Income!$Z$6:$Z$289),INDEX(Income!$E$6:$Z$289,MATCH(ROW()-5,Income!$Z$6:$Z$289,0),4),"") | H12: =IF(ROW() -5<= MAX(Income!$Z$6:$Z$289),INDEX(Income!$F$6:$Z$289,MATCH(ROW()-5,Income!$Z$6:$Z$289,0),4),"") | K12: =IF(ROW() -5<= MAX(Income!$Z$6:$Z$289),INDEX(Income!$B$6:$Z$289,MATCH(ROW()-5,Income!$Z$6:$Z$289,0),24),"")
B13: =IF(ROW() -5<= MAX(Income!$Z$6:$Z$289),INDEX(Income!$B$6:$Z$289,MATCH(ROW()-5,Income!$Z$6:$Z$289,0),1),"") | C13: =IF(ROW() -5<= MAX(Income!$Z$6:$Z$289),INDEX(Income!$B$6:$Z$289,MATCH(ROW()-5,Income!$Z$6:$Z$289,0),2),"") | D13: =IF(ROW() -5<= MAX(Income!$Z$6:$Z$289),INDEX(Income!$B$6:$Z$289,MATCH(ROW()-5,Income!$Z$6:$Z$289,0),4),"") | E13: =IF(ROW() -5<= MAX(Income!$Z$6:$Z$289),INDEX(Income!$C$6:$Z$289,MATCH(ROW()-5,Income!$Z$6:$Z$289,0),4),"") | F13: =IF(ROW() -5<= MAX(Income!$Z$6:$Z$289),INDEX(Income!$D$6:$Z$289,MATCH(ROW()-5,Income!$Z$6:$Z$289,0),4),"") | G13: =IF(ROW() -5<= MAX(Income!$Z$6:$Z$289),INDEX(Income!$E$6:$Z$289,MATCH(ROW()-5,Income!$Z$6:$Z$289,0),4),"") | H13: =IF(ROW() -5<= MAX(Income!$Z$6:$Z$289),INDEX(Income!$F$6:$Z$289,MATCH(ROW()-5,Income!$Z$6:$Z$289,0),4),"") | K13: =IF(ROW() -5<= MAX(Income!$Z$6:$Z$289),INDEX(Income!$B$6:$Z$289,MATCH(ROW()-5,Income!$Z$6:$Z$289,0),24),"")
B14: =IF(ROW() -5<= MAX(Income!$Z$6:$Z$289),INDEX(Income!$B$6:$Z$289,MATCH(ROW()-5,Income!$Z$6:$Z$289,0),1),"") | C14: =IF(ROW() -5<= MAX(Income!$Z$6:$Z$289),INDEX(Income!$B$6:$Z$289,MATCH(ROW()-5,Income!$Z$6:$Z$289,0),2),"") | D14: =IF(ROW() -5<= MAX(Income!$Z$6:$Z$289),INDEX(Income!$B$6:$Z$289,MATCH(ROW()-5,Income!$Z$6:$Z$289,0),4),"") | E14: =IF(ROW() -5<= MAX(Income!$Z$6:$Z$289),INDEX(Income!$C$6:$Z$289,MATCH(ROW()-5,Income!$Z$6:$Z$289,0),4),"") | F14: =IF(ROW() -5<= MAX(Income!$Z$6:$Z$289),INDEX(Income!$D$6:$Z$289,MATCH(ROW()-5,Income!$Z$6:$Z$289,0),4),"") | G14: =IF(ROW() -5<= MAX(Income!$Z$6:$Z$289),INDEX(Income!$E$6:$Z$289,MATCH(ROW()-5,Income!$Z$6:$Z$289,0),4),"") | H14: =IF(ROW() -5<= MAX(Income!$Z$6:$Z$289),INDEX(Income!$F$6:$Z$289,MATCH(ROW()-5,Income!$Z$6:$Z$289,0),4),"") | K14: =IF(ROW() -5<= MAX(Income!$Z$6:$Z$289),INDEX(Income!$B$6:$Z$289,MATCH(ROW()-5,Income!$Z$6:$Z$289,0),24),"")
B15: =IF(ROW() -5<= MAX(Income!$Z$6:$Z$289),INDEX(Income!$B$6:$Z$289,MATCH(ROW()-5,Income!$Z$6:$Z$289,0),1),"") | C15: =IF(ROW() -5<= MAX(Income!$Z$6:$Z$289),INDEX(Income!$B$6:$Z$289,MATCH(ROW()-5,Income!$Z$6:$Z$289,0),2),"") | D15: =IF(ROW() -5<= MAX(Income!$Z$6:$Z$289),INDEX(Income!$B$6:$Z$289,MATCH(ROW()-5,Income!$Z$6:$Z$289,0),4),"") | E15: =IF(ROW() -5<= MAX(Income!$Z$6:$Z$289),INDEX(Income!$C$6:$Z$289,MATCH(ROW()-5,Income!$Z$6:$Z$289,0),4),"") | F15: =IF(ROW() -5<= MAX(Income!$Z$6:$Z$289),INDEX(Income!$D$6:$Z$289,MATCH(ROW()-5,Income!$Z$6:$Z$289,0),4),"") | G15: =IF(ROW() -5<= MAX(Income!$Z$6:$Z$289),INDEX(Income!$E$6:$Z$289,MATCH(ROW()-5,Income!$Z$6:$Z$289,0),4),"") | H15: =IF(ROW() -5<= MAX(Income!$Z$6:$Z$289),INDEX(Income!$F$6:$Z$289,MATCH(ROW()-5,Income!$Z$6:$Z$289,0),4),"") | K15: =IF(ROW() -5<= MAX(Income!$Z$6:$Z$289),INDEX(Income!$B$6:$Z$289,MATCH(ROW()-5,Income!$Z$6:$Z$289,0),24),"")
B16: =IF(ROW() -5<= MAX(Income!$Z$6:$Z$289),INDEX(Income!$B$6:$Z$289,MATCH(ROW()-5,Income!$Z$6:$Z$289,0),1),"") | C16: =IF(ROW() -5<= MAX(Income!$Z$6:$Z$289),INDEX(Income!$B$6:$Z$289,MATCH(ROW()-5,Income!$Z$6:$Z$289,0),2),"") | D16: =IF(ROW() -5<= MAX(Income!$Z$6:$Z$289),INDEX(Income!$B$6:$Z$289,MATCH(ROW()-5,Income!$Z$6:$Z$289,0),4),"") | E16: =IF(ROW() -5<= MAX(Income!$Z$6:$Z$289),INDEX(Income!$C$6:$Z$289,MATCH(ROW()-5,Income!$Z$6:$Z$289,0),4),"") | F16: =IF(ROW() -5<= MAX(Income!$Z$6:$Z$289),INDEX(Income!$D$6:$Z$289,MATCH(ROW()-5,Income!$Z$6:$Z$289,0),4),"") | G16: =IF(ROW() -5<= MAX(Income!$Z$6:$Z$289),INDEX(Income!$E$6:$Z$289,MATCH(ROW()-5,Income!$Z$6:$Z$289,0),4),"") | H16: =IF(ROW() -5<= MAX(Income!$Z$6:$Z$289),INDEX(Income!$F$6:$Z$289,MATCH(ROW()-5,Income!$Z$6:$Z$289,0),4),"") | K16: =IF(ROW() -5<= MAX(Income!$Z$6:$Z$289),INDEX(Income!$B$6:$Z$289,MATCH(ROW()-5,Income!$Z$6:$Z$289,0),24),"")
B17: =IF(ROW() -5<= MAX(Income!$Z$6:$Z$289),INDEX(Income!$B$6:$Z$289,MATCH(ROW()-5,Income!$Z$6:$Z$289,0),1),"") | C17: =IF(ROW() -5<= MAX(Income!$Z$6:$Z$289),INDEX(Income!$B$6:$Z$289,MATCH(ROW()-5,Income!$Z$6:$Z$289,0),2),"") | D17: =IF(ROW() -5<= MAX(Income!$Z$6:$Z$289),INDEX(Income!$B$6:$Z$289,MATCH(ROW()-5,Income!$Z$6:$Z$289,0),4),"") | E17: =IF(ROW() -5<= MAX(Income!$Z$6:$Z$289),INDEX(Income!$C$6:$Z$289,MATCH(ROW()-5,Income!$Z$6:$Z$289,0),4),"") | F17: =IF(ROW() -5<= MAX(Income!$Z$6:$Z$289),INDEX(Income!$D$6:$Z$289,MATCH(ROW()-5,Income!$Z$6:$Z$289,0),4),"") | G17: =IF(ROW() -5<= MAX(Income!$Z$6:$Z$289),INDEX(Income!$E$6:$Z$289,MATCH(ROW()-5,Income!$Z$6:$Z$289,0),4),"") | H17: =IF(ROW() -5<= MAX(Income!$Z$6:$Z$289),INDEX(Income!$F$6:$Z$289,MATCH(ROW()-5,Income!$Z$6:$Z$289,0),4),"") | K17: =IF(ROW() -5<= MAX(Income!$Z$6:$Z$289),INDEX(Income!$B$6:$Z$289,MATCH(ROW()-5,Income!$Z$6:$Z$289,0),24),"")
B18: =IF(ROW() -5<= MAX(Income!$Z$6:$Z$289),INDEX(Income!$B$6:$Z$289,MATCH(ROW()-5,Income!$Z$6:$Z$289,0),1),"") | C18: =IF(ROW() -5<= MAX(Income!$Z$6:$Z$289),INDEX(Income!$B$6:$Z$289,MATCH(ROW()-5,Income!$Z$6:$Z$289,0),2),"") | D18: =IF(ROW() -5<= MAX(Income!$Z$6:$Z$289),INDEX(Income!$B$6:$Z$289,MATCH(ROW()-5,Income!$Z$6:$Z$289,0),4),"") | E18: =IF(ROW() -5<= MAX(Income!$Z$6:$Z$289),INDEX(Income!$C$6:$Z$289,MATCH(ROW()-5,Income!$Z$6:$Z$289,0),4),"") | F18: =IF(ROW() -5<= MAX(Income!$Z$6:$Z$289),INDEX(Income!$D$6:$Z$289,MATCH(ROW()-5,Income!$Z$6:$Z$289,0),4),"") | G18: =IF(ROW() -5<= MAX(Income!$Z$6:$Z$289),INDEX(Income!$E$6:$Z$289,MATCH(ROW()-5,Income!$Z$6:$Z$289,0),4),"") | H18: =IF(ROW() -5<= MAX(Income!$Z$6:$Z$289),INDEX(Income!$F$6:$Z$289,MATCH(ROW()-5,Income!$Z$6:$Z$289,0),4),"") | K18: =IF(ROW() -5<= MAX(Income!$Z$6:$Z$289),INDEX(Income!$B$6:$Z$289,MATCH(ROW()-5,Income!$Z$6:$Z$289,0),24),"")
B19: =IF(ROW() -5<= MAX(Income!$Z$6:$Z$289),INDEX(Income!$B$6:$Z$289,MATCH(ROW()-5,Income!$Z$6:$Z$289,0),1),"") | C19: =IF(ROW() -5<= MAX(Income!$Z$6:$Z$289),INDEX(Income!$B$6:$Z$289,MATCH(ROW()-5,Income!$Z$6:$Z$289,0),2),"") | D19: =IF(ROW() -5<= MAX(Income!$Z$6:$Z$289),INDEX(Income!$B$6:$Z$289,MATCH(ROW()-5,Income!$Z$6:$Z$289,0),4),"") | E19: =IF(ROW() -5<= MAX(Income!$Z$6:$Z$289),INDEX(Income!$C$6:$Z$289,MATCH(ROW()-5,Income!$Z$6:$Z$289,0),4),"") | F19: =IF(ROW() -5<= MAX(Income!$Z$6:$Z$289),INDEX(Income!$D$6:$Z$289,MATCH(ROW()-5,Income!$Z$6:$Z$289,0),4),"") | G19: =IF(ROW() -5<= MAX(Income!$Z$6:$Z$289),INDEX(Income!$E$6:$Z$289,MATCH(ROW()-5,Income!$Z$6:$Z$289,0),4),"") | H19: =IF(ROW() -5<= MAX(Income!$Z$6:$Z$289),INDEX(Income!$F$6:$Z$289,MATCH(ROW()-5,Income!$Z$6:$Z$289,0),4),"") | K19: =IF(ROW() -5<= MAX(Income!$Z$6:$Z$289),INDEX(Income!$B$6:$Z$289,MATCH(ROW()-5,Income!$Z$6:$Z$289,0),24),"")
B20: =IF(ROW() -5<= MAX(Income!$Z$6:$Z$289),INDEX(Income!$B$6:$Z$289,MATCH(ROW()-5,Income!$Z$6:$Z$289,0),1),"") | C20: =IF(ROW() -5<= MAX(Income!$Z$6:$Z$289),INDEX(Income!$B$6:$Z$289,MATCH(ROW()-5,Income!$Z$6:$Z$289,0),2),"") | D20: =IF(ROW() -5<= MAX(Income!$Z$6:$Z$289),INDEX(Income!$B$6:$Z$289,MATCH(ROW()-5,Income!$Z$6:$Z$289,0),4),"") | E20: =IF(ROW() -5<= MAX(Income!$Z$6:$Z$289),INDEX(Income!$C$6:$Z$289,MATCH(ROW()-5,Income!$Z$6:$Z$289,0),4),"") | F20: =IF(ROW() -5<= MAX(Income!$Z$6:$Z$289),INDEX(Income!$D$6:$Z$289,MATCH(ROW()-5,Income!$Z$6:$Z$289,0),4),"") | G20: =IF(ROW() -5<= MAX(Income!$Z$6:$Z$289),INDEX(Income!$E$6:$Z$289,MATCH(ROW()-5,Income!$Z$6:$Z$289,0),4),"") | H20: =IF(ROW() -5<= MAX(Income!$Z$6:$Z$289),INDEX(Income!$F$6:$Z$289,MATCH(ROW()-5,Income!$Z$6:$Z$289,0),4),"") | K20: =IF(ROW() -5<= MAX(Income!$Z$6:$Z$289),INDEX(Income!$B$6:$Z$289,MATCH(ROW()-5,Income!$Z$6:$Z$289,0),24),"")
B21: =IF(ROW() -5<= MAX(Income!$Z$6:$Z$289),INDEX(Income!$B$6:$Z$289,MATCH(ROW()-5,Income!$Z$6:$Z$289,0),1),"") | C21: =IF(ROW() -5<= MAX(Income!$Z$6:$Z$289),INDEX(Income!$B$6:$Z$289,MATCH(ROW()-5,Income!$Z$6:$Z$289,0),2),"") | D21: =IF(ROW() -5<= MAX(Income!$Z$6:$Z$289),INDEX(Income!$B$6:$Z$289,MATCH(ROW()-5,Income!$Z$6:$Z$289,0),4),"") | E21: =IF(ROW() -5<= MAX(Income!$Z$6:$Z$289),INDEX(Income!$C$6:$Z$289,MATCH(ROW()-5,Income!$Z$6:$Z$289,0),4),"") | F21: =IF(ROW() -5<= MAX(Income!$Z$6:$Z$289),INDEX(Income!$D$6:$Z$289,MATCH(ROW()-5,Income!$Z$6:$Z$289,0),4),"") | G21: =IF(ROW() -5<= MAX(Income!$Z$6:$Z$289),INDEX(Income!$E$6:$Z$289,MATCH(ROW()-5,Income!$Z$6:$Z$289,0),4),"") | H21: =IF(ROW() -5<= MAX(Income!$Z$6:$Z$289),INDEX(Income!$F$6:$Z$289,MATCH(ROW()-5,Income!$Z$6:$Z$289,0),4),"") | K21: =IF(ROW() -5<= MAX(Income!$Z$6:$Z$289),INDEX(Income!$B$6:$Z$289,MATCH(ROW()-5,Income!$Z$6:$Z$289,0),24),"")
... B288: =IF(ROW() -5<= MAX(Income!$Z$6:$Z$289),INDEX(Income!$B$6:$Z$289,MATCH(ROW()-5,Income!$Z$6:$Z$289,0),1),"") | C288: =IF(ROW() -5<= MAX(Income!$Z$6:$Z$289),INDEX(Income!$B$6:$Z$289,MATCH(ROW()-5,Income!$Z$6:$Z$289,0),2),"") | D288: =IF(ROW() -5<= MAX(Income!$Z$6:$Z$289),INDEX(Income!$B$6:$Z$289,MATCH(ROW()-5,Income!$Z$6:$Z$289,0),4),"") | E288: =IF(ROW() -5<= MAX(Income!$Z$6:$Z$289),INDEX(Income!$C$6:$Z$289,MATCH(ROW()-5,Income!$Z$6:$Z$289,0),4),"") | F288: =IF(ROW() -5<= MAX(Income!$Z$6:$Z$289),INDEX(Income!$D$6:$Z$289,MATCH(ROW()-5,Income!$Z$6:$Z$289,0),4),"") | G288: =IF(ROW() -5<= MAX(Income!$Z$6:$Z$289),INDEX(Income!$E$6:$Z$289,MATCH(ROW()-5,Income!$Z$6:$Z$289,0),4),"") | H288: =IF(ROW() -5<= MAX(Income!$Z$6:$Z$289),INDEX(Income!$F$6:$Z$289,MATCH(ROW()-5,Income!$Z$6:$Z$289,0),4),"") | K288: =IF(ROW() -5<= MAX(Income!$Z$6:$Z$289),INDEX(Income!$B$6:$Z$289,MATCH(ROW()-5,Income!$Z$6:$Z$289,0),24),"")

Sheet TRA1
B1: =_ref1 | G1: =_YA1
B2: ITA - Article 14(1)(h) - Scientific Research
B3: Has the scientific research been carried out in Malta? | G3: Yes | I3: =IF(H3="",0,1) | J3: =IF(G3=B65,1,0)
B4: Are you exercising the option to inflate the expenditure by 50%? | G4: No | I4: =IF(H4="",0,1) | J4: =IF(G4=B65,1,0) | K4: =SUM(J3:J4)
B5: Please indicate the turnover for the year | I5: =IF(H5="",0,1) | J5: =IF(ISBLANK(G5),0,1)
J6: =SUM(J3:J5) | K6: =COUNTA(B10:G20,B23:G37,F42,F51)
B7: ALL EXPENDITURE INCURRED ON OR AFTER 1 JANUARY 2005 MUST BE REFLECTED IN TRA 42
B8: Details of expenditure on scientific research | G8: Amount
B9: Capital expenditure [in respect of which no deductions are allowed under par. (f) and (j) of the I.T.Act]
H10: =IF(J10=0,"",IF(J10=2,"","All details!")) | I10: =IF(H10="",0,1) | J10: =COUNTA(B10,G10)
H11: =IF(J11=0,"",IF(J11=2,"","All details!")) | I11: =IF(H11="",0,1) -> 0 | J11: =COUNTA(B11,G11)
H12: =IF(J12=0,"",IF(J12=2,"","All details!")) | I12: =IF(H12="",0,1) -> 0 | J12: =COUNTA(B12,G12) -> 0
H13: =IF(J13=0,"",IF(J13=2,"","All details!")) | I13: =IF(H13="",0,1) -> 0 | J13: =COUNTA(B13,G13) -> 0
H14: =IF(J14=0,"",IF(J14=2,"","All details!")) | I14: =IF(H14="",0,1) -> 0 | J14: =COUNTA(B14,G14) -> 0
H15: =IF(J15=0,"",IF(J15=2,"","All details!")) | I15: =IF(H15="",0,1) -> 0 | J15: =COUNTA(B15,G15) -> 0
H16: =IF(J16=0,"",IF(J16=2,"","All details!")) | I16: =IF(H16="",0,1) -> 0 | J16: =COUNTA(B16,G16) -> 0
H17: =IF(J17=0,"",IF(J17=2,"","All details!")) | I17: =IF(H17="",0,1) -> 0 | J17: =COUNTA(B17,G17) -> 0
H18: =IF(J18=0,"",IF(J18=2,"","All details!")) | I18: =IF(H18="",0,1) -> 0 | J18: =COUNTA(B18,G18) -> 0
H19: =IF(J19=0,"",IF(J19=2,"","All details!")) | I19: =IF(H19="",0,1) -> 0 | J19: =COUNTA(B19,G19) -> 0
H20: =IF(J20=0,"",IF(J20=2,"","All details!")) | I20: =IF(H20="",0,1) -> 0 | J20: =COUNTA(B20,G20) -> 0
B21: Total scientific research expenditure of a capital nature | G21: =SUM(G10:G20)
B22: Other expenditure on scientific research
H23: =IF(J23=0,"",IF(J23=2,"","All details!")) | I23: =IF(H23="",0,1) -> 0 | J23: =COUNTA(B23,G23) -> 0
H24: =IF(J24=0,"",IF(J24=2,"","All details!")) | I24: =IF(H24="",0,1) -> 0 | J24: =COUNTA(B24,G24) -> 0
H25: =IF(J25=0,"",IF(J25=2,"","All details!")) | I25: =IF(H25="",0,1) -> 0 | J25: =COUNTA(B25,G25) -> 0
H26: =IF(J26=0,"",IF(J26=2,"","All details!")) | I26: =IF(H26="",0,1) -> 0 | J26: =COUNTA(B26,G26) -> 0
H27: =IF(J27=0,"",IF(J27=2,"","All details!")) | I27: =IF(H27="",0,1) -> 0 | J27: =COUNTA(B27,G27) -> 0
H28: =IF(J28=0,"",IF(J28=2,"","All details!")) | I28: =IF(H28="",0,1) -> 0 | J28: =COUNTA(B28,G28) -> 0
H29: =IF(J29=0,"",IF(J29=2,"","All details!")) | I29: =IF(H29="",0,1) -> 0 | J29: =COUNTA(B29,G29) -> 0
H30: =IF(J30=0,"",IF(J30=2,"","All details!")) | I30: =IF(H30="",0,1) -> 0 | J30: =COUNTA(B30,G30) -> 0
H31: =IF(J31=0,"",IF(J31=2,"","All details!")) | I31: =IF(H31="",0,1) -> 0 | J31: =COUNTA(B31,G31) -> 0
H32: =IF(J32=0,"",IF(J32=2,"","All details!")) | I32: =IF(H32="",0,1) -> 0 | J32: =COUNTA(B32,G32) -> 0
H33: =IF(J33=0,"",IF(J33=2,"","All details!")) | I33: =IF(H33="",0,1) -> 0 | J33: =COUNTA(B33,G33) -> 0
H34: =IF(J34=0,"",IF(J34=2,"","All details!")) | I34: =IF(H34="",0,1) -> 0 | J34: =COUNTA(B34,G34) -> 0
... H37: =IF(J37=0,"",IF(J37=2,"","All details!")) | I37: =IF(H37="",0,1) -> 0 | J37: =COUNTA(B37,G37)
B38: Total other scientific research expenditure | G38: =SUM(G23:G37)
B39: Total expenditure on Scientific Research incurred during the year | G39: =ROUND(G21+G38,0)
B41: One sixth of the capital expenditure that can be claimed for the year | F41: =ROUND(G21/6,0)
B42: One sixth of the capital expenditure, incurred in prior years, claimed for the year
B43: Portion of capital expenditure on Scientific Research that can be claimed for the year | G43: =F41+F42
B45: Other expenditure on scientific research that can be claimed for the year | G45: =G38
B46: Total expenditure on Scientific Research that can be claimed for the year | G46: =SUM(G45,G43)
B47: Increased deduction for the year [50% of Total expenditure on scientific research]
B48: Maximum increased deduction that can be claimed [limited to 5% of turnover]
B50: Total increased deduction that stands to be claimed for the current Y/A
B51: Increased deduction not allowed in previous years due to 5% of turnover limitation b/fwd
B52: Increased deduction disallowed due to the 5% of turnover limitation, c/fwd
B54: Total increased deduction claimed for the year | I54: =SUM(I3:I37)
B56: Total claim for scientific research for the year | G56: =IF(K4=2,G46+G54,G46) | H56: TRA 60
B57: =EUR
B58: =_xlfn.SINGLE(MTCA) | C58: =ver -> TA2_e-CO_2025_Ver 1.1 | G58: TRA 01
D60: IS ATTACHMENT COMPLETE [Y or N] ? | I60: =IF(K6=0,0,IF(I54<>0,100,IF(F60="Yes",1,100)))
B62: B A C K T O I N D E X
B65: Yes
B66: No

Sheet TRA2
A1: =_ref1 | J1: =_YA1
A2: BPA Regulation 13 - [Incentives for Job Creation]
A3: Documentation required
A4: a) Certificate issued by the Employment and Training Corporation [Regulation 13 (1)]
A5: b) Documentation referred to in Note 1 below
A6: c) Where applicable, the written approval by E.T.C., for training programmes provided by employers to qualifying individuals | AO6: Yes
A7: d) Where applicable, the written approval by ETC for claims of cash grant(s) in lieu of additional deductions. | AO7: No
A10: Particulars of Employer | D10: P.E. No. > | F10: =IF(AE34=0,"",IF(N14=0,"YOU HAVE TO INDICATE THE EMPLOYER NUMBER(S)","")) | K10: =IF(F10="",0,1) | N10: =IF($AE$34=0,0,IF(ISBLANK(E10),0,1))
D11: P.E. No. > | K11: =IF(F11="",0,1) | N11: =IF($AE$34=0,0,IF(ISBLANK(E11),0,1))
D12: P.E. No. > | K12: =IF(F12="",0,1) | N12: =IF($AE$34=0,0,IF(ISBLANK(E12),0,1))
D13: P.E. No. > | K13: =IF(F13="",0,1) | N13: =IF($AE$34=0,0,IF(ISBLANK(E13),0,1))
N14: =SUM(N10:N13)
A15: Particulars of Qualifying Individual(s) in respect of whom benefit(s) are being claimed
A16: ID number / Tax Reg. No. | B16: Name | D16: Date of Employment | E16: Wage Cost | F16: Amount set to determine Upper limit 1 | G16: Qualifies under Reg 13 … subreg. | H16: Approved Training Programme? | I16: Rate for additional deduction | J16: Additional Deduction
O17: Workings | R17: Rate | S17: Addit. DED | T17: Upper limit | AO17: (13)(a) / (b)
I18: =IF(R18=0,"",R18) | J18: =IF(U18=0,"",IF(E18="","",IF(F18="","",U18))) | L18: 0.65 | M18: 1 | N18: a & b | O18: =IF(G18<>ab,0,IF(H18="",$L$18,IF(H18="No",$L$18,$M$18))) | P18: =IF(G18<>dis,0,$L$19) | Q18: =IF(G18<>regc,0,IF(H18="",$L$20,IF(H18="No",$L$20,$M$20))) | R18: =SUM(O18:Q18) | S18: =E18*R18 | T18: =F18*1.25 | U18: =IF(S18<=T18,S18,T18) | X18: =IF(ISBLANK(A18),0,1) | Y18: =IF(ISBLANK(B18),0,1) | Z18: =IF(ISBLANK(D18),0,1) | AA18: =IF(ISBLANK(E18),0,1) | AB18: =IF(ISBLANK(F18),0,1) | AC18: =IF(ISBLANK(G18),0,1) | AD18: =IF(ISBLANK(H18),0,1) | AE18: =SUM(X18:AD18) | AG18: =IF(AE18>0,1,0) | AO18: (13)(c)
I19: =IF(R19=0,"",R19) | J19: =IF(U19=0,"",IF(F19="","",U19)) | L19: 2 | M19: 2 | N19: disabled | O19: =IF(G19<>ab,0,IF(H19="",$L$18,IF(H19="No",$L$18,$M$18))) -> 0 | P19: =IF(G19<>dis,0,$L$19) -> 0 | Q19: =IF(G19<>regc,0,IF(H19="",$L$20,IF(H19="No",$L$20,$M$20))) -> 0 | R19: =SUM(O19:Q19) -> 0 | S19: =E19*R19 -> 0 | T19: =F19*1.25 -> 0 | U19: =IF(S19<=T19,S19,T19) -> 0 | X19: =IF(ISBLANK(A19),0,1) -> 0 | Y19: =IF(ISBLANK(B19),0,1) -> 0 | Z19: =IF(ISBLANK(D19),0,1) -> 0 | AA19: =IF(ISBLANK(E19),0,1) -> 0 | AB19: =IF(ISBLANK(F19),0,1) -> 0 | AC19: =IF(ISBLANK(G19),0,1) -> 0 | AD19: =IF(ISBLANK(H19),0,1) -> 0 | AE19: =SUM(X19:AD19) -> 0 | AG19: =IF(AE19>0,1,0) -> 0 | AO19: (13)(10)
I20: =IF(R20=0,"",R20) | J20: =IF(U20=0,"",IF(F20="","",U20)) | L20: 1.5 | M20: 2 | N20: c | O20: =IF(G20<>ab,0,IF(H20="",$L$18,IF(H20="No",$L$18,$M$18))) -> 0 | P20: =IF(G20<>dis,0,$L$19) -> 0 | Q20: =IF(G20<>regc,0,IF(H20="",$L$20,IF(H20="No",$L$20,$M$20))) -> 0 | R20: =SUM(O20:Q20) -> 0 | S20: =E20*R20 -> 0 | T20: =F20*1.25 -> 0 | U20: =IF(S20<=T20,S20,T20) -> 0 | X20: =IF(ISBLANK(A20),0,1) -> 0 | Y20: =IF(ISBLANK(B20),0,1) -> 0 | Z20: =IF(ISBLANK(D20),0,1) -> 0 | AA20: =IF(ISBLANK(E20),0,1) -> 0 | AB20: =IF(ISBLANK(F20),0,1) -> 0 | AC20: =IF(ISBLANK(G20),0,1) -> 0 | AD20: =IF(ISBLANK(H20),0,1) -> 0 | AE20: =SUM(X20:AD20) -> 0 | AG20: =IF(AE20>0,1,0) -> 0
I21: =IF(R21=0,"",R21) | J21: =IF(U21=0,"",IF(F21="","",U21)) | O21: =IF(G21<>ab,0,IF(H21="",$L$18,IF(H21="No",$L$18,$M$18))) -> 0 | P21: =IF(G21<>dis,0,$L$19) -> 0 | Q21: =IF(G21<>regc,0,IF(H21="",$L$20,IF(H21="No",$L$20,$M$20))) -> 0 | R21: =SUM(O21:Q21) -> 0 | S21: =E21*R21 -> 0 | T21: =F21*1.25 -> 0 | U21: =IF(S21<=T21,S21,T21) -> 0 | X21: =IF(ISBLANK(A21),0,1) -> 0 | Y21: =IF(ISBLANK(B21),0,1) -> 0 | Z21: =IF(ISBLANK(D21),0,1) -> 0 | AA21: =IF(ISBLANK(E21),0,1) -> 0 | AB21: =IF(ISBLANK(F21),0,1) -> 0 | AC21: =IF(ISBLANK(G21),0,1) -> 0 | AD21: =IF(ISBLANK(H21),0,1) -> 0 | AE21: =SUM(X21:AD21) -> 0 | AG21: =IF(AE21>0,1,0) -> 0
I22: =IF(R22=0,"",R22) | J22: =IF(U22=0,"",IF(F22="","",U22)) | O22: =IF(G22<>ab,0,IF(H22="",$L$18,IF(H22="No",$L$18,$M$18))) -> 0 | P22: =IF(G22<>dis,0,$L$19) -> 0 | Q22: =IF(G22<>regc,0,IF(H22="",$L$20,IF(H22="No",$L$20,$M$20))) -> 0 | R22: =SUM(O22:Q22) -> 0 | S22: =E22*R22 -> 0 | T22: =F22*1.25 -> 0 | U22: =IF(S22<=T22,S22,T22) -> 0 | X22: =IF(ISBLANK(A22),0,1) -> 0 | Y22: =IF(ISBLANK(B22),0,1) -> 0 | Z22: =IF(ISBLANK(D22),0,1) -> 0 | AA22: =IF(ISBLANK(E22),0,1) -> 0 | AB22: =IF(ISBLANK(F22),0,1) -> 0 | AC22: =IF(ISBLANK(G22),0,1) -> 0 | AD22: =IF(ISBLANK(H22),0,1) -> 0 | AE22: =SUM(X22:AD22) -> 0 | AG22: =IF(AE22>0,1,0) -> 0
I23: =IF(R23=0,"",R23) | J23: =IF(U23=0,"",IF(F23="","",U23)) | O23: =IF(G23<>ab,0,IF(H23="",$L$18,IF(H23="No",$L$18,$M$18))) -> 0 | P23: =IF(G23<>dis,0,$L$19) -> 0 | Q23: =IF(G23<>regc,0,IF(H23="",$L$20,IF(H23="No",$L$20,$M$20))) -> 0 | R23: =SUM(O23:Q23) -> 0 | S23: =E23*R23 -> 0 | T23: =F23*1.25 -> 0 | U23: =IF(S23<=T23,S23,T23) -> 0 | X23: =IF(ISBLANK(A23),0,1) -> 0 | Y23: =IF(ISBLANK(B23),0,1) -> 0 | Z23: =IF(ISBLANK(D23),0,1) -> 0 | AA23: =IF(ISBLANK(E23),0,1) -> 0 | AB23: =IF(ISBLANK(F23),0,1) -> 0 | AC23: =IF(ISBLANK(G23),0,1) -> 0 | AD23: =IF(ISBLANK(H23),0,1) -> 0 | AE23: =SUM(X23:AD23) -> 0 | AG23: =IF(AE23>0,1,0) -> 0
I24: =IF(R24=0,"",R24) | J24: =IF(U24=0,"",IF(F24="","",U24)) | O24: =IF(G24<>ab,0,IF(H24="",$L$18,IF(H24="No",$L$18,$M$18))) -> 0 | P24: =IF(G24<>dis,0,$L$19) -> 0 | Q24: =IF(G24<>regc,0,IF(H24="",$L$20,IF(H24="No",$L$20,$M$20))) -> 0 | R24: =SUM(O24:Q24) -> 0 | S24: =E24*R24 -> 0 | T24: =F24*1.25 -> 0 | U24: =IF(S24<=T24,S24,T24) -> 0 | X24: =IF(ISBLANK(A24),0,1) -> 0 | Y24: =IF(ISBLANK(B24),0,1) -> 0 | Z24: =IF(ISBLANK(D24),0,1) -> 0 | AA24: =IF(ISBLANK(E24),0,1) -> 0 | AB24: =IF(ISBLANK(F24),0,1) -> 0 | AC24: =IF(ISBLANK(G24),0,1) -> 0 | AD24: =IF(ISBLANK(H24),0,1) -> 0 | AE24: =SUM(X24:AD24) -> 0 | AG24: =IF(AE24>0,1,0) -> 0
I25: =IF(R25=0,"",R25) | J25: =IF(U25=0,"",IF(F25="","",U25)) | O25: =IF(G25<>ab,0,IF(H25="",$L$18,IF(H25="No",$L$18,$M$18))) -> 0 | P25: =IF(G25<>dis,0,$L$19) -> 0 | Q25: =IF(G25<>regc,0,IF(H25="",$L$20,IF(H25="No",$L$20,$M$20))) -> 0 | R25: =SUM(O25:Q25) -> 0 | S25: =E25*R25 -> 0 | T25: =F25*1.25 -> 0 | U25: =IF(S25<=T25,S25,T25) -> 0 | X25: =IF(ISBLANK(A25),0,1) -> 0 | Y25: =IF(ISBLANK(B25),0,1) -> 0 | Z25: =IF(ISBLANK(D25),0,1) -> 0 | AA25: =IF(ISBLANK(E25),0,1) -> 0 | AB25: =IF(ISBLANK(F25),0,1) -> 0 | AC25: =IF(ISBLANK(G25),0,1) -> 0 | AD25: =IF(ISBLANK(H25),0,1) -> 0 | AE25: =SUM(X25:AD25) -> 0 | AG25: =IF(AE25>0,1,0) -> 0
I26: =IF(R26=0,"",R26) | J26: =IF(U26=0,"",IF(F26="","",U26)) | O26: =IF(G26<>ab,0,IF(H26="",$L$18,IF(H26="No",$L$18,$M$18))) -> 0 | P26: =IF(G26<>dis,0,$L$19) -> 0 | Q26: =IF(G26<>regc,0,IF(H26="",$L$20,IF(H26="No",$L$20,$M$20))) -> 0 | R26: =SUM(O26:Q26) -> 0 | S26: =E26*R26 -> 0 | T26: =F26*1.25 -> 0 | U26: =IF(S26<=T26,S26,T26) -> 0 | X26: =IF(ISBLANK(A26),0,1) -> 0 | Y26: =IF(ISBLANK(B26),0,1) -> 0 | Z26: =IF(ISBLANK(D26),0,1) -> 0 | AA26: =IF(ISBLANK(E26),0,1) -> 0 | AB26: =IF(ISBLANK(F26),0,1) -> 0 | AC26: =IF(ISBLANK(G26),0,1) -> 0 | AD26: =IF(ISBLANK(H26),0,1) -> 0 | AE26: =SUM(X26:AD26) -> 0 | AG26: =IF(AE26>0,1,0) -> 0
I27: =IF(R27=0,"",R27) | J27: =IF(U27=0,"",IF(F27="","",U27)) | O27: =IF(G27<>ab,0,IF(H27="",$L$18,IF(H27="No",$L$18,$M$18))) -> 0 | P27: =IF(G27<>dis,0,$L$19) -> 0 | Q27: =IF(G27<>regc,0,IF(H27="",$L$20,IF(H27="No",$L$20,$M$20))) -> 0 | R27: =SUM(O27:Q27) -> 0 | S27: =E27*R27 -> 0 | T27: =F27*1.25 -> 0 | U27: =IF(S27<=T27,S27,T27) -> 0 | X27: =IF(ISBLANK(A27),0,1) -> 0 | Y27: =IF(ISBLANK(B27),0,1) -> 0 | Z27: =IF(ISBLANK(D27),0,1) -> 0 | AA27: =IF(ISBLANK(E27),0,1) -> 0 | AB27: =IF(ISBLANK(F27),0,1) -> 0 | AC27: =IF(ISBLANK(G27),0,1) -> 0 | AD27: =IF(ISBLANK(H27),0,1) -> 0 | AE27: =SUM(X27:AD27) -> 0 | AG27: =IF(AE27>0,1,0) -> 0
I28: =IF(R28=0,"",R28) | J28: =IF(U28=0,"",IF(F28="","",U28)) | O28: =IF(G28<>ab,0,IF(H28="",$L$18,IF(H28="No",$L$18,$M$18))) -> 0 | P28: =IF(G28<>dis,0,$L$19) -> 0 | Q28: =IF(G28<>regc,0,IF(H28="",$L$20,IF(H28="No",$L$20,$M$20))) -> 0 | R28: =SUM(O28:Q28) -> 0 | S28: =E28*R28 -> 0 | T28: =F28*1.25 -> 0 | U28: =IF(S28<=T28,S28,T28) -> 0 | X28: =IF(ISBLANK(A28),0,1) -> 0 | Y28: =IF(ISBLANK(B28),0,1) -> 0 | Z28: =IF(ISBLANK(D28),0,1) -> 0 | AA28: =IF(ISBLANK(E28),0,1) -> 0 | AB28: =IF(ISBLANK(F28),0,1) -> 0 | AC28: =IF(ISBLANK(G28),0,1) -> 0 | AD28: =IF(ISBLANK(H28),0,1) -> 0 | AE28: =SUM(X28:AD28) -> 0 | AG28: =IF(AE28>0,1,0) -> 0
I29: =IF(R29=0,"",R29) | J29: =IF(U29=0,"",IF(F29="","",U29)) | O29: =IF(G29<>ab,0,IF(H29="",$L$18,IF(H29="No",$L$18,$M$18))) -> 0 | P29: =IF(G29<>dis,0,$L$19) -> 0 | Q29: =IF(G29<>regc,0,IF(H29="",$L$20,IF(H29="No",$L$20,$M$20))) -> 0 | R29: =SUM(O29:Q29) -> 0 | S29: =E29*R29 -> 0 | T29: =F29*1.25 -> 0 | U29: =IF(S29<=T29,S29,T29) -> 0 | X29: =IF(ISBLANK(A29),0,1) -> 0 | Y29: =IF(ISBLANK(B29),0,1) -> 0 | Z29: =IF(ISBLANK(D29),0,1) -> 0 | AA29: =IF(ISBLANK(E29),0,1) -> 0 | AB29: =IF(ISBLANK(F29),0,1) -> 0 | AC29: =IF(ISBLANK(G29),0,1) -> 0 | AD29: =IF(ISBLANK(H29),0,1) -> 0 | AE29: =SUM(X29:AD29) -> 0 | AG29: =IF(AE29>0,1,0) -> 0
I30: =IF(R30=0,"",R30) | J30: =IF(U30=0,"",IF(F30="","",U30)) | O30: =IF(G30<>ab,0,IF(H30="",$L$18,IF(H30="No",$L$18,$M$18))) -> 0 | P30: =IF(G30<>dis,0,$L$19) -> 0 | Q30: =IF(G30<>regc,0,IF(H30="",$L$20,IF(H30="No",$L$20,$M$20))) -> 0 | R30: =SUM(O30:Q30) -> 0 | S30: =E30*R30 -> 0 | T30: =F30*1.25 -> 0 | U30: =IF(S30<=T30,S30,T30) -> 0 | X30: =IF(ISBLANK(A30),0,1) -> 0 | Y30: =IF(ISBLANK(B30),0,1) -> 0 | Z30: =IF(ISBLANK(D30),0,1) -> 0 | AA30: =IF(ISBLANK(E30),0,1) -> 0 | AB30: =IF(ISBLANK(F30),0,1) -> 0 | AC30: =IF(ISBLANK(G30),0,1) -> 0 | AD30: =IF(ISBLANK(H30),0,1) -> 0 | AE30: =SUM(X30:AD30) -> 0 | AG30: =IF(AE30>0,1,0) -> 0
I31: =IF(R31=0,"",R31) | J31: =IF(U31=0,"",IF(F31="","",U31)) | O31: =IF(G31<>ab,0,IF(H31="",$L$18,IF(H31="No",$L$18,$M$18))) -> 0 | P31: =IF(G31<>dis,0,$L$19) -> 0 | Q31: =IF(G31<>regc,0,IF(H31="",$L$20,IF(H31="No",$L$20,$M$20))) -> 0 | R31: =SUM(O31:Q31) -> 0 | S31: =E31*R31 -> 0 | T31: =F31*1.25 -> 0 | U31: =IF(S31<=T31,S31,T31) -> 0 | X31: =IF(ISBLANK(A31),0,1) -> 0 | Y31: =IF(ISBLANK(B31),0,1) -> 0 | Z31: =IF(ISBLANK(D31),0,1) -> 0 | AA31: =IF(ISBLANK(E31),0,1) -> 0 | AB31: =IF(ISBLANK(F31),0,1) -> 0 | AC31: =IF(ISBLANK(G31),0,1) -> 0 | AD31: =IF(ISBLANK(H31),0,1) -> 0 | AE31: =SUM(X31:AD31) -> 0 | AG31: =IF(AE31>0,1,0) -> 0
I32: =IF(R32=0,"",R32) | J32: =IF(U32=0,"",IF(F32="","",U32)) | O32: =IF(G32<>ab,0,IF(H32="",$L$18,IF(H32="No",$L$18,$M$18))) -> 0 | P32: =IF(G32<>dis,0,$L$19) -> 0 | Q32: =IF(G32<>regc,0,IF(H32="",$L$20,IF(H32="No",$L$20,$M$20))) -> 0 | R32: =SUM(O32:Q32) -> 0 | S32: =E32*R32 -> 0 | T32: =F32*1.25 -> 0 | U32: =IF(S32<=T32,S32,T32) -> 0 | X32: =IF(ISBLANK(A32),0,1) -> 0 | Y32: =IF(ISBLANK(B32),0,1) -> 0 | Z32: =IF(ISBLANK(D32),0,1) -> 0 | AA32: =IF(ISBLANK(E32),0,1) -> 0 | AB32: =IF(ISBLANK(F32),0,1) -> 0 | AC32: =IF(ISBLANK(G32),0,1) -> 0 | AD32: =IF(ISBLANK(H32),0,1) -> 0 | AE32: =SUM(X32:AD32) -> 0 | AG32: =IF(AE32>0,1,0) -> 0
I33: =IF(R33=0,"",R33) | J33: =IF(U33=0,"",IF(F33="","",U33)) | O33: =IF(G33<>ab,0,IF(H33="",$L$18,IF(H33="No",$L$18,$M$18))) -> 0 | P33: =IF(G33<>dis,0,$L$19) -> 0 | Q33: =IF(G33<>regc,0,IF(H33="",$L$20,IF(H33="No",$L$20,$M$20))) -> 0 | R33: =SUM(O33:Q33) -> 0 | S33: =E33*R33 -> 0 | T33: =F33*1.25 -> 0 | U33: =IF(S33<=T33,S33,T33) -> 0 | X33: =IF(ISBLANK(A33),0,1) -> 0 | Y33: =IF(ISBLANK(B33),0,1) -> 0 | Z33: =IF(ISBLANK(D33),0,1) -> 0 | AA33: =IF(ISBLANK(E33),0,1) -> 0 | AB33: =IF(ISBLANK(F33),0,1) -> 0 | AC33: =IF(ISBLANK(G33),0,1) -> 0 | AD33: =IF(ISBLANK(H33),0,1) -> 0 | AE33: =SUM(X33:AD33) -> 0 | AG33: =IF(AE33>0,1,0) -> 0
A34: Totals | E34: =SUM(E18:E33) | F34: =IF(AE34=AF34,"","All data must be entered!") | J34: =ROUND(SUM(J18:J33),0) | K34: =IF(F34="",0,1) | AE34: =SUM(AE18:AE33) | AF34: =AG34*7 | AG34: =SUM(AG18:AG33)
A36: To be filled in ONLY where cash grants have been claimed in lieu of additional deductions
F37: (deduction) | G37: (deduction) | H37: (deduction) | I37: (deduction) | J37: TOTALS
A38: a] Additional deduction [as computed above] | D38: =IF(J38=0,"",IF(J38=J34,"","Totals must be equal!")) | J38: =SUM(F38:I38) | K38: =IF(L38=0,0,IF(D38="",0,1)) | L38: =COUNT(F38:I38)
A39: (apportion the resulting additional deduction above, according to rate(s) of tax applicable)
A40: multiplied by | F40: [rate of tax] | G40: [rate of tax] | H40: [rate of tax] | I40: [rate of tax]
A41: b] rate(s) of tax at which enterprise was otherwise taxable (lowest rates first) | J41: =IF(L41<>L38,"Rates !","") | K41: =IF(J41="",0,1) | L41: =COUNT(F41:I41)
A43: Result of multiplying values in row (a) by the corresponding rate in row (b) | F43: =F38*F41 | G43: =G38*G41 | H43: =H38*H41 | I43: =I38*I41 | J43: =SUM(F43:I43)
A45: CASH GRANT [representing 70 % thereof] > | J45: =ROUND(J43*0.7,0) | N45: =IF(J45>0,0,J34) | O45: pg3
A47: Note 1
A48: This amount is referred to in Regulation 13 (7) and represents:
A49: a. | B49: an amount set by the E.T.C. for qualifying individuals defined under subregulation 13 (a)
A50: b. | B50: wage cost for the 12 months before commencement of this employment of qualifying individuals defined under subreg. 13 (b)
A51: c. | B51: wage cost for the 24 months before commencement of this employment of qualifying individuals defined under subreg. 13 (c)
A52: In all cases documentary evidence has to be provided and attached to the tax return.
A54: =_xlfn.SINGLE(MTCA) | B54: =ver -> TA2_e-CO_2025_Ver 1.1 | J54: TRA 02 | K54: =SUM(K41,K38,K34,K10:K13)
K55: =IF(AE34=0,0,IF(K54<>0,100,IF(D56="yes",1,100)))
C56: =COM
A58: B A C K T O I N D E X
A64: PE NUMBER CHECK DIGIT
A65: LIST OF CURRENCIES

Sheet TRA3
B1: =_ref1 | G1: =_YA1 | H1: =IF(G29=0,0,IF(ISBLANK(D3),1,0))
B2: Other statutory inflation of expenditure
B3: Please specify Act and relative Article | I3: A0301 | J3: D
B4: Expenditure [details] | G4: Amount
B29: Total Expenditure | F29: =SUM(G5:G28) | G29: =SUM(G5:G28)
B31: Statutory inflation | C31: [specify percentage] | E31: =IF(F29=0,"",IF(ISBLANK(D31),"< Rate!","")) | G31: =ROUND(G29*D31,0)
B32: =_xlfn.SINGLE(MTCA) | C32: =ver -> TA2_e-CO_2025_Ver 1.1 | G32: TRA 03
AI33: Yes
C34: =COM | AI34: No
I35: =IF(E31="",0,1) | J35: =IF(I35<>0,100,IF(G29<>0,IF(D34="YES",1,100),0))
B36: B A C K T O I N D E X
B55: =IF(F29=0,0,1) | C55: =IF(ISBLANK(D31),0,1) | D55: =SUM(B55:C55)

Sheet TRA4
C1: =ref&" "&_nm1 | J1: =_YA1 | P1: Proceeds! | IV1: Distinguish between ITA and BPA. [Default ITA ]
C2: ITA - BALANCING STATEMENT | IR2: Income Tax Act
C3: Asset Description | D3: Taxed Account | E3: Year of Purchase [Y/A] | F3: COST | G3: WDV on disposal | H3: Proceeds on disposal | I3: Balancing | R3: Restrict to cost | AC3: IPA | AD3: IPA & MTA | AE3: MTA | AF3: FIA | AG3: Untaxed | AJ3: IPA | AK3: IPA & MTA | AL3: MTA | AM3: FIA | AN3: Untaxed | IR3: Business Promotion
S4: Allce / Charge | X4: MTA
I5: Allowance | J5: Charge | T5: Allowance | U5: Charge | X5: FIA
A6: =VLOOKUP(B6,'TRA5'!$A$6:$J$270,1,FALSE) | B6: 1 | C6: =IF(ISERROR(A6),"",VLOOKUP(B6,'TRA5'!$A$6:$J$270,2,FALSE)) | D6: MTA | E6: =IF(ISERROR(A6),"",VLOOKUP($B6,'TRA5'!$A$6:$J$270,4,FALSE)) | F6: =IF(ISERROR(A6),"",VLOOKUP($B6,'TRA5'!$A$6:$J$270,9,FALSE)) | G6: =IF(ISERROR(A6),"",VLOOKUP($B6,'TRA5'!$A$6:$J$270,10,FALSE)) | I6: =IF(D6="","",IF(H6="","",IF(IV6=$IR$3,0,T6))) | J6: =IF(D6="","",IF(H6="","",IF(IV6=$IR$3,0,U6))) | K6: =IF(C6="","",IF(H6="",$P$1,"")) | Q6: =IF(ISERROR(A6),0,G6) | R6: =IF(H6>F6,F6,H6) | S6: =ROUND(R6-Q6,0) | T6: =IF(S6<=0,S6*-1,0) | U6: =IF(S6<=0,0,S6) | AE6: =IF($D6=mt,$I6,0) | AL6: =IF($D6=mt,$J6,0) | IV6: Income Tax Act
A7: =VLOOKUP(B7,'TRA5'!$A$6:$J$270,1,FALSE) | B7: 2 | C7: =IF(ISERROR(A7),"",VLOOKUP(B7,'TRA5'!$A$6:$J$270,2,FALSE)) | D7: MTA | E7: =IF(ISERROR(A7),"",VLOOKUP($B7,'TRA5'!$A$6:$J$270,4,FALSE)) | F7: =IF(ISERROR(A7),"",VLOOKUP($B7,'TRA5'!$A$6:$J$270,9,FALSE)) | G7: =IF(ISERROR(A7),"",VLOOKUP($B7,'TRA5'!$A$6:$J$270,10,FALSE)) | I7: =IF(D7="","",IF(H7="","",IF(IV7=$IR$3,0,T7))) | J7: =IF(D7="","",IF(H7="","",IF(IV7=$IR$3,0,U7))) | K7: =IF(C7="","",IF(H7="",$P$1,"")) | Q7: =IF(ISERROR(A7),0,G7) -> 0 | R7: =IF(H7>F7,F7,H7) -> 0 | S7: =ROUND(R7-Q7,0) | T7: =IF(S7<=0,S7*-1,0) -> 0 | U7: =IF(S7<=0,0,S7) -> 0 | AE7: =IF($D7=mt,$I7,0) | AL7: =IF($D7=mt,$J7,0) | IV7: Income Tax Act
A8: =VLOOKUP(B8,'TRA5'!$A$6:$J$270,1,FALSE) | B8: 3 | C8: =IF(ISERROR(A8),"",VLOOKUP(B8,'TRA5'!$A$6:$J$270,2,FALSE)) | D8: MTA | E8: =IF(ISERROR(A8),"",VLOOKUP($B8,'TRA5'!$A$6:$J$270,4,FALSE)) | F8: =IF(ISERROR(A8),"",VLOOKUP($B8,'TRA5'!$A$6:$J$270,9,FALSE)) | G8: =IF(ISERROR(A8),"",VLOOKUP($B8,'TRA5'!$A$6:$J$270,10,FALSE)) | I8: =IF(D8="","",IF(H8="","",IF(IV8=$IR$3,0,T8))) | J8: =IF(D8="","",IF(H8="","",IF(IV8=$IR$3,0,U8))) | K8: =IF(C8="","",IF(H8="",$P$1,"")) | Q8: =IF(ISERROR(A8),0,G8) -> 0 | R8: =IF(H8>F8,F8,H8) -> 0 | S8: =ROUND(R8-Q8,0) | T8: =IF(S8<=0,S8*-1,0) -> 0 | U8: =IF(S8<=0,0,S8) -> 0 | AE8: =IF($D8=mt,$I8,0) | AL8: =IF($D8=mt,$J8,0) | IV8: Income Tax Act
A9: =VLOOKUP(B9,'TRA5'!$A$6:$J$270,1,FALSE) | B9: 4 | C9: =IF(ISERROR(A9),"",VLOOKUP(B9,'TRA5'!$A$6:$J$270,2,FALSE)) | D9: MTA | E9: =IF(ISERROR(A9),"",VLOOKUP($B9,'TRA5'!$A$6:$J$270,4,FALSE)) | F9: =IF(ISERROR(A9),"",VLOOKUP($B9,'TRA5'!$A$6:$J$270,9,FALSE)) | G9: =IF(ISERROR(A9),"",VLOOKUP($B9,'TRA5'!$A$6:$J$270,10,FALSE)) | I9: =IF(D9="","",IF(H9="","",IF(IV9=$IR$3,0,T9))) | J9: =IF(D9="","",IF(H9="","",IF(IV9=$IR$3,0,U9))) | K9: =IF(C9="","",IF(H9="",$P$1,"")) | Q9: =IF(ISERROR(A9),0,G9) -> 0 | R9: =IF(H9>F9,F9,H9) -> 0 | S9: =ROUND(R9-Q9,0) | T9: =IF(S9<=0,S9*-1,0) -> 0 | U9: =IF(S9<=0,0,S9) -> 0 | AE9: =IF($D9=mt,$I9,0) | AL9: =IF($D9=mt,$J9,0) | IV9: Income Tax Act
A10: =VLOOKUP(B10,'TRA5'!$A$6:$J$270,1,FALSE) | B10: 5 | C10: =IF(ISERROR(A10),"",VLOOKUP(B10,'TRA5'!$A$6:$J$270,2,FALSE)) | D10: MTA | E10: =IF(ISERROR(A10),"",VLOOKUP($B10,'TRA5'!$A$6:$J$270,4,FALSE)) | F10: =IF(ISERROR(A10),"",VLOOKUP($B10,'TRA5'!$A$6:$J$270,9,FALSE)) | G10: =IF(ISERROR(A10),"",VLOOKUP($B10,'TRA5'!$A$6:$J$270,10,FALSE)) | I10: =IF(D10="","",IF(H10="","",IF(IV10=$IR$3,0,T10))) | J10: =IF(D10="","",IF(H10="","",IF(IV10=$IR$3,0,U10))) | K10: =IF(C10="","",IF(H10="",$P$1,"")) | Q10: =IF(ISERROR(A10),0,G10) | R10: =IF(H10>F10,F10,H10) | S10: =ROUND(R10-Q10,0) | T10: =IF(S10<=0,S10*-1,0) | U10: =IF(S10<=0,0,S10) | IV10: Income Tax Act
A11: =VLOOKUP(B11,'TRA5'!$A$6:$J$270,1,FALSE) | B11: 6 | C11: =IF(ISERROR(A11),"",VLOOKUP(B11,'TRA5'!$A$6:$J$270,2,FALSE)) | D11: MTA | E11: =IF(ISERROR(A11),"",VLOOKUP($B11,'TRA5'!$A$6:$J$270,4,FALSE)) | F11: =IF(ISERROR(A11),"",VLOOKUP($B11,'TRA5'!$A$6:$J$270,9,FALSE)) | G11: =IF(ISERROR(A11),"",VLOOKUP($B11,'TRA5'!$A$6:$J$270,10,FALSE)) | I11: =IF(D11="","",IF(H11="","",IF(IV11=$IR$3,0,T11))) | J11: =IF(D11="","",IF(H11="","",IF(IV11=$IR$3,0,U11))) | K11: =IF(C11="","",IF(H11="",$P$1,"")) | Q11: =IF(ISERROR(A11),0,G11) -> 0 | R11: =IF(H11>F11,F11,H11) -> 0 | S11: =ROUND(R11-Q11,0) -> 0 | T11: =IF(S11<=0,S11*-1,0) -> 0 | U11: =IF(S11<=0,0,S11) -> 0 | IV11: Income Tax Act
A12: =VLOOKUP(B12,'TRA5'!$A$6:$J$270,1,FALSE) | B12: 7 | C12: =IF(ISERROR(A12),"",VLOOKUP(B12,'TRA5'!$A$6:$J$270,2,FALSE)) | D12: MTA | E12: =IF(ISERROR(A12),"",VLOOKUP($B12,'TRA5'!$A$6:$J$270,4,FALSE)) | F12: =IF(ISERROR(A12),"",VLOOKUP($B12,'TRA5'!$A$6:$J$270,9,FALSE)) | G12: =IF(ISERROR(A12),"",VLOOKUP($B12,'TRA5'!$A$6:$J$270,10,FALSE)) | I12: =IF(D12="","",IF(H12="","",IF(IV12=$IR$3,0,T12))) | J12: =IF(D12="","",IF(H12="","",IF(IV12=$IR$3,0,U12))) | K12: =IF(C12="","",IF(H12="",$P$1,"")) | Q12: =IF(ISERROR(A12),0,G12) -> 0 | R12: =IF(H12>F12,F12,H12) -> 0 | S12: =ROUND(R12-Q12,0) -> 0 | T12: =IF(S12<=0,S12*-1,0) -> 0 | U12: =IF(S12<=0,0,S12) -> 0 | IV12: Income Tax Act
A13: =VLOOKUP(B13,'TRA5'!$A$6:$J$270,1,FALSE) | B13: 8 | C13: =IF(ISERROR(A13),"",VLOOKUP(B13,'TRA5'!$A$6:$J$270,2,FALSE)) | D13: MTA | E13: =IF(ISERROR(A13),"",VLOOKUP($B13,'TRA5'!$A$6:$J$270,4,FALSE)) | F13: =IF(ISERROR(A13),"",VLOOKUP($B13,'TRA5'!$A$6:$J$270,9,FALSE)) | G13: =IF(ISERROR(A13),"",VLOOKUP($B13,'TRA5'!$A$6:$J$270,10,FALSE)) | I13: =IF(D13="","",IF(H13="","",IF(IV13=$IR$3,0,T13))) | J13: =IF(D13="","",IF(H13="","",IF(IV13=$IR$3,0,U13))) | K13: =IF(C13="","",IF(H13="",$P$1,"")) | Q13: =IF(ISERROR(A13),0,G13) -> 0 | R13: =IF(H13>F13,F13,H13) -> 0 | S13: =ROUND(R13-Q13,0) -> 0 | T13: =IF(S13<=0,S13*-1,0) -> 0 | U13: =IF(S13<=0,0,S13) -> 0 | IV13: Income Tax Act
A14: =VLOOKUP(B14,'TRA5'!$A$6:$J$270,1,FALSE) | B14: 9 | C14: =IF(ISERROR(A14),"",VLOOKUP(B14,'TRA5'!$A$6:$J$270,2,FALSE)) | D14: MTA | E14: =IF(ISERROR(A14),"",VLOOKUP($B14,'TRA5'!$A$6:$J$270,4,FALSE)) | F14: =IF(ISERROR(A14),"",VLOOKUP($B14,'TRA5'!$A$6:$J$270,9,FALSE)) | G14: =IF(ISERROR(A14),"",VLOOKUP($B14,'TRA5'!$A$6:$J$270,10,FALSE)) | I14: =IF(D14="","",IF(H14="","",IF(IV14=$IR$3,0,T14))) | J14: =IF(D14="","",IF(H14="","",IF(IV14=$IR$3,0,U14))) | K14: =IF(C14="","",IF(H14="",$P$1,"")) | Q14: =IF(ISERROR(A14),0,G14) -> 0 | R14: =IF(H14>F14,F14,H14) -> 0 | S14: =ROUND(R14-Q14,0) -> 0 | T14: =IF(S14<=0,S14*-1,0) -> 0 | U14: =IF(S14<=0,0,S14) -> 0 | IV14: Income Tax Act
A15: =VLOOKUP(B15,'TRA5'!$A$6:$J$270,1,FALSE) | B15: 10 | C15: =IF(ISERROR(A15),"",VLOOKUP(B15,'TRA5'!$A$6:$J$270,2,FALSE)) | D15: MTA | E15: =IF(ISERROR(A15),"",VLOOKUP($B15,'TRA5'!$A$6:$J$270,4,FALSE)) | F15: =IF(ISERROR(A15),"",VLOOKUP($B15,'TRA5'!$A$6:$J$270,9,FALSE)) | G15: =IF(ISERROR(A15),"",VLOOKUP($B15,'TRA5'!$A$6:$J$270,10,FALSE)) | I15: =IF(D15="","",IF(H15="","",IF(IV15=$IR$3,0,T15))) | J15: =IF(D15="","",IF(H15="","",IF(IV15=$IR$3,0,U15))) | K15: =IF(C15="","",IF(H15="",$P$1,"")) | Q15: =IF(ISERROR(A15),0,G15) -> 0 | R15: =IF(H15>F15,F15,H15) -> 0 | S15: =ROUND(R15-Q15,0) -> 0 | T15: =IF(S15<=0,S15*-1,0) -> 0 | U15: =IF(S15<=0,0,S15) -> 0 | IV15: Income Tax Act
A16: =VLOOKUP(B16,'TRA5'!$A$6:$J$270,1,FALSE) | B16: 11 | C16: =IF(ISERROR(A16),"",VLOOKUP(B16,'TRA5'!$A$6:$J$270,2,FALSE)) | D16: MTA | E16: =IF(ISERROR(A16),"",VLOOKUP($B16,'TRA5'!$A$6:$J$270,4,FALSE)) | F16: =IF(ISERROR(A16),"",VLOOKUP($B16,'TRA5'!$A$6:$J$270,9,FALSE)) | G16: =IF(ISERROR(A16),"",VLOOKUP($B16,'TRA5'!$A$6:$J$270,10,FALSE)) | I16: =IF(D16="","",IF(H16="","",IF(IV16=$IR$3,0,T16))) | J16: =IF(D16="","",IF(H16="","",IF(IV16=$IR$3,0,U16))) | K16: =IF(C16="","",IF(H16="",$P$1,"")) | Q16: =IF(ISERROR(A16),0,G16) -> 0 | R16: =IF(H16>F16,F16,H16) -> 0 | S16: =ROUND(R16-Q16,0) -> 0 | T16: =IF(S16<=0,S16*-1,0) -> 0 | U16: =IF(S16<=0,0,S16) -> 0 | IV16: Income Tax Act
A17: =VLOOKUP(B17,'TRA5'!$A$6:$J$270,1,FALSE) | B17: 12 | C17: =IF(ISERROR(A17),"",VLOOKUP(B17,'TRA5'!$A$6:$J$270,2,FALSE)) | D17: MTA | E17: =IF(ISERROR(A17),"",VLOOKUP($B17,'TRA5'!$A$6:$J$270,4,FALSE)) | F17: =IF(ISERROR(A17),"",VLOOKUP($B17,'TRA5'!$A$6:$J$270,9,FALSE)) | G17: =IF(ISERROR(A17),"",VLOOKUP($B17,'TRA5'!$A$6:$J$270,10,FALSE)) | I17: =IF(D17="","",IF(H17="","",IF(IV17=$IR$3,0,T17))) | J17: =IF(D17="","",IF(H17="","",IF(IV17=$IR$3,0,U17))) | K17: =IF(C17="","",IF(H17="",$P$1,"")) | Q17: =IF(ISERROR(A17),0,G17) -> 0 | R17: =IF(H17>F17,F17,H17) -> 0 | S17: =ROUND(R17-Q17,0) -> 0 | T17: =IF(S17<=0,S17*-1,0) -> 0 | U17: =IF(S17<=0,0,S17) -> 0 | IV17: Income Tax Act
A18: =VLOOKUP(B18,'TRA5'!$A$6:$J$270,1,FALSE) | B18: 13 | C18: =IF(ISERROR(A18),"",VLOOKUP(B18,'TRA5'!$A$6:$J$270,2,FALSE)) | D18: MTA | E18: =IF(ISERROR(A18),"",VLOOKUP($B18,'TRA5'!$A$6:$J$270,4,FALSE)) | F18: =IF(ISERROR(A18),"",VLOOKUP($B18,'TRA5'!$A$6:$J$270,9,FALSE)) | G18: =IF(ISERROR(A18),"",VLOOKUP($B18,'TRA5'!$A$6:$J$270,10,FALSE)) | I18: =IF(D18="","",IF(H18="","",IF(IV18=$IR$3,0,T18))) | J18: =IF(D18="","",IF(H18="","",IF(IV18=$IR$3,0,U18))) | K18: =IF(C18="","",IF(H18="",$P$1,"")) | Q18: =IF(ISERROR(A18),0,G18) -> 0 | R18: =IF(H18>F18,F18,H18) -> 0 | S18: =ROUND(R18-Q18,0) -> 0 | T18: =IF(S18<=0,S18*-1,0) -> 0 | U18: =IF(S18<=0,0,S18) -> 0 | IV18: Income Tax Act
A19: =VLOOKUP(B19,'TRA5'!$A$6:$J$270,1,FALSE) | B19: 14 | C19: =IF(ISERROR(A19),"",VLOOKUP(B19,'TRA5'!$A$6:$J$270,2,FALSE)) | D19: MTA | E19: =IF(ISERROR(A19),"",VLOOKUP($B19,'TRA5'!$A$6:$J$270,4,FALSE)) | F19: =IF(ISERROR(A19),"",VLOOKUP($B19,'TRA5'!$A$6:$J$270,9,FALSE)) | G19: =IF(ISERROR(A19),"",VLOOKUP($B19,'TRA5'!$A$6:$J$270,10,FALSE)) | I19: =IF(D19="","",IF(H19="","",IF(IV19=$IR$3,0,T19))) | J19: =IF(D19="","",IF(H19="","",IF(IV19=$IR$3,0,U19))) | K19: =IF(C19="","",IF(H19="",$P$1,"")) | Q19: =IF(ISERROR(A19),0,G19) -> 0 | R19: =IF(H19>F19,F19,H19) -> 0 | S19: =ROUND(R19-Q19,0) -> 0 | T19: =IF(S19<=0,S19*-1,0) -> 0 | U19: =IF(S19<=0,0,S19) -> 0 | IV19: Income Tax Act
A20: =VLOOKUP(B20,'TRA5'!$A$6:$J$270,1,FALSE) | B20: 15 | C20: =IF(ISERROR(A20),"",VLOOKUP(B20,'TRA5'!$A$6:$J$270,2,FALSE)) | D20: MTA | E20: =IF(ISERROR(A20),"",VLOOKUP($B20,'TRA5'!$A$6:$J$270,4,FALSE)) | F20: =IF(ISERROR(A20),"",VLOOKUP($B20,'TRA5'!$A$6:$J$270,9,FALSE)) | G20: =IF(ISERROR(A20),"",VLOOKUP($B20,'TRA5'!$A$6:$J$270,10,FALSE)) | I20: =IF(D20="","",IF(H20="","",IF(IV20=$IR$3,0,T20))) | J20: =IF(D20="","",IF(H20="","",IF(IV20=$IR$3,0,U20))) | K20: =IF(C20="","",IF(H20="",$P$1,"")) | Q20: =IF(ISERROR(A20),0,G20) -> 0 | R20: =IF(H20>F20,F20,H20) -> 0 | S20: =ROUND(R20-Q20,0) -> 0 | T20: =IF(S20<=0,S20*-1,0) -> 0 | U20: =IF(S20<=0,0,S20) -> 0 | IV20: Income Tax Act
A21: =VLOOKUP(B21,'TRA5'!$A$6:$J$270,1,FALSE) | B21: 16 | C21: =IF(ISERROR(A21),"",VLOOKUP(B21,'TRA5'!$A$6:$J$270,2,FALSE)) | D21: MTA | E21: =IF(ISERROR(A21),"",VLOOKUP($B21,'TRA5'!$A$6:$J$270,4,FALSE)) | F21: =IF(ISERROR(A21),"",VLOOKUP($B21,'TRA5'!$A$6:$J$270,9,FALSE)) | G21: =IF(ISERROR(A21),"",VLOOKUP($B21,'TRA5'!$A$6:$J$270,10,FALSE)) | I21: =IF(D21="","",IF(H21="","",IF(IV21=$IR$3,0,T21))) | J21: =IF(D21="","",IF(H21="","",IF(IV21=$IR$3,0,U21))) | K21: =IF(C21="","",IF(H21="",$P$1,"")) | Q21: =IF(ISERROR(A21),0,G21) -> 0 | R21: =IF(H21>F21,F21,H21) -> 0 | S21: =ROUND(R21-Q21,0) -> 0 | T21: =IF(S21<=0,S21*-1,0) -> 0 | U21: =IF(S21<=0,0,S21) -> 0 | IV21: Income Tax Act
... A40: =VLOOKUP(B40,'TRA5'!$A$6:$J$270,1,FALSE) | B40: 35 | C40: =IF(ISERROR(A40),"",VLOOKUP(B40,'TRA5'!$A$6:$J$270,2,FALSE)) | D40: MTA | E40: =IF(ISERROR(A40),"",VLOOKUP($B40,'TRA5'!$A$6:$J$270,4,FALSE)) | F40: =IF(ISERROR(A40),"",VLOOKUP($B40,'TRA5'!$A$6:$J$270,9,FALSE)) | G40: =IF(ISERROR(A40),"",VLOOKUP($B40,'TRA5'!$A$6:$J$270,10,FALSE)) | I40: =IF(D40="","",IF(H40="","",IF(IV40=$IR$3,0,T40))) | J40: =IF(D40="","",IF(H40="","",IF(IV40=$IR$3,0,U40))) | K40: =IF(C40="","",IF(H40="",$P$1,"")) | Q40: =IF(ISERROR(A40),0,G40) -> 0 | R40: =IF(H40>F40,F40,H40) -> 0 | S40: =ROUND(R40-Q40,0) -> 0 | T40: =IF(S40<=0,S40*-1,0) -> 0 | U40: =IF(S40<=0,0,S40) -> 0 | IV40: Income Tax Act
A41: =VLOOKUP(B41,'TRA5'!$A$6:$J$270,1,FALSE) | B41: 36 | C41: =IF(ISERROR(A41),"",VLOOKUP(B41,'TRA5'!$A$6:$J$270,2,FALSE)) | D41: MTA | E41: =IF(ISERROR(A41),"",VLOOKUP($B41,'TRA5'!$A$6:$J$270,4,FALSE)) | F41: =IF(ISERROR(A41),"",VLOOKUP($B41,'TRA5'!$A$6:$J$270,9,FALSE)) | G41: =IF(ISERROR(A41),"",VLOOKUP($B41,'TRA5'!$A$6:$J$270,10,FALSE)) | I41: =IF(D41="","",IF(H41="","",IF(IV41=$IR$3,0,T41))) | J41: =IF(D41="","",IF(H41="","",IF(IV41=$IR$3,0,U41))) | K41: =IF(C41="","",IF(H41="",$P$1,"")) | Q41: =IF(ISERROR(A41),0,G41) -> 0 | R41: =IF(H41>F41,F41,H41) -> 0 | S41: =ROUND(R41-Q41,0) | T41: =IF(S41<=0,S41*-1,0) -> 0 | U41: =IF(S41<=0,0,S41) -> 0 | AE41: =IF($D41=mt,$I41,0) | AL41: =IF($D41=mt,$J41,0) | IV41: Income Tax Act
A42: =VLOOKUP(B42,'TRA5'!$A$6:$J$270,1,FALSE) | B42: 37 | C42: =IF(ISERROR(A42),"",VLOOKUP(B42,'TRA5'!$A$6:$J$270,2,FALSE)) | D42: MTA | E42: =IF(ISERROR(A42),"",VLOOKUP($B42,'TRA5'!$A$6:$J$270,4,FALSE)) | F42: =IF(ISERROR(A42),"",VLOOKUP($B42,'TRA5'!$A$6:$J$270,9,FALSE)) | G42: =IF(ISERROR(A42),"",VLOOKUP($B42,'TRA5'!$A$6:$J$270,10,FALSE)) | I42: =IF(D42="","",IF(H42="","",IF(IV42=$IR$3,0,T42))) | J42: =IF(D42="","",IF(H42="","",IF(IV42=$IR$3,0,U42))) | K42: =IF(C42="","",IF(H42="",$P$1,"")) | Q42: =IF(ISERROR(A42),0,G42) -> 0 | R42: =IF(H42>F42,F42,H42) -> 0 | S42: =ROUND(R42-Q42,0) -> 0 | T42: =IF(S42<=0,S42*-1,0) -> 0 | U42: =IF(S42<=0,0,S42) -> 0 | AE42: =IF($D42=mt,$I42,0) | AL42: =IF($D42=mt,$J42,0) | IV42: Income Tax Act
A43: =VLOOKUP(B43,'TRA5'!$A$6:$J$270,1,FALSE) | B43: 38 | C43: =IF(ISERROR(A43),"",VLOOKUP(B43,'TRA5'!$A$6:$J$270,2,FALSE)) | D43: MTA | E43: =IF(ISERROR(A43),"",VLOOKUP($B43,'TRA5'!$A$6:$J$270,4,FALSE)) | F43: =IF(ISERROR(A43),"",VLOOKUP($B43,'TRA5'!$A$6:$J$270,9,FALSE)) | G43: =IF(ISERROR(A43),"",VLOOKUP($B43,'TRA5'!$A$6:$J$270,10,FALSE)) | I43: =IF(D43="","",IF(H43="","",IF(IV43=$IR$3,0,T43))) | J43: =IF(D43="","",IF(H43="","",IF(IV43=$IR$3,0,U43))) | K43: =IF(C43="","",IF(H43="",$P$1,"")) | Q43: =IF(ISERROR(A43),0,G43) -> 0 | R43: =IF(H43>F43,F43,H43) -> 0 | S43: =ROUND(R43-Q43,0) -> 0 | T43: =IF(S43<=0,S43*-1,0) -> 0 | U43: =IF(S43<=0,0,S43) -> 0 | AE43: =IF($D43=mt,$I43,0) | AL43: =IF($D43=mt,$J43,0) | IV43: Income Tax Act
A44: =VLOOKUP(B44,'TRA5'!$A$6:$J$270,1,FALSE) | B44: 39 | C44: =IF(ISERROR(A44),"",VLOOKUP(B44,'TRA5'!$A$6:$J$270,2,FALSE)) | D44: MTA | E44: =IF(ISERROR(A44),"",VLOOKUP($B44,'TRA5'!$A$6:$J$270,4,FALSE)) | F44: =IF(ISERROR(A44),"",VLOOKUP($B44,'TRA5'!$A$6:$J$270,9,FALSE)) | G44: =IF(ISERROR(A44),"",VLOOKUP($B44,'TRA5'!$A$6:$J$270,10,FALSE)) | I44: =IF(D44="","",IF(H44="","",IF(IV44=$IR$3,0,T44))) | J44: =IF(D44="","",IF(H44="","",IF(IV44=$IR$3,0,U44))) | K44: =IF(C44="","",IF(H44="",$P$1,"")) | Q44: =IF(ISERROR(A44),0,G44) -> 0 | R44: =IF(H44>F44,F44,H44) -> 0 | S44: =ROUND(R44-Q44,0) -> 0 | T44: =IF(S44<=0,S44*-1,0) -> 0 | U44: =IF(S44<=0,0,S44) -> 0 | AE44: =IF($D44=mt,$I44,0) | AL44: =IF($D44=mt,$J44,0) | IV44: Income Tax Act
A45: =VLOOKUP(B45,'TRA5'!$A$6:$J$270,1,FALSE) | B45: 40 | C45: =IF(ISERROR(A45),"",VLOOKUP(B45,'TRA5'!$A$6:$J$270,2,FALSE)) | D45: MTA | E45: =IF(ISERROR(A45),"",VLOOKUP($B45,'TRA5'!$A$6:$J$270,4,FALSE)) | F45: =IF(ISERROR(A45),"",VLOOKUP($B45,'TRA5'!$A$6:$J$270,9,FALSE)) | G45: =IF(ISERROR(A45),"",VLOOKUP($B45,'TRA5'!$A$6:$J$270,10,FALSE)) | I45: =IF(D45="","",IF(H45="","",IF(IV45=$IR$3,0,T45))) | J45: =IF(D45="","",IF(H45="","",IF(IV45=$IR$3,0,U45))) | K45: =IF(C45="","",IF(H45="",$P$1,"")) | Q45: =IF(ISERROR(A45),0,G45) -> 0 | R45: =IF(H45>F45,F45,H45) -> 0 | S45: =ROUND(R45-Q45,0) -> 0 | T45: =IF(S45<=0,S45*-1,0) -> 0 | U45: =IF(S45<=0,0,S45) -> 0 | AE45: =IF($D45=mt,$I45,0) | AL45: =IF($D45=mt,$J45,0) | IV45: Income Tax Act
A46: =VLOOKUP(B46,'TRA5'!$A$6:$J$270,1,FALSE) | B46: 41 | C46: =IF(ISERROR(A46),"",VLOOKUP(B46,'TRA5'!$A$6:$J$270,2,FALSE)) | D46: MTA | E46: =IF(ISERROR(A46),"",VLOOKUP($B46,'TRA5'!$A$6:$J$270,4,FALSE)) | F46: =IF(ISERROR(A46),"",VLOOKUP($B46,'TRA5'!$A$6:$J$270,9,FALSE)) | G46: =IF(ISERROR(A46),"",VLOOKUP($B46,'TRA5'!$A$6:$J$270,10,FALSE)) | I46: =IF(D46="","",IF(H46="","",IF(IV46=$IR$3,0,T46))) | J46: =IF(D46="","",IF(H46="","",IF(IV46=$IR$3,0,U46))) | K46: =IF(C46="","",IF(H46="",$P$1,"")) | Q46: =IF(ISERROR(A46),0,G46) -> 0 | R46: =IF(H46>F46,F46,H46) -> 0 | S46: =ROUND(R46-Q46,0) -> 0 | T46: =IF(S46<=0,S46*-1,0) -> 0 | U46: =IF(S46<=0,0,S46) -> 0 | AE46: =IF($D46=mt,$I46,0) | AL46: =IF($D46=mt,$J46,0) | IV46: Income Tax Act
A47: =VLOOKUP(B47,'TRA5'!$A$6:$J$270,1,FALSE) | B47: 42 | C47: =IF(ISERROR(A47),"",VLOOKUP(B47,'TRA5'!$A$6:$J$270,2,FALSE)) | D47: MTA | E47: =IF(ISERROR(A47),"",VLOOKUP($B47,'TRA5'!$A$6:$J$270,4,FALSE)) | F47: =IF(ISERROR(A47),"",VLOOKUP($B47,'TRA5'!$A$6:$J$270,9,FALSE)) | G47: =IF(ISERROR(A47),"",VLOOKUP($B47,'TRA5'!$A$6:$J$270,10,FALSE)) | I47: =IF(D47="","",IF(H47="","",IF(IV47=$IR$3,0,T47))) | J47: =IF(D47="","",IF(H47="","",IF(IV47=$IR$3,0,U47))) | K47: =IF(C47="","",IF(H47="",$P$1,"")) | Q47: =IF(ISERROR(A47),0,G47) -> 0 | R47: =IF(H47>F47,F47,H47) -> 0 | S47: =ROUND(R47-Q47,0) -> 0 | T47: =IF(S47<=0,S47*-1,0) -> 0 | U47: =IF(S47<=0,0,S47) -> 0 | AE47: =IF($D47=mt,$I47,0) | AL47: =IF($D47=mt,$J47,0) | IV47: Income Tax Act
A48: =VLOOKUP(B48,'TRA5'!$A$6:$J$270,1,FALSE) | B48: 43 | C48: =IF(ISERROR(A48),"",VLOOKUP(B48,'TRA5'!$A$6:$J$270,2,FALSE)) | D48: MTA | E48: =IF(ISERROR(A48),"",VLOOKUP($B48,'TRA5'!$A$6:$J$270,4,FALSE)) | F48: =IF(ISERROR(A48),"",VLOOKUP($B48,'TRA5'!$A$6:$J$270,9,FALSE)) | G48: =IF(ISERROR(A48),"",VLOOKUP($B48,'TRA5'!$A$6:$J$270,10,FALSE)) | I48: =IF(D48="","",IF(H48="","",IF(IV48=$IR$3,0,T48))) | J48: =IF(D48="","",IF(H48="","",IF(IV48=$IR$3,0,U48))) | K48: =IF(C48="","",IF(H48="",$P$1,"")) | Q48: =IF(ISERROR(A48),0,G48) -> 0 | R48: =IF(H48>F48,F48,H48) -> 0 | S48: =ROUND(R48-Q48,0) -> 0 | T48: =IF(S48<=0,S48*-1,0) -> 0 | U48: =IF(S48<=0,0,S48) -> 0 | AE48: =IF($D48=mt,$I48,0) | AL48: =IF($D48=mt,$J48,0) | IV48: Income Tax Act
A49: =VLOOKUP(B49,'TRA5'!$A$6:$J$270,1,FALSE) | B49: 44 | C49: =IF(ISERROR(A49),"",VLOOKUP(B49,'TRA5'!$A$6:$J$270,2,FALSE)) | D49: MTA | E49: =IF(ISERROR(A49),"",VLOOKUP($B49,'TRA5'!$A$6:$J$270,4,FALSE)) | F49: =IF(ISERROR(A49),"",VLOOKUP($B49,'TRA5'!$A$6:$J$270,9,FALSE)) | G49: =IF(ISERROR(A49),"",VLOOKUP($B49,'TRA5'!$A$6:$J$270,10,FALSE)) | I49: =IF(D49="","",IF(H49="","",IF(IV49=$IR$3,0,T49))) | J49: =IF(D49="","",IF(H49="","",IF(IV49=$IR$3,0,U49))) | K49: =IF(C49="","",IF(H49="",$P$1,"")) | Q49: =IF(ISERROR(A49),0,G49) -> 0 | R49: =IF(H49>F49,F49,H49) -> 0 | S49: =ROUND(R49-Q49,0) -> 0 | T49: =IF(S49<=0,S49*-1,0) -> 0 | U49: =IF(S49<=0,0,S49) -> 0 | AE49: =IF($D49=mt,$I49,0) | AL49: =IF($D49=mt,$J49,0) | IV49: Income Tax Act
A50: =VLOOKUP(B50,'TRA5'!$A$6:$J$270,1,FALSE) | B50: 45 | C50: =IF(ISERROR(A50),"",VLOOKUP(B50,'TRA5'!$A$6:$J$270,2,FALSE)) | D50: MTA | E50: =IF(ISERROR(A50),"",VLOOKUP($B50,'TRA5'!$A$6:$J$270,4,FALSE)) | F50: =IF(ISERROR(A50),"",VLOOKUP($B50,'TRA5'!$A$6:$J$270,9,FALSE)) | G50: =IF(ISERROR(A50),"",VLOOKUP($B50,'TRA5'!$A$6:$J$270,10,FALSE)) | I50: =IF(D50="","",IF(H50="","",IF(IV50=$IR$3,0,T50))) | J50: =IF(D50="","",IF(H50="","",IF(IV50=$IR$3,0,U50))) | K50: =IF(C50="","",IF(H50="",$P$1,"")) | Q50: =IF(ISERROR(A50),0,G50) -> 0 | R50: =IF(H50>F50,F50,H50) -> 0 | S50: =ROUND(R50-Q50,0) -> 0 | T50: =IF(S50<=0,S50*-1,0) -> 0 | U50: =IF(S50<=0,0,S50) -> 0 | AE50: =IF($D50=mt,$I50,0) | AL50: =IF($D50=mt,$J50,0) | IV50: Income Tax Act
A51: =VLOOKUP(B51,'TRA5'!$A$6:$J$270,1,FALSE) | B51: 46 | C51: =IF(ISERROR(A51),"",VLOOKUP(B51,'TRA5'!$A$6:$J$270,2,FALSE)) | D51: MTA | E51: =IF(ISERROR(A51),"",VLOOKUP($B51,'TRA5'!$A$6:$J$270,4,FALSE)) | F51: =IF(ISERROR(A51),"",VLOOKUP($B51,'TRA5'!$A$6:$J$270,9,FALSE)) | G51: =IF(ISERROR(A51),"",VLOOKUP($B51,'TRA5'!$A$6:$J$270,10,FALSE)) | I51: =IF(D51="","",IF(H51="","",IF(IV51=$IR$3,0,T51))) | J51: =IF(D51="","",IF(H51="","",IF(IV51=$IR$3,0,U51))) | K51: =IF(C51="","",IF(H51="",$P$1,"")) | Q51: =IF(ISERROR(A51),0,G51) -> 0 | R51: =IF(H51>F51,F51,H51) -> 0 | S51: =ROUND(R51-Q51,0) -> 0 | T51: =IF(S51<=0,S51*-1,0) -> 0 | U51: =IF(S51<=0,0,S51) -> 0 | AE51: =IF($D51=mt,$I51,0) | AL51: =IF($D51=mt,$J51,0) | IV51: Income Tax Act
A52: =VLOOKUP(B52,'TRA5'!$A$6:$J$270,1,FALSE) | B52: 47 | C52: =IF(ISERROR(A52),"",VLOOKUP(B52,'TRA5'!$A$6:$J$270,2,FALSE)) | D52: MTA | E52: =IF(ISERROR(A52),"",VLOOKUP($B52,'TRA5'!$A$6:$J$270,4,FALSE)) | F52: =IF(ISERROR(A52),"",VLOOKUP($B52,'TRA5'!$A$6:$J$270,9,FALSE)) | G52: =IF(ISERROR(A52),"",VLOOKUP($B52,'TRA5'!$A$6:$J$270,10,FALSE)) | I52: =IF(D52="","",IF(H52="","",IF(IV52=$IR$3,0,T52))) | J52: =IF(D52="","",IF(H52="","",IF(IV52=$IR$3,0,U52))) | K52: =IF(C52="","",IF(H52="",$P$1,"")) | Q52: =IF(ISERROR(A52),0,G52) -> 0 | R52: =IF(H52>F52,F52,H52) -> 0 | S52: =ROUND(R52-Q52,0) -> 0 | T52: =IF(S52<=0,S52*-1,0) -> 0 | U52: =IF(S52<=0,0,S52) -> 0 | AE52: =IF($D52=mt,$I52,0) | AL52: =IF($D52=mt,$J52,0) | IV52: Income Tax Act
... A66: =VLOOKUP(B66,'TRA5'!$A$6:$J$270,1,FALSE) | B66: 61 | C66: =IF(ISERROR(A66),"",VLOOKUP(B66,'TRA5'!$A$6:$J$270,2,FALSE)) | D66: MTA | E66: =IF(ISERROR(A66),"",VLOOKUP($B66,'TRA5'!$A$6:$J$270,4,FALSE)) | F66: =IF(ISERROR(A66),"",VLOOKUP($B66,'TRA5'!$A$6:$J$270,9,FALSE)) | G66: =IF(ISERROR(A66),"",VLOOKUP($B66,'TRA5'!$A$6:$J$270,10,FALSE)) | I66: =IF(D66="","",IF(H66="","",IF(IV66=$IR$3,0,T66))) | J66: =IF(D66="","",IF(H66="","",IF(IV66=$IR$3,0,U66))) | K66: =IF(C66="","",IF(H66="",$P$1,"")) | Q66: =IF(ISERROR(A66),0,G66) -> 0 | R66: =IF(H66>F66,F66,H66) -> 0 | S66: =ROUND(R66-Q66,0) -> 0 | T66: =IF(S66<=0,S66*-1,0) -> 0 | U66: =IF(S66<=0,0,S66) -> 0 | AE66: =IF($D66=mt,$I66,0) | AL66: =IF($D66=mt,$J66,0) | IV66: Income Tax Act
C97: TOTALS | D97: =IF(P97=O97,""," NOT ALL PROCEEDS INDICATED!") | I97: =SUM(I6:I66) | J97: =SUM(J6:J66) | N97: =IF(D97="",0,1) | O97: =COUNT(G6:G66) | P97: =COUNT(H6:H66) | R97: =SUM(R6:R66)
C98: Balancing amounts attaching to source of income included as | G98: Exempt Income [TRA18] | H98: Tax computation [page 4 of tax return] | R98: =COUNT(H6:H66)
H99: =ip | I99: =mt | J99: =fi
C100: Balancing Allowances | K100: =IF(AND(I97>0,O100<>4),reo,IF(I97<>P100,"Check values!","")) | N100: =IF(K100=reo,1,0) | O100: =COUNT(G100:J100) | P100: =SUM(G100:J100)
H101: Overall Total | I101: =I97
C102: Balancing Charges | K102: =IF(AND(J97>0,O102<>4),reo,IF(J97<>P102,"Check values!","")) | N102: =IF(K102=reo,1,0) | O102: =COUNT(G102:J102) | P102: =SUM(G102:J102)
H103: Overall Total | I103: =J97 | N103: =SUM(N97:N102)
C105: =_xlfn.SINGLE(MTCA) | D105: =ver -> TA2_e-CO_2025_Ver 1.1 | L105: TRA 04
C106: NOTE: In the case of Motor Vehicles, you have to apportion the proceeds pro-rata if the original cost was statutorily restricted. | N106: =IF(N103<>0,100,IF(R98<>0,IF(E108="YES",1,100),0))
C108: =COM | D108: =COM | R108: =IF(AND(N100=0,K100<>""),1,IF(AND(N102=0,K102<>""),1,0)) | BS108: Yes
BS109: No
C110: B A C K T O I N D E X

Sheet TRA5
B1: =_ref1 | N1: =_YA1 | Q1: =ya | S1: =reg*1 | Y1: Disposals (Cost or WDV)! | Z1: =IF('p2'!G21="y",1,0) | AA1: TAX A/c! | AB1: Cost!! | AC1: WDV!! | AD1: empty fields! | AE1: Year of Purchase! | AF1: 4 | AL1: Disposals! | BA1: Number of years dep'n - Mandatory
B2: Capital Allowances Schedule - INCOME TAX ACT CAP 123 | BA2: Number of years dep'n | BY2: IPA | CC2: IPA | CE2: MTA | CF2: FIA | CG2: Untaxed
B3: Plant and Machinery Use this part where the Annual Wear and Tear is calculated on the WRITTEN DOWN VALUE [Assets acquired before Y/A 2002 OR AIRCRAFT in use before the Y/A 2010 - LN 291 of 2010] | D3: Year of Purchase [Y/A] | E3: Original Cost | F3: WDV START Y/A 2002 OR START Y/A 2010 (Aircraft) | G3: WDV b/fwd [to-date] | H3: Disposals at WDV START Y/A 2002 OR START Y/A 2010 (Aircraft) | I3: Disposals at Original Cost | J3: Disposals at W.D.V. [to-date] | K3: Number of years dep'n | L3: WDV start Y/A 2002 OR START Y/A 2010 c/fwd | M3: Annual W & T | N3: WDV [to-date] c/fwd | BY3: MTA | CA3: FTA
AB4: Bal Stat | BY4: FIA | CA4: IPA
AB5: 0 | AC5: 0 | CA5: MTA
A6: =IF(AC6=AC5,0,AC6) | C6: MTA | L6: =IF(ISBLANK(B6),0,IF(T6=0,0,F6-H6)) | M6: =IF(ISBLANK(B6),0,IF(T6=0,0,IF(W6<0,0,W6))) | N6: =IF(ISBLANK(B6),0,IF(T6=0,0,IF(AP6=0,Y6,IF(AP6<>3,0,Y6)))) | P6: =IF(B6="","",IF(C6="",$AA$1,IF(AQ6<>2,$AC$1,IF(AP6=0,"",IF(D6="",$AE$1,IF(E6="",$AB$1,IF(AP6<>3,$AL$1,IF(AR6>0,$Y$1,"")))))))) | S6: =IF(P6="",0,1) | T6: =IF(ISERROR(X6),4,X6) | U6: =IF(ISBLANK(K6),T6,IF(K6=0,0,IF(K6>T6,K6,T6))) | V6: =IF(L6=0,0,IF(U6=0,0,ROUND(L6*1/U6,0))) | W6: =IF(V6<=AA6,V6,AA6) | X6: =IF(ISBLANK($B6),0,VLOOKUP($B6,$B$322:$C$343,2,FALSE)) | Y6: =IF(AA6-V6<=0,0,AA6-V6) | AA6: =G6-J6 | AC6: =IF(AD6=3,AC5+1,AC5) | AD6: =SUM(AE6:AG6) | AE6: =IF(ISBLANK(H6),0,1) | AF6: =IF(ISBLANK(I6),0,1) | AG6: =IF(ISBLANK(J6),0,1) | AH6: =G6-J6 | AI6: =IF(ISBLANK(E6),9999999,E6) | AJ6: =F6 | AK6: =G6 | AM6: =IF(ISBLANK(H6),0,1) | AN6: =IF(ISBLANK(I6),0,1) | AO6: =IF(ISBLANK(J6),0,1) | AP6: =SUM(AM6:AO6) | AQ6: =IF(B6="",0,COUNT(F6:G6)) | AR6: =IF(J6>G6,1,IF(I6>E6,1,IF(H6>F6,1,0))) | BA6: =IF(ISERROR(BB6),2001,2009) | BB6: =VLOOKUP(B6,$B$340:$C$343,2,FALSE) | CA6: FIA
A7: =IF(AC7=AC6,0,AC7) -> 0 | C7: MTA | L7: =IF(ISBLANK(B7),0,IF(T7=0,0,F7-H7)) -> 0 | M7: =IF(ISBLANK(B7),0,IF(T7=0,0,IF(W7<0,0,W7))) | N7: =IF(ISBLANK(B7),0,IF(T7=0,0,IF(AP7=0,Y7,IF(AP7<>3,0,Y7)))) | P7: =IF(B7="","",IF(C7="",$AA$1,IF(AQ7<>2,$AC$1,IF(AP7=0,"",IF(D7="",$AE$1,IF(E7="",$AB$1,IF(AP7<>3,$AL$1,IF(AR7>0,$Y$1,"")))))))) | S7: =IF(P7="",0,1) -> 0 | T7: =IF(ISERROR(X7),4,X7) | U7: =IF(ISBLANK(K7),T7,IF(K7=0,0,IF(K7>T7,K7,T7))) | V7: =IF(L7=0,0,IF(U7=0,0,ROUND(L7*1/U7,0))) | W7: =IF(V7<=AA7,V7,AA7) -> 0 | X7: =IF(ISBLANK($B7),0,VLOOKUP($B7,$B$322:$C$343,2,FALSE)) -> 0 | Y7: =IF(AA7-V7<=0,0,AA7-V7) -> 0 | AA7: =G7-J7 -> 0 | AC7: =IF(AD7=3,AC6+1,AC6) -> 0 | AD7: =SUM(AE7:AG7) -> 0 | AE7: =IF(ISBLANK(H7),0,1) -> 0 | AF7: =IF(ISBLANK(I7),0,1) -> 0 | AG7: =IF(ISBLANK(J7),0,1) -> 0 | AH7: =G7-J7 -> 0 | AI7: =IF(ISBLANK(E7),9999999,E7) | AJ7: =F7 -> 0 | AK7: =G7 -> 0 | AM7: =IF(ISBLANK(H7),0,1) -> 0 | AN7: =IF(ISBLANK(I7),0,1) -> 0 | AO7: =IF(ISBLANK(J7),0,1) -> 0 | AP7: =SUM(AM7:AO7) -> 0 | AQ7: =IF(B7="",0,COUNT(F7:G7)) | AR7: =IF(J7>G7,1,IF(I7>E7,1,IF(H7>F7,1,0))) | BA7: =IF(ISERROR(BB7),2001,2009) | BB7: =VLOOKUP(B7,$B$340:$C$343,2,FALSE) -> #N/A
A8: =IF(AC8=AC7,0,AC8) -> 0 | C8: MTA | L8: =IF(ISBLANK(B8),0,IF(T8=0,0,F8-H8)) -> 0 | M8: =IF(ISBLANK(B8),0,IF(T8=0,0,IF(W8<0,0,W8))) -> 0 | N8: =IF(ISBLANK(B8),0,IF(T8=0,0,IF(AP8=0,Y8,IF(AP8<>3,0,Y8)))) -> 0 | P8: =IF(B8="","",IF(C8="",$AA$1,IF(AQ8<>2,$AC$1,IF(AP8=0,"",IF(D8="",$AE$1,IF(E8="",$AB$1,IF(AP8<>3,$AL$1,IF(AR8>0,$Y$1,"")))))))) | S8: =IF(P8="",0,1) -> 0 | T8: =IF(ISERROR(X8),4,X8) | U8: =IF(ISBLANK(K8),T8,IF(K8=0,0,IF(K8>T8,K8,T8))) -> 0 | V8: =IF(L8=0,0,IF(U8=0,0,ROUND(L8*1/U8,0))) -> 0 | W8: =IF(V8<=AA8,V8,AA8) -> 0 | X8: =IF(ISBLANK($B8),0,VLOOKUP($B8,$B$322:$C$343,2,FALSE)) -> 0 | Y8: =IF(AA8-V8<=0,0,AA8-V8) -> 0 | AA8: =G8-J8 -> 0 | AC8: =IF(AD8=3,AC7+1,AC7) -> 0 | AD8: =SUM(AE8:AG8) -> 0 | AE8: =IF(ISBLANK(H8),0,1) -> 0 | AF8: =IF(ISBLANK(I8),0,1) -> 0 | AG8: =IF(ISBLANK(J8),0,1) -> 0 | AH8: =G8-J8 -> 0 | AI8: =IF(ISBLANK(E8),9999999,E8) -> 9999999 | AJ8: =F8 -> 0 | AK8: =G8 -> 0 | AM8: =IF(ISBLANK(H8),0,1) -> 0 | AN8: =IF(ISBLANK(I8),0,1) -> 0 | AO8: =IF(ISBLANK(J8),0,1) -> 0 | AP8: =SUM(AM8:AO8) -> 0 | AQ8: =IF(B8="",0,COUNT(F8:G8)) -> 0 | AR8: =IF(J8>G8,1,IF(I8>E8,1,IF(H8>F8,1,0))) -> 0 | BA8: =IF(ISERROR(BB8),2001,2009) -> 2001 | BB8: =VLOOKUP(B8,$B$340:$C$343,2,FALSE) -> #N/A | CA8: Untaxed
A9: =IF(AC9=AC8,0,AC9) -> 0 | C9: MTA | L9: =IF(ISBLANK(B9),0,IF(T9=0,0,F9-H9)) -> 0 | M9: =IF(ISBLANK(B9),0,IF(T9=0,0,IF(W9<0,0,W9))) -> 0 | N9: =IF(ISBLANK(B9),0,IF(T9=0,0,IF(AP9=0,Y9,IF(AP9<>3,0,Y9)))) -> 0 | P9: =IF(B9="","",IF(C9="",$AA$1,IF(AQ9<>2,$AC$1,IF(AP9=0,"",IF(D9="",$AE$1,IF(E9="",$AB$1,IF(AP9<>3,$AL$1,IF(AR9>0,$Y$1,"")))))))) | S9: =IF(P9="",0,1) -> 0 | T9: =IF(ISERROR(X9),4,X9) -> 0 | U9: =IF(ISBLANK(K9),T9,IF(K9=0,0,IF(K9>T9,K9,T9))) -> 0 | V9: =IF(L9=0,0,IF(U9=0,0,ROUND(L9*1/U9,0))) -> 0 | W9: =IF(V9<=AA9,V9,AA9) -> 0 | X9: =IF(ISBLANK($B9),0,VLOOKUP($B9,$B$322:$C$343,2,FALSE)) -> 0 | Y9: =IF(AA9-V9<=0,0,AA9-V9) -> 0 | AA9: =G9-J9 -> 0 | AC9: =IF(AD9=3,AC8+1,AC8) -> 0 | AD9: =SUM(AE9:AG9) -> 0 | AE9: =IF(ISBLANK(H9),0,1) -> 0 | AF9: =IF(ISBLANK(I9),0,1) -> 0 | AG9: =IF(ISBLANK(J9),0,1) -> 0 | AH9: =G9-J9 -> 0 | AI9: =IF(ISBLANK(E9),9999999,E9) -> 9999999 | AJ9: =F9 -> 0 | AK9: =G9 -> 0 | AM9: =IF(ISBLANK(H9),0,1) -> 0 | AN9: =IF(ISBLANK(I9),0,1) -> 0 | AO9: =IF(ISBLANK(J9),0,1) -> 0 | AP9: =SUM(AM9:AO9) -> 0 | AQ9: =IF(B9="",0,COUNT(F9:G9)) -> 0 | AR9: =IF(J9>G9,1,IF(I9>E9,1,IF(H9>F9,1,0))) -> 0 | BA9: =IF(ISERROR(BB9),2001,2009) -> 2001 | BB9: =VLOOKUP(B9,$B$340:$C$343,2,FALSE) -> #N/A
A10: =IF(AC10=AC9,0,AC10) -> 0 | C10: MTA | L10: =IF(ISBLANK(B10),0,IF(T10=0,0,F10-H10)) -> 0 | M10: =IF(ISBLANK(B10),0,IF(T10=0,0,IF(W10<0,0,W10))) -> 0 | N10: =IF(ISBLANK(B10),0,IF(T10=0,0,IF(AP10=0,Y10,IF(AP10<>3,0,Y10)))) -> 0 | P10: =IF(B10="","",IF(C10="",$AA$1,IF(AQ10<>2,$AC$1,IF(AP10=0,"",IF(D10="",$AE$1,IF(E10="",$AB$1,IF(AP10<>3,$AL$1,IF(AR10>0,$Y$1,"")))))))) | S10: =IF(P10="",0,1) -> 0 | T10: =IF(ISERROR(X10),4,X10) -> 0 | U10: =IF(ISBLANK(K10),T10,IF(K10=0,0,IF(K10>T10,K10,T10))) -> 0 | V10: =IF(L10=0,0,IF(U10=0,0,ROUND(L10*1/U10,0))) -> 0 | W10: =IF(V10<=AA10,V10,AA10) -> 0 | X10: =IF(ISBLANK($B10),0,VLOOKUP($B10,$B$322:$C$343,2,FALSE)) -> 0 | Y10: =IF(AA10-V10<=0,0,AA10-V10) -> 0 | AA10: =G10-J10 -> 0 | AC10: =IF(AD10=3,AC9+1,AC9) -> 0 | AD10: =SUM(AE10:AG10) -> 0 | AE10: =IF(ISBLANK(H10),0,1) -> 0 | AF10: =IF(ISBLANK(I10),0,1) -> 0 | AG10: =IF(ISBLANK(J10),0,1) -> 0 | AH10: =G10-J10 -> 0 | AI10: =IF(ISBLANK(E10),9999999,E10) -> 9999999 | AJ10: =F10 -> 0 | AK10: =G10 -> 0 | AM10: =IF(ISBLANK(H10),0,1) -> 0 | AN10: =IF(ISBLANK(I10),0,1) -> 0 | AO10: =IF(ISBLANK(J10),0,1) -> 0 | AP10: =SUM(AM10:AO10) -> 0 | AQ10: =IF(B10="",0,COUNT(F10:G10)) -> 0 | AR10: =IF(J10>G10,1,IF(I10>E10,1,IF(H10>F10,1,0))) -> 0 | BA10: =IF(ISERROR(BB10),2001,2009) -> 2001 | BB10: =VLOOKUP(B10,$B$340:$C$343,2,FALSE) -> #N/A
A11: =IF(AC11=AC10,0,AC11) -> 0 | C11: MTA | L11: =IF(ISBLANK(B11),0,IF(T11=0,0,F11-H11)) -> 0 | M11: =IF(ISBLANK(B11),0,IF(T11=0,0,IF(W11<0,0,W11))) -> 0 | N11: =IF(ISBLANK(B11),0,IF(T11=0,0,IF(AP11=0,Y11,IF(AP11<>3,0,Y11)))) -> 0 | P11: =IF(B11="","",IF(C11="",$AA$1,IF(AQ11<>2,$AC$1,IF(AP11=0,"",IF(D11="",$AE$1,IF(E11="",$AB$1,IF(AP11<>3,$AL$1,IF(AR11>0,$Y$1,"")))))))) | S11: =IF(P11="",0,1) -> 0 | T11: =IF(ISERROR(X11),4,X11) -> 0 | U11: =IF(ISBLANK(K11),T11,IF(K11=0,0,IF(K11>T11,K11,T11))) -> 0 | V11: =IF(L11=0,0,IF(U11=0,0,ROUND(L11*1/U11,0))) -> 0 | W11: =IF(V11<=AA11,V11,AA11) -> 0 | X11: =IF(ISBLANK($B11),0,VLOOKUP($B11,$B$322:$C$343,2,FALSE)) -> 0 | Y11: =IF(AA11-V11<=0,0,AA11-V11) -> 0 | AA11: =G11-J11 -> 0 | AC11: =IF(AD11=3,AC10+1,AC10) -> 0 | AD11: =SUM(AE11:AG11) -> 0 | AE11: =IF(ISBLANK(H11),0,1) -> 0 | AF11: =IF(ISBLANK(I11),0,1) -> 0 | AG11: =IF(ISBLANK(J11),0,1) -> 0 | AH11: =G11-J11 -> 0 | AI11: =IF(ISBLANK(E11),9999999,E11) -> 9999999 | AJ11: =F11 -> 0 | AK11: =G11 -> 0 | AM11: =IF(ISBLANK(H11),0,1) -> 0 | AN11: =IF(ISBLANK(I11),0,1) -> 0 | AO11: =IF(ISBLANK(J11),0,1) -> 0 | AP11: =SUM(AM11:AO11) -> 0 | AQ11: =IF(B11="",0,COUNT(F11:G11)) -> 0 | AR11: =IF(J11>G11,1,IF(I11>E11,1,IF(H11>F11,1,0))) -> 0 | BA11: =IF(ISERROR(BB11),2001,2009) -> 2001 | BB11: =VLOOKUP(B11,$B$340:$C$343,2,FALSE) -> #N/A
A12: =IF(AC12=AC11,0,AC12) -> 0 | C12: MTA | L12: =IF(ISBLANK(B12),0,IF(T12=0,0,F12-H12)) -> 0 | M12: =IF(ISBLANK(B12),0,IF(T12=0,0,IF(W12<0,0,W12))) -> 0 | N12: =IF(ISBLANK(B12),0,IF(T12=0,0,IF(AP12=0,Y12,IF(AP12<>3,0,Y12)))) -> 0 | P12: =IF(B12="","",IF(C12="",$AA$1,IF(AQ12<>2,$AC$1,IF(AP12=0,"",IF(D12="",$AE$1,IF(E12="",$AB$1,IF(AP12<>3,$AL$1,IF(AR12>0,$Y$1,"")))))))) | S12: =IF(P12="",0,1) -> 0 | T12: =IF(ISERROR(X12),4,X12) -> 0 | U12: =IF(ISBLANK(K12),T12,IF(K12=0,0,IF(K12>T12,K12,T12))) -> 0 | V12: =IF(L12=0,0,IF(U12=0,0,ROUND(L12*1/U12,0))) -> 0 | W12: =IF(V12<=AA12,V12,AA12) -> 0 | X12: =IF(ISBLANK($B12),0,VLOOKUP($B12,$B$322:$C$343,2,FALSE)) -> 0 | Y12: =IF(AA12-V12<=0,0,AA12-V12) -> 0 | AA12: =G12-J12 -> 0 | AC12: =IF(AD12=3,AC11+1,AC11) -> 0 | AD12: =SUM(AE12:AG12) -> 0 | AE12: =IF(ISBLANK(H12),0,1) -> 0 | AF12: =IF(ISBLANK(I12),0,1) -> 0 | AG12: =IF(ISBLANK(J12),0,1) -> 0 | AH12: =G12-J12 -> 0 | AI12: =IF(ISBLANK(E12),9999999,E12) -> 9999999 | AJ12: =F12 -> 0 | AK12: =G12 -> 0 | AM12: =IF(ISBLANK(H12),0,1) -> 0 | AN12: =IF(ISBLANK(I12),0,1) -> 0 | AO12: =IF(ISBLANK(J12),0,1) -> 0 | AP12: =SUM(AM12:AO12) -> 0 | AQ12: =IF(B12="",0,COUNT(F12:G12)) -> 0 | AR12: =IF(J12>G12,1,IF(I12>E12,1,IF(H12>F12,1,0))) -> 0 | BA12: =IF(ISERROR(BB12),2001,2009) -> 2001 | BB12: =VLOOKUP(B12,$B$340:$C$343,2,FALSE) -> #N/A
A13: =IF(AC13=AC12,0,AC13) -> 0 | C13: MTA | L13: =IF(ISBLANK(B13),0,IF(T13=0,0,F13-H13)) -> 0 | M13: =IF(ISBLANK(B13),0,IF(T13=0,0,IF(W13<0,0,W13))) -> 0 | N13: =IF(ISBLANK(B13),0,IF(T13=0,0,IF(AP13=0,Y13,IF(AP13<>3,0,Y13)))) -> 0 | P13: =IF(B13="","",IF(C13="",$AA$1,IF(AQ13<>2,$AC$1,IF(AP13=0,"",IF(D13="",$AE$1,IF(E13="",$AB$1,IF(AP13<>3,$AL$1,IF(AR13>0,$Y$1,"")))))))) | S13: =IF(P13="",0,1) -> 0 | T13: =IF(ISERROR(X13),4,X13) -> 0 | U13: =IF(ISBLANK(K13),T13,IF(K13=0,0,IF(K13>T13,K13,T13))) -> 0 | V13: =IF(L13=0,0,IF(U13=0,0,ROUND(L13*1/U13,0))) -> 0 | W13: =IF(V13<=AA13,V13,AA13) -> 0 | X13: =IF(ISBLANK($B13),0,VLOOKUP($B13,$B$322:$C$343,2,FALSE)) -> 0 | Y13: =IF(AA13-V13<=0,0,AA13-V13) -> 0 | AA13: =G13-J13 -> 0 | AC13: =IF(AD13=3,AC12+1,AC12) -> 0 | AD13: =SUM(AE13:AG13) -> 0 | AE13: =IF(ISBLANK(H13),0,1) -> 0 | AF13: =IF(ISBLANK(I13),0,1) -> 0 | AG13: =IF(ISBLANK(J13),0,1) -> 0 | AH13: =G13-J13 -> 0 | AI13: =IF(ISBLANK(E13),9999999,E13) -> 9999999 | AJ13: =F13 -> 0 | AK13: =G13 -> 0 | AM13: =IF(ISBLANK(H13),0,1) -> 0 | AN13: =IF(ISBLANK(I13),0,1) -> 0 | AO13: =IF(ISBLANK(J13),0,1) -> 0 | AP13: =SUM(AM13:AO13) -> 0 | AQ13: =IF(B13="",0,COUNT(F13:G13)) -> 0 | AR13: =IF(J13>G13,1,IF(I13>E13,1,IF(H13>F13,1,0))) -> 0 | BA13: =IF(ISERROR(BB13),2001,2009) -> 2001 | BB13: =VLOOKUP(B13,$B$340:$C$343,2,FALSE) -> #N/A
A14: =IF(AC14=AC13,0,AC14) -> 0 | C14: MTA | L14: =IF(ISBLANK(B14),0,IF(T14=0,0,F14-H14)) -> 0 | M14: =IF(ISBLANK(B14),0,IF(T14=0,0,IF(W14<0,0,W14))) -> 0 | N14: =IF(ISBLANK(B14),0,IF(T14=0,0,IF(AP14=0,Y14,IF(AP14<>3,0,Y14)))) -> 0 | P14: =IF(B14="","",IF(C14="",$AA$1,IF(AQ14<>2,$AC$1,IF(AP14=0,"",IF(D14="",$AE$1,IF(E14="",$AB$1,IF(AP14<>3,$AL$1,IF(AR14>0,$Y$1,"")))))))) | S14: =IF(P14="",0,1) -> 0 | T14: =IF(ISERROR(X14),4,X14) -> 0 | U14: =IF(ISBLANK(K14),T14,IF(K14=0,0,IF(K14>T14,K14,T14))) -> 0 | V14: =IF(L14=0,0,IF(U14=0,0,ROUND(L14*1/U14,0))) -> 0 | W14: =IF(V14<=AA14,V14,AA14) -> 0 | X14: =IF(ISBLANK($B14),0,VLOOKUP($B14,$B$322:$C$343,2,FALSE)) -> 0 | Y14: =IF(AA14-V14<=0,0,AA14-V14) -> 0 | AA14: =G14-J14 -> 0 | AC14: =IF(AD14=3,AC13+1,AC13) -> 0 | AD14: =SUM(AE14:AG14) -> 0 | AE14: =IF(ISBLANK(H14),0,1) -> 0 | AF14: =IF(ISBLANK(I14),0,1) -> 0 | AG14: =IF(ISBLANK(J14),0,1) -> 0 | AH14: =G14-J14 -> 0 | AI14: =IF(ISBLANK(E14),9999999,E14) -> 9999999 | AJ14: =F14 -> 0 | AK14: =G14 -> 0 | AM14: =IF(ISBLANK(H14),0,1) -> 0 | AN14: =IF(ISBLANK(I14),0,1) -> 0 | AO14: =IF(ISBLANK(J14),0,1) -> 0 | AP14: =SUM(AM14:AO14) -> 0 | AQ14: =IF(B14="",0,COUNT(F14:G14)) -> 0 | AR14: =IF(J14>G14,1,IF(I14>E14,1,IF(H14>F14,1,0))) -> 0 | BA14: =IF(ISERROR(BB14),2001,2009) -> 2001 | BB14: =VLOOKUP(B14,$B$340:$C$343,2,FALSE) -> #N/A
A15: =IF(AC15=AC14,0,AC15) -> 0 | C15: MTA | L15: =IF(ISBLANK(B15),0,IF(T15=0,0,F15-H15)) -> 0 | M15: =IF(ISBLANK(B15),0,IF(T15=0,0,IF(W15<0,0,W15))) -> 0 | N15: =IF(ISBLANK(B15),0,IF(T15=0,0,IF(AP15=0,Y15,IF(AP15<>3,0,Y15)))) -> 0 | P15: =IF(B15="","",IF(C15="",$AA$1,IF(AQ15<>2,$AC$1,IF(AP15=0,"",IF(D15="",$AE$1,IF(E15="",$AB$1,IF(AP15<>3,$AL$1,IF(AR15>0,$Y$1,"")))))))) | S15: =IF(P15="",0,1) -> 0 | T15: =IF(ISERROR(X15),4,X15) -> 0 | U15: =IF(ISBLANK(K15),T15,IF(K15=0,0,IF(K15>T15,K15,T15))) -> 0 | V15: =IF(L15=0,0,IF(U15=0,0,ROUND(L15*1/U15,0))) -> 0 | W15: =IF(V15<=AA15,V15,AA15) -> 0 | X15: =IF(ISBLANK($B15),0,VLOOKUP($B15,$B$322:$C$343,2,FALSE)) -> 0 | Y15: =IF(AA15-V15<=0,0,AA15-V15) -> 0 | AA15: =G15-J15 -> 0 | AC15: =IF(AD15=3,AC14+1,AC14) -> 0 | AD15: =SUM(AE15:AG15) -> 0 | AE15: =IF(ISBLANK(H15),0,1) -> 0 | AF15: =IF(ISBLANK(I15),0,1) -> 0 | AG15: =IF(ISBLANK(J15),0,1) -> 0 | AH15: =G15-J15 -> 0 | AI15: =IF(ISBLANK(E15),9999999,E15) -> 9999999 | AJ15: =F15 -> 0 | AK15: =G15 -> 0 | AM15: =IF(ISBLANK(H15),0,1) -> 0 | AN15: =IF(ISBLANK(I15),0,1) -> 0 | AO15: =IF(ISBLANK(J15),0,1) -> 0 | AP15: =SUM(AM15:AO15) -> 0 | AQ15: =IF(B15="",0,COUNT(F15:G15)) -> 0 | AR15: =IF(J15>G15,1,IF(I15>E15,1,IF(H15>F15,1,0))) -> 0 | BA15: =IF(ISERROR(BB15),2001,2009) -> 2001 | BB15: =VLOOKUP(B15,$B$340:$C$343,2,FALSE) -> #N/A
A16: =IF(AC16=AC15,0,AC16) -> 0 | C16: MTA | L16: =IF(ISBLANK(B16),0,IF(T16=0,0,F16-H16)) -> 0 | M16: =IF(ISBLANK(B16),0,IF(T16=0,0,IF(W16<0,0,W16))) -> 0 | N16: =IF(ISBLANK(B16),0,IF(T16=0,0,IF(AP16=0,Y16,IF(AP16<>3,0,Y16)))) -> 0 | P16: =IF(B16="","",IF(C16="",$AA$1,IF(AQ16<>2,$AC$1,IF(AP16=0,"",IF(D16="",$AE$1,IF(E16="",$AB$1,IF(AP16<>3,$AL$1,IF(AR16>0,$Y$1,"")))))))) | S16: =IF(P16="",0,1) -> 0 | T16: =IF(ISERROR(X16),4,X16) -> 0 | U16: =IF(ISBLANK(K16),T16,IF(K16=0,0,IF(K16>T16,K16,T16))) -> 0 | V16: =IF(L16=0,0,IF(U16=0,0,ROUND(L16*1/U16,0))) -> 0 | W16: =IF(V16<=AA16,V16,AA16) -> 0 | X16: =IF(ISBLANK($B16),0,VLOOKUP($B16,$B$322:$C$343,2,FALSE)) -> 0 | Y16: =IF(AA16-V16<=0,0,AA16-V16) -> 0 | AA16: =G16-J16 -> 0 | AC16: =IF(AD16=3,AC15+1,AC15) -> 0 | AD16: =SUM(AE16:AG16) -> 0 | AE16: =IF(ISBLANK(H16),0,1) -> 0 | AF16: =IF(ISBLANK(I16),0,1) -> 0 | AG16: =IF(ISBLANK(J16),0,1) -> 0 | AH16: =G16-J16 -> 0 | AI16: =IF(ISBLANK(E16),9999999,E16) -> 9999999 | AJ16: =F16 -> 0 | AK16: =G16 -> 0 | AM16: =IF(ISBLANK(H16),0,1) -> 0 | AN16: =IF(ISBLANK(I16),0,1) -> 0 | AO16: =IF(ISBLANK(J16),0,1) -> 0 | AP16: =SUM(AM16:AO16) -> 0 | AQ16: =IF(B16="",0,COUNT(F16:G16)) -> 0 | AR16: =IF(J16>G16,1,IF(I16>E16,1,IF(H16>F16,1,0))) -> 0 | BA16: =IF(ISERROR(BB16),2001,2009) -> 2001 | BB16: =VLOOKUP(B16,$B$340:$C$343,2,FALSE) -> #N/A
A17: =IF(AC17=AC16,0,AC17) -> 0 | C17: MTA | L17: =IF(ISBLANK(B17),0,IF(T17=0,0,F17-H17)) -> 0 | M17: =IF(ISBLANK(B17),0,IF(T17=0,0,IF(W17<0,0,W17))) -> 0 | N17: =IF(ISBLANK(B17),0,IF(T17=0,0,IF(AP17=0,Y17,IF(AP17<>3,0,Y17)))) -> 0 | P17: =IF(B17="","",IF(C17="",$AA$1,IF(AQ17<>2,$AC$1,IF(AP17=0,"",IF(D17="",$AE$1,IF(E17="",$AB$1,IF(AP17<>3,$AL$1,IF(AR17>0,$Y$1,"")))))))) | S17: =IF(P17="",0,1) -> 0 | T17: =IF(ISERROR(X17),4,X17) -> 0 | U17: =IF(ISBLANK(K17),T17,IF(K17=0,0,IF(K17>T17,K17,T17))) -> 0 | V17: =IF(L17=0,0,IF(U17=0,0,ROUND(L17*1/U17,0))) -> 0 | W17: =IF(V17<=AA17,V17,AA17) -> 0 | X17: =IF(ISBLANK($B17),0,VLOOKUP($B17,$B$322:$C$343,2,FALSE)) -> 0 | Y17: =IF(AA17-V17<=0,0,AA17-V17) -> 0 | AA17: =G17-J17 -> 0 | AC17: =IF(AD17=3,AC16+1,AC16) -> 0 | AD17: =SUM(AE17:AG17) -> 0 | AE17: =IF(ISBLANK(H17),0,1) -> 0 | AF17: =IF(ISBLANK(I17),0,1) -> 0 | AG17: =IF(ISBLANK(J17),0,1) -> 0 | AH17: =G17-J17 -> 0 | AI17: =IF(ISBLANK(E17),9999999,E17) -> 9999999 | AJ17: =F17 -> 0 | AK17: =G17 -> 0 | AM17: =IF(ISBLANK(H17),0,1) -> 0 | AN17: =IF(ISBLANK(I17),0,1) -> 0 | AO17: =IF(ISBLANK(J17),0,1) -> 0 | AP17: =SUM(AM17:AO17) -> 0 | AQ17: =IF(B17="",0,COUNT(F17:G17)) -> 0 | AR17: =IF(J17>G17,1,IF(I17>E17,1,IF(H17>F17,1,0))) -> 0 | BA17: =IF(ISERROR(BB17),2001,2009) -> 2001 | BB17: =VLOOKUP(B17,$B$340:$C$343,2,FALSE) -> #N/A
A18: =IF(AC18=AC17,0,AC18) -> 0 | C18: MTA | L18: =IF(ISBLANK(B18),0,IF(T18=0,0,F18-H18)) | M18: =IF(ISBLANK(B18),0,IF(T18=0,0,IF(W18<0,0,W18))) | N18: =IF(ISBLANK(B18),0,IF(T18=0,0,IF(AP18=0,Y18,IF(AP18<>3,0,Y18)))) | P18: =IF(B18="","",IF(C18="",$AA$1,IF(AQ18<>2,$AC$1,IF(AP18=0,"",IF(D18="",$AE$1,IF(E18="",$AB$1,IF(AP18<>3,$AL$1,IF(AR18>0,$Y$1,"")))))))) | S18: =IF(P18="",0,1) | T18: =IF(ISERROR(X18),4,X18) | U18: =IF(ISBLANK(K18),T18,IF(K18=0,0,IF(K18>T18,K18,T18))) | V18: =IF(L18=0,0,IF(U18=0,0,ROUND(L18*1/U18,0))) | W18: =IF(V18<=AA18,V18,AA18) | X18: =IF(ISBLANK($B18),0,VLOOKUP($B18,$B$322:$C$343,2,FALSE)) | Y18: =IF(AA18-V18<=0,0,AA18-V18) | AA18: =G18-J18 | AC18: =IF(AD18=3,AC17+1,AC17) | AD18: =SUM(AE18:AG18) | AE18: =IF(ISBLANK(H18),0,1) | AF18: =IF(ISBLANK(I18),0,1) | AG18: =IF(ISBLANK(J18),0,1) | AH18: =G18-J18 | AI18: =IF(ISBLANK(E18),9999999,E18) | AJ18: =F18 | AK18: =G18 | AM18: =IF(ISBLANK(H18),0,1) | AN18: =IF(ISBLANK(I18),0,1) | AO18: =IF(ISBLANK(J18),0,1) | AP18: =SUM(AM18:AO18) | AQ18: =IF(B18="",0,COUNT(F18:G18)) | AR18: =IF(J18>G18,1,IF(I18>E18,1,IF(H18>F18,1,0))) | BA18: =IF(ISERROR(BB18),2001,2009) | BB18: =VLOOKUP(B18,$B$340:$C$343,2,FALSE)
A19: =IF(AC19=AC18,0,AC19) -> 0 | C19: MTA | L19: =IF(ISBLANK(B19),0,IF(T19=0,0,F19-H19)) -> 0 | M19: =IF(ISBLANK(B19),0,IF(T19=0,0,IF(W19<0,0,W19))) -> 0 | N19: =IF(ISBLANK(B19),0,IF(T19=0,0,IF(AP19=0,Y19,IF(AP19<>3,0,Y19)))) -> 0 | P19: =IF(B19="","",IF(C19="",$AA$1,IF(AQ19<>2,$AC$1,IF(AP19=0,"",IF(D19="",$AE$1,IF(E19="",$AB$1,IF(AP19<>3,$AL$1,IF(AR19>0,$Y$1,"")))))))) | S19: =IF(P19="",0,1) -> 0 | T19: =IF(ISERROR(X19),4,X19) -> 0 | U19: =IF(ISBLANK(K19),T19,IF(K19=0,0,IF(K19>T19,K19,T19))) -> 0 | V19: =IF(L19=0,0,IF(U19=0,0,ROUND(L19*1/U19,0))) -> 0 | W19: =IF(V19<=AA19,V19,AA19) -> 0 | X19: =IF(ISBLANK($B19),0,VLOOKUP($B19,$B$322:$C$343,2,FALSE)) -> 0 | Y19: =IF(AA19-V19<=0,0,AA19-V19) -> 0 | AA19: =G19-J19 -> 0 | AC19: =IF(AD19=3,AC18+1,AC18) -> 0 | AD19: =SUM(AE19:AG19) -> 0 | AE19: =IF(ISBLANK(H19),0,1) -> 0 | AF19: =IF(ISBLANK(I19),0,1) -> 0 | AG19: =IF(ISBLANK(J19),0,1) -> 0 | AH19: =G19-J19 -> 0 | AI19: =IF(ISBLANK(E19),9999999,E19) -> 9999999 | AJ19: =F19 -> 0 | AK19: =G19 -> 0 | AM19: =IF(ISBLANK(H19),0,1) -> 0 | AN19: =IF(ISBLANK(I19),0,1) -> 0 | AO19: =IF(ISBLANK(J19),0,1) -> 0 | AP19: =SUM(AM19:AO19) -> 0 | AQ19: =IF(B19="",0,COUNT(F19:G19)) -> 0 | AR19: =IF(J19>G19,1,IF(I19>E19,1,IF(H19>F19,1,0))) -> 0 | BA19: =IF(ISERROR(BB19),2001,2009) -> 2001 | BB19: =VLOOKUP(B19,$B$340:$C$343,2,FALSE) -> #N/A
A20: =IF(AC20=AC19,0,AC20) -> 0 | C20: MTA | L20: =IF(ISBLANK(B20),0,IF(T20=0,0,F20-H20)) -> 0 | M20: =IF(ISBLANK(B20),0,IF(T20=0,0,IF(W20<0,0,W20))) -> 0 | N20: =IF(ISBLANK(B20),0,IF(T20=0,0,IF(AP20=0,Y20,IF(AP20<>3,0,Y20)))) -> 0 | P20: =IF(B20="","",IF(C20="",$AA$1,IF(AQ20<>2,$AC$1,IF(AP20=0,"",IF(D20="",$AE$1,IF(E20="",$AB$1,IF(AP20<>3,$AL$1,IF(AR20>0,$Y$1,"")))))))) | S20: =IF(P20="",0,1) -> 0 | T20: =IF(ISERROR(X20),4,X20) -> 0 | U20: =IF(ISBLANK(K20),T20,IF(K20=0,0,IF(K20>T20,K20,T20))) -> 0 | V20: =IF(L20=0,0,IF(U20=0,0,ROUND(L20*1/U20,0))) -> 0 | W20: =IF(V20<=AA20,V20,AA20) -> 0 | X20: =IF(ISBLANK($B20),0,VLOOKUP($B20,$B$322:$C$343,2,FALSE)) -> 0 | Y20: =IF(AA20-V20<=0,0,AA20-V20) -> 0 | AA20: =G20-J20 -> 0 | AC20: =IF(AD20=3,AC19+1,AC19) -> 0 | AD20: =SUM(AE20:AG20) -> 0 | AE20: =IF(ISBLANK(H20),0,1) -> 0 | AF20: =IF(ISBLANK(I20),0,1) -> 0 | AG20: =IF(ISBLANK(J20),0,1) -> 0 | AH20: =G20-J20 -> 0 | AI20: =IF(ISBLANK(E20),9999999,E20) -> 9999999 | AJ20: =F20 -> 0 | AK20: =G20 -> 0 | AM20: =IF(ISBLANK(H20),0,1) -> 0 | AN20: =IF(ISBLANK(I20),0,1) -> 0 | AO20: =IF(ISBLANK(J20),0,1) -> 0 | AP20: =SUM(AM20:AO20) -> 0 | AQ20: =IF(B20="",0,COUNT(F20:G20)) -> 0 | AR20: =IF(J20>G20,1,IF(I20>E20,1,IF(H20>F20,1,0))) -> 0 | BA20: =IF(ISERROR(BB20),2001,2009) -> 2001 | BB20: =VLOOKUP(B20,$B$340:$C$343,2,FALSE) -> #N/A
... A32: =IF(AC32=AC31,0,AC32) -> 0 | C32: MTA | L32: =IF(ISBLANK(B32),0,IF(T32=0,0,F32-H32)) -> 0 | M32: =IF(ISBLANK(B32),0,IF(T32=0,0,IF(W32<0,0,W32))) -> 0 | N32: =IF(ISBLANK(B32),0,IF(T32=0,0,IF(AP32=0,Y32,IF(AP32<>3,0,Y32)))) -> 0 | P32: =IF(B32="","",IF(C32="",$AA$1,IF(AQ32<>2,$AC$1,IF(AP32=0,"",IF(D32="",$AE$1,IF(E32="",$AB$1,IF(AP32<>3,$AL$1,IF(AR32>0,$Y$1,"")))))))) | S32: =IF(P32="",0,1) -> 0 | T32: =IF(ISERROR(X32),4,X32) -> 0 | U32: =IF(ISBLANK(K32),T32,IF(K32=0,0,IF(K32>T32,K32,T32))) -> 0 | V32: =IF(L32=0,0,IF(U32=0,0,ROUND(L32*1/U32,0))) -> 0 | W32: =IF(V32<=AA32,V32,AA32) -> 0 | X32: =IF(ISBLANK($B32),0,VLOOKUP($B32,$B$322:$C$343,2,FALSE)) -> 0 | Y32: =IF(AA32-V32<=0,0,AA32-V32) -> 0 | AA32: =G32-J32 -> 0 | AC32: =IF(AD32=3,AC31+1,AC31) -> 0 | AD32: =SUM(AE32:AG32) -> 0 | AE32: =IF(ISBLANK(H32),0,1) -> 0 | AF32: =IF(ISBLANK(I32),0,1) -> 0 | AG32: =IF(ISBLANK(J32),0,1) -> 0 | AH32: =G32-J32 -> 0 | AI32: =IF(ISBLANK(E32),9999999,E32) -> 9999999 | AJ32: =F32 -> 0 | AK32: =G32 -> 0 | AM32: =IF(ISBLANK(H32),0,1) -> 0 | AN32: =IF(ISBLANK(I32),0,1) -> 0 | AO32: =IF(ISBLANK(J32),0,1) -> 0 | AP32: =SUM(AM32:AO32) -> 0 | AQ32: =IF(B32="",0,COUNT(F32:G32)) -> 0 | AR32: =IF(J32>G32,1,IF(I32>E32,1,IF(H32>F32,1,0))) -> 0 | BA32: =IF(ISERROR(BB32),2001,2009) -> 2001 | BB32: =VLOOKUP(B32,$B$340:$C$343,2,FALSE) -> #N/A
A33: =IF(AC33=AC17,0,AC33) | C33: MTA | L33: =IF(ISBLANK(B33),0,IF(T33=0,0,F33-H33)) -> 0 | M33: =IF(ISBLANK(B33),0,IF(T33=0,0,IF(W33<0,0,W33))) -> 0 | N33: =IF(ISBLANK(B33),0,IF(T33=0,0,IF(AP33=0,Y33,IF(AP33<>3,0,Y33)))) -> 0 | P33: =IF(B33="","",IF(C33="",$AA$1,IF(AQ33<>2,$AC$1,IF(AP33=0,"",IF(D33="",$AE$1,IF(E33="",$AB$1,IF(AP33<>3,$AL$1,IF(AR33>0,$Y$1,"")))))))) | S33: =IF(P33="",0,1) -> 0 | T33: =IF(ISERROR(X33),4,X33) -> 0 | U33: =IF(ISBLANK(K33),T33,IF(K33=0,0,IF(K33>T33,K33,T33))) -> 0 | V33: =IF(L33=0,0,IF(U33=0,0,ROUND(L33*1/U33,0))) -> 0 | W33: =IF(V33<=AA33,V33,AA33) -> 0 | X33: =IF(ISBLANK($B33),0,VLOOKUP($B33,$B$322:$C$343,2,FALSE)) | Y33: =IF(AA33-V33<=0,0,AA33-V33) -> 0 | AA33: =G33-J33 -> 0 | AC33: =IF(AD33=3,AC32+1,AC32) -> 0 | AD33: =SUM(AE33:AG33) -> 0 | AE33: =IF(ISBLANK(H33),0,1) -> 0 | AF33: =IF(ISBLANK(I33),0,1) -> 0 | AG33: =IF(ISBLANK(J33),0,1) -> 0 | AH33: =G33-J33 -> 0 | AI33: =IF(ISBLANK(E33),9999999,E33) -> 9999999 | AJ33: =F33 -> 0 | AK33: =G33 -> 0 | AM33: =IF(ISBLANK(H33),0,1) -> 0 | AN33: =IF(ISBLANK(I33),0,1) -> 0 | AO33: =IF(ISBLANK(J33),0,1) -> 0 | AP33: =SUM(AM33:AO33) -> 0 | AQ33: =IF(B33="",0,COUNT(F33:G33)) -> 0 | AR33: =IF(J33>G33,1,IF(I33>E33,1,IF(H33>F33,1,0))) -> 0 | BA33: =IF(ISERROR(BB33),2001,2009) -> 2001 | BB33: =VLOOKUP(B33,$B$340:$C$343,2,FALSE)
A34: =IF(AC34=AC33,0,AC34) -> 0 | C34: MTA | L34: =IF(ISBLANK(B34),0,IF(T34=0,0,F34-H34)) -> 0 | M34: =IF(ISBLANK(B34),0,IF(T34=0,0,IF(W34<0,0,W34))) -> 0 | N34: =IF(ISBLANK(B34),0,IF(T34=0,0,IF(AP34=0,Y34,IF(AP34<>3,0,Y34)))) -> 0 | P34: =IF(B34="","",IF(C34="",$AA$1,IF(AQ34<>2,$AC$1,IF(AP34=0,"",IF(D34="",$AE$1,IF(E34="",$AB$1,IF(AP34<>3,$AL$1,IF(AR34>0,$Y$1,"")))))))) | S34: =IF(P34="",0,1) -> 0 | T34: =IF(ISERROR(X34),4,X34) -> 0 | U34: =IF(ISBLANK(K34),T34,IF(K34=0,0,IF(K34>T34,K34,T34))) -> 0 | V34: =IF(L34=0,0,IF(U34=0,0,ROUND(L34*1/U34,0))) -> 0 | W34: =IF(V34<=AA34,V34,AA34) -> 0 | X34: =IF(ISBLANK($B34),0,VLOOKUP($B34,$B$322:$C$343,2,FALSE)) -> 0 | Y34: =IF(AA34-V34<=0,0,AA34-V34) -> 0 | AA34: =G34-J34 -> 0 | AC34: =IF(AD34=3,AC33+1,AC33) -> 0 | AD34: =SUM(AE34:AG34) -> 0 | AE34: =IF(ISBLANK(H34),0,1) -> 0 | AF34: =IF(ISBLANK(I34),0,1) -> 0 | AG34: =IF(ISBLANK(J34),0,1) -> 0 | AH34: =G34-J34 -> 0 | AI34: =IF(ISBLANK(E34),9999999,E34) -> 9999999 | AJ34: =F34 -> 0 | AK34: =G34 -> 0 | AM34: =IF(ISBLANK(H34),0,1) -> 0 | AN34: =IF(ISBLANK(I34),0,1) -> 0 | AO34: =IF(ISBLANK(J34),0,1) -> 0 | AP34: =SUM(AM34:AO34) -> 0 | AQ34: =IF(B34="",0,COUNT(F34:G34)) -> 0 | AR34: =IF(J34>G34,1,IF(I34>E34,1,IF(H34>F34,1,0))) -> 0 | BA34: =IF(ISERROR(BB34),2001,2009) -> 2001 | BB34: =VLOOKUP(B34,$B$340:$C$343,2,FALSE) -> #N/A
A35: =IF(AC35=AC34,0,AC35) -> 0 | C35: MTA | L35: =IF(ISBLANK(B35),0,IF(T35=0,0,F35-H35)) -> 0 | M35: =IF(ISBLANK(B35),0,IF(T35=0,0,IF(W35<0,0,W35))) -> 0 | N35: =IF(ISBLANK(B35),0,IF(T35=0,0,IF(AP35=0,Y35,IF(AP35<>3,0,Y35)))) -> 0 | P35: =IF(B35="","",IF(C35="",$AA$1,IF(AQ35<>2,$AC$1,IF(AP35=0,"",IF(D35="",$AE$1,IF(E35="",$AB$1,IF(AP35<>3,$AL$1,IF(AR35>0,$Y$1,"")))))))) | S35: =IF(P35="",0,1) -> 0 | T35: =IF(ISERROR(X35),4,X35) -> 0 | U35: =IF(ISBLANK(K35),T35,IF(K35=0,0,IF(K35>T35,K35,T35))) -> 0 | V35: =IF(L35=0,0,IF(U35=0,0,ROUND(L35*1/U35,0))) -> 0 | W35: =IF(V35<=AA35,V35,AA35) -> 0 | X35: =IF(ISBLANK($B35),0,VLOOKUP($B35,$B$322:$C$343,2,FALSE)) -> 0 | Y35: =IF(AA35-V35<=0,0,AA35-V35) -> 0 | AA35: =G35-J35 -> 0 | AC35: =IF(AD35=3,AC34+1,AC34) -> 0 | AD35: =SUM(AE35:AG35) -> 0 | AE35: =IF(ISBLANK(H35),0,1) -> 0 | AF35: =IF(ISBLANK(I35),0,1) -> 0 | AG35: =IF(ISBLANK(J35),0,1) -> 0 | AH35: =G35-J35 -> 0 | AI35: =IF(ISBLANK(E35),9999999,E35) -> 9999999 | AJ35: =F35 -> 0 | AK35: =G35 -> 0 | AM35: =IF(ISBLANK(H35),0,1) -> 0 | AN35: =IF(ISBLANK(I35),0,1) -> 0 | AO35: =IF(ISBLANK(J35),0,1) -> 0 | AP35: =SUM(AM35:AO35) -> 0 | AQ35: =IF(B35="",0,COUNT(F35:G35)) -> 0 | AR35: =IF(J35>G35,1,IF(I35>E35,1,IF(H35>F35,1,0))) -> 0 | BA35: =IF(ISERROR(BB35),2001,2009) -> 2001 | BB35: =VLOOKUP(B35,$B$340:$C$343,2,FALSE) -> #N/A
A36: =IF(AC36=AC35,0,AC36) -> 0 | C36: MTA | L36: =IF(ISBLANK(B36),0,IF(T36=0,0,F36-H36)) -> 0 | M36: =IF(ISBLANK(B36),0,IF(T36=0,0,IF(W36<0,0,W36))) -> 0 | N36: =IF(ISBLANK(B36),0,IF(T36=0,0,IF(AP36=0,Y36,IF(AP36<>3,0,Y36)))) -> 0 | P36: =IF(B36="","",IF(C36="",$AA$1,IF(AQ36<>2,$AC$1,IF(AP36=0,"",IF(D36="",$AE$1,IF(E36="",$AB$1,IF(AP36<>3,$AL$1,IF(AR36>0,$Y$1,"")))))))) | S36: =IF(P36="",0,1) -> 0 | T36: =IF(ISERROR(X36),4,X36) -> 0 | U36: =IF(ISBLANK(K36),T36,IF(K36=0,0,IF(K36>T36,K36,T36))) -> 0 | V36: =IF(L36=0,0,IF(U36=0,0,ROUND(L36*1/U36,0))) -> 0 | W36: =IF(V36<=AA36,V36,AA36) -> 0 | X36: =IF(ISBLANK($B36),0,VLOOKUP($B36,$B$322:$C$343,2,FALSE)) -> 0 | Y36: =IF(AA36-V36<=0,0,AA36-V36) -> 0 | AA36: =G36-J36 -> 0 | AC36: =IF(AD36=3,AC35+1,AC35) -> 0 | AD36: =SUM(AE36:AG36) -> 0 | AE36: =IF(ISBLANK(H36),0,1) -> 0 | AF36: =IF(ISBLANK(I36),0,1) -> 0 | AG36: =IF(ISBLANK(J36),0,1) -> 0 | AH36: =G36-J36 -> 0 | AI36: =IF(ISBLANK(E36),9999999,E36) -> 9999999 | AJ36: =F36 -> 0 | AK36: =G36 -> 0 | AM36: =IF(ISBLANK(H36),0,1) -> 0 | AN36: =IF(ISBLANK(I36),0,1) -> 0 | AO36: =IF(ISBLANK(J36),0,1) -> 0 | AP36: =SUM(AM36:AO36) -> 0 | AQ36: =IF(B36="",0,COUNT(F36:G36)) -> 0 | AR36: =IF(J36>G36,1,IF(I36>E36,1,IF(H36>F36,1,0))) -> 0 | BA36: =IF(ISERROR(BB36),2001,2009) -> 2001 | BB36: =VLOOKUP(B36,$B$340:$C$343,2,FALSE) -> #N/A
A37: =IF(AC37=AC36,0,AC37) -> 0 | C37: MTA | L37: =IF(ISBLANK(B37),0,IF(T37=0,0,F37-H37)) -> 0 | M37: =IF(ISBLANK(B37),0,IF(T37=0,0,IF(W37<0,0,W37))) -> 0 | N37: =IF(ISBLANK(B37),0,IF(T37=0,0,IF(AP37=0,Y37,IF(AP37<>3,0,Y37)))) -> 0 | P37: =IF(B37="","",IF(C37="",$AA$1,IF(AQ37<>2,$AC$1,IF(AP37=0,"",IF(D37="",$AE$1,IF(E37="",$AB$1,IF(AP37<>3,$AL$1,IF(AR37>0,$Y$1,"")))))))) | S37: =IF(P37="",0,1) -> 0 | T37: =IF(ISERROR(X37),4,X37) -> 0 | U37: =IF(ISBLANK(K37),T37,IF(K37=0,0,IF(K37>T37,K37,T37))) -> 0 | V37: =IF(L37=0,0,IF(U37=0,0,ROUND(L37*1/U37,0))) -> 0 | W37: =IF(V37<=AA37,V37,AA37) -> 0 | X37: =IF(ISBLANK($B37),0,VLOOKUP($B37,$B$322:$C$343,2,FALSE)) -> 0 | Y37: =IF(AA37-V37<=0,0,AA37-V37) -> 0 | AA37: =G37-J37 -> 0 | AC37: =IF(AD37=3,AC36+1,AC36) -> 0 | AD37: =SUM(AE37:AG37) -> 0 | AE37: =IF(ISBLANK(H37),0,1) -> 0 | AF37: =IF(ISBLANK(I37),0,1) -> 0 | AG37: =IF(ISBLANK(J37),0,1) -> 0 | AH37: =G37-J37 -> 0 | AI37: =IF(ISBLANK(E37),9999999,E37) -> 9999999 | AJ37: =F37 -> 0 | AK37: =G37 -> 0 | AM37: =IF(ISBLANK(H37),0,1) -> 0 | AN37: =IF(ISBLANK(I37),0,1) -> 0 | AO37: =IF(ISBLANK(J37),0,1) -> 0 | AP37: =SUM(AM37:AO37) -> 0 | AQ37: =IF(B37="",0,COUNT(F37:G37)) -> 0 | AR37: =IF(J37>G37,1,IF(I37>E37,1,IF(H37>F37,1,0))) -> 0 | BA37: =IF(ISERROR(BB37),2001,2009) -> 2001 | BB37: =VLOOKUP(B37,$B$340:$C$343,2,FALSE) -> #N/A
A38: =IF(AC38=AC37,0,AC38) -> 0 | C38: MTA | L38: =IF(ISBLANK(B38),0,IF(T38=0,0,F38-H38)) -> 0 | M38: =IF(ISBLANK(B38),0,IF(T38=0,0,IF(W38<0,0,W38))) -> 0 | N38: =IF(ISBLANK(B38),0,IF(T38=0,0,IF(AP38=0,Y38,IF(AP38<>3,0,Y38)))) -> 0 | P38: =IF(B38="","",IF(C38="",$AA$1,IF(AQ38<>2,$AC$1,IF(AP38=0,"",IF(D38="",$AE$1,IF(E38="",$AB$1,IF(AP38<>3,$AL$1,IF(AR38>0,$Y$1,"")))))))) | S38: =IF(P38="",0,1) | T38: =IF(ISERROR(X38),4,X38) -> 0 | U38: =IF(ISBLANK(K38),T38,IF(K38=0,0,IF(K38>T38,K38,T38))) -> 0 | V38: =IF(L38=0,0,IF(U38=0,0,ROUND(L38*1/U38,0))) -> 0 | W38: =IF(V38<=AA38,V38,AA38) -> 0 | X38: =IF(ISBLANK($B38),0,VLOOKUP($B38,$B$322:$C$343,2,FALSE)) -> 0 | Y38: =IF(AA38-V38<=0,0,AA38-V38) -> 0 | AA38: =G38-J38 -> 0 | AC38: =IF(AD38=3,AC37+1,AC37) -> 0 | AD38: =SUM(AE38:AG38) -> 0 | AE38: =IF(ISBLANK(H38),0,1) -> 0 | AF38: =IF(ISBLANK(I38),0,1) -> 0 | AG38: =IF(ISBLANK(J38),0,1) -> 0 | AH38: =G38-J38 -> 0 | AI38: =IF(ISBLANK(E38),9999999,E38) -> 9999999 | AJ38: =F38 -> 0 | AK38: =G38 -> 0 | AM38: =IF(ISBLANK(H38),0,1) -> 0 | AN38: =IF(ISBLANK(I38),0,1) -> 0 | AO38: =IF(ISBLANK(J38),0,1) -> 0 | AP38: =SUM(AM38:AO38) -> 0 | AQ38: =IF(B38="",0,COUNT(F38:G38)) -> 0 | AR38: =IF(J38>G38,1,IF(I38>E38,1,IF(H38>F38,1,0))) -> 0 | BA38: =IF(ISERROR(BB38),2001,2009) -> 2001 | BB38: =VLOOKUP(B38,$B$340:$C$343,2,FALSE) -> #N/A
B70: MTCA - Malta | E70: =ver -> TA2_e-CO_2025_Ver 1.1 | N70: TRA 05_1
B71: Plant and Machinery - Assets acquired and first used after Y/A 2001 [Include fully depreciated assets that are disposed of during the year] | D71: Year of Purchase [Y/A] | E71: Assets at Cost b/fwd | F71: WDV b/fwd | G71: Additions at Cost | I71: Disposals at Cost | J71: Disposals at W.D.V. | K71: =IF($Z$1=1,$BA$1,$BA$2) | L71: Assets at cost c/fwd | M71: Annual W & T | N71: WDV c/fwd
G72: New | H72: Used
W73: cost c/f | Z73: W&t | AH73: =AC38
A74: =IF(AH74=AH73,0,AH74) | C74: MTA | F74: 0 | J74: =IF(I74="",0,IF($D74=$Q$1,0,AC74)) | L74: =IF(T74=0,0,IF(W74<0,0,W74)) | M74: =IF(T74=0,0,Z74) | N74: =IF(T74=0,0,IF(AA74>=0,AA74,0)) | P74: =IF(B74="","",IF(C74="",$AA$1,IF(D74="",$AE$1,IF(AND(D74<>$Q$1,E74=""),$AB$1,IF(AND(D74<>$Q$1,F74=""),$AC$1,IF(AND(D74=$Q$1,G74+H74=0),$AB$1,IF(I74="","",IF(AK74=0,$AB$1,"")))))))) | S74: =IF(P74="",0,1) | T74: =IF(ISERROR(V74),4,V74) | U74: =IF($Z$1=1,K74,IF(ISBLANK(K74),T74,IF(K74=0,0,IF(K74>T74,K74,T74)))) | V74: =IF(ISBLANK(B74),0,VLOOKUP($B74,$B$322:$C$343,2,FALSE)) | W74: =IF(D74=$Q$1,(G74+H74),E74-I74) | X74: =IF(D74=$Q$1,W74,F74-AC74) | Y74: =IF(U74=0,0,W74/U74) | Z74: =IF(Y74<0,0,IF(Y74>X74,X74,Y74)) | AA74: =X74-Z74 | AC74: =IF(T74=0,0,IF(D74=$Q$1,0,IF(AD74<>2,0,ROUND(F74*I74/E74,0)))) | AD74: =SUM(AE74:AF74) | AE74: =IF(ISBLANK(F74),0,1) | AF74: =IF(ISBLANK(E74),0,1) | AH74: =IF(I74>0,AH73+1,AH73) | AI74: =E74 | AJ74: =F74 -> 0 | AK74: =IF($D74=$Q$1,0,E74)
A75: =IF(AH75=AH74,0,AH75) -> 0 | C75: MTA | F75: 0 | J75: =IF(I75="",0,IF($D75=$Q$1,0,AC75)) | L75: =IF(T75=0,0,IF(W75<0,0,W75)) | M75: =IF(T75=0,0,Z75) | N75: =IF(T75=0,0,IF(AA75>=0,AA75,0)) | P75: =IF(B75="","",IF(C75="",$AA$1,IF(D75="",$AE$1,IF(AND(D75<>$Q$1,E75=""),$AB$1,IF(AND(D75<>$Q$1,F75=""),$AC$1,IF(AND(D75=$Q$1,G75+H75=0),$AB$1,IF(I75="","",IF(AK75=0,$AB$1,"")))))))) | S75: =IF(P75="",0,1) | T75: =IF(ISERROR(V75),4,V75) | U75: =IF($Z$1=1,K75,IF(ISBLANK(K75),T75,IF(K75=0,0,IF(K75>T75,K75,T75)))) | V75: =IF(ISBLANK(B75),0,VLOOKUP($B75,$B$322:$C$343,2,FALSE)) -> 4 | W75: =IF(D75=$Q$1,(G75+H75),E75-I75) | X75: =IF(D75=$Q$1,W75,F75-AC75) | Y75: =IF(U75=0,0,W75/U75) | Z75: =IF(Y75<0,0,IF(Y75>X75,X75,Y75)) | AA75: =X75-Z75 | AC75: =IF(T75=0,0,IF(D75=$Q$1,0,IF(AD75<>2,0,ROUND(F75*I75/E75,0)))) | AD75: =SUM(AE75:AF75) | AE75: =IF(ISBLANK(F75),0,1) | AF75: =IF(ISBLANK(E75),0,1) | AH75: =IF(I75>0,AH74+1,AH74) | AI75: =E75 -> 35622 | AJ75: =F75 -> 0 | AK75: =IF($D75=$Q$1,0,E75)
A76: =IF(AH76=AH75,0,AH76) -> 0 | C76: MTA | F76: 0 | J76: =IF(I76="",0,IF($D76=$Q$1,0,AC76)) | L76: =IF(T76=0,0,IF(W76<0,0,W76)) | M76: =IF(T76=0,0,Z76) | N76: =IF(T76=0,0,IF(AA76>=0,AA76,0)) | P76: =IF(B76="","",IF(C76="",$AA$1,IF(D76="",$AE$1,IF(AND(D76<>$Q$1,E76=""),$AB$1,IF(AND(D76<>$Q$1,F76=""),$AC$1,IF(AND(D76=$Q$1,G76+H76=0),$AB$1,IF(I76="","",IF(AK76=0,$AB$1,"")))))))) | S76: =IF(P76="",0,1) | T76: =IF(ISERROR(V76),4,V76) | U76: =IF($Z$1=1,K76,IF(ISBLANK(K76),T76,IF(K76=0,0,IF(K76>T76,K76,T76)))) | V76: =IF(ISBLANK(B76),0,VLOOKUP($B76,$B$322:$C$343,2,FALSE)) -> 4 | W76: =IF(D76=$Q$1,(G76+H76),E76-I76) | X76: =IF(D76=$Q$1,W76,F76-AC76) | Y76: =IF(U76=0,0,W76/U76) | Z76: =IF(Y76<0,0,IF(Y76>X76,X76,Y76)) | AA76: =X76-Z76 | AC76: =IF(T76=0,0,IF(D76=$Q$1,0,IF(AD76<>2,0,ROUND(F76*I76/E76,0)))) | AD76: =SUM(AE76:AF76) | AE76: =IF(ISBLANK(F76),0,1) | AF76: =IF(ISBLANK(E76),0,1) | AH76: =IF(I76>0,AH75+1,AH75) | AI76: =E76 -> 686 | AJ76: =F76 -> 0 | AK76: =IF($D76=$Q$1,0,E76)
A77: =IF(AH77=AH76,0,AH77) -> 0 | C77: MTA | J77: =IF(I77="",0,IF($D77=$Q$1,0,AC77)) | L77: =IF(T77=0,0,IF(W77<0,0,W77)) | M77: =IF(T77=0,0,Z77) | N77: =IF(T77=0,0,IF(AA77>=0,AA77,0)) | P77: =IF(B77="","",IF(C77="",$AA$1,IF(D77="",$AE$1,IF(AND(D77<>$Q$1,E77=""),$AB$1,IF(AND(D77<>$Q$1,F77=""),$AC$1,IF(AND(D77=$Q$1,G77+H77=0),$AB$1,IF(I77="","",IF(AK77=0,$AB$1,"")))))))) | S77: =IF(P77="",0,1) | T77: =IF(ISERROR(V77),4,V77) | U77: =IF($Z$1=1,K77,IF(ISBLANK(K77),T77,IF(K77=0,0,IF(K77>T77,K77,T77)))) | V77: =IF(ISBLANK(B77),0,VLOOKUP($B77,$B$322:$C$343,2,FALSE)) -> 10 | W77: =IF(D77=$Q$1,(G77+H77),E77-I77) | X77: =IF(D77=$Q$1,W77,F77-AC77) | Y77: =IF(U77=0,0,W77/U77) | Z77: =IF(Y77<0,0,IF(Y77>X77,X77,Y77)) | AA77: =X77-Z77 | AC77: =IF(T77=0,0,IF(D77=$Q$1,0,IF(AD77<>2,0,ROUND(F77*I77/E77,0)))) | AD77: =SUM(AE77:AF77) | AE77: =IF(ISBLANK(F77),0,1) | AF77: =IF(ISBLANK(E77),0,1) | AH77: =IF(I77>0,AH76+1,AH76) | AI77: =E77 -> 393 | AJ77: =F77 -> 198 | AK77: =IF($D77=$Q$1,0,E77)
A78: =IF(AH78=AH77,0,AH78) -> 0 | C78: MTA | J78: =IF(I78="",0,IF($D78=$Q$1,0,AC78)) | L78: =IF(T78=0,0,IF(W78<0,0,W78)) | M78: =IF(T78=0,0,Z78) | N78: =IF(T78=0,0,IF(AA78>=0,AA78,0)) | P78: =IF(B78="","",IF(C78="",$AA$1,IF(D78="",$AE$1,IF(AND(D78<>$Q$1,E78=""),$AB$1,IF(AND(D78<>$Q$1,F78=""),$AC$1,IF(AND(D78=$Q$1,G78+H78=0),$AB$1,IF(I78="","",IF(AK78=0,$AB$1,"")))))))) | S78: =IF(P78="",0,1) | T78: =IF(ISERROR(V78),4,V78) | U78: =IF($Z$1=1,K78,IF(ISBLANK(K78),T78,IF(K78=0,0,IF(K78>T78,K78,T78)))) | V78: =IF(ISBLANK(B78),0,VLOOKUP($B78,$B$322:$C$343,2,FALSE)) -> 4 | W78: =IF(D78=$Q$1,(G78+H78),E78-I78) | X78: =IF(D78=$Q$1,W78,F78-AC78) | Y78: =IF(U78=0,0,W78/U78) | Z78: =IF(Y78<0,0,IF(Y78>X78,X78,Y78)) | AA78: =X78-Z78 | AC78: =IF(T78=0,0,IF(D78=$Q$1,0,IF(AD78<>2,0,ROUND(F78*I78/E78,0)))) | AD78: =SUM(AE78:AF78) | AE78: =IF(ISBLANK(F78),0,1) | AF78: =IF(ISBLANK(E78),0,1) | AH78: =IF(I78>0,AH77+1,AH77) | AI78: =E78 | AJ78: =F78 | AK78: =IF($D78=$Q$1,0,E78)
A79: =IF(AH79=AH78,0,AH79) -> 0 | C79: MTA | J79: =IF(I79="",0,IF($D79=$Q$1,0,AC79)) -> 0 | L79: =IF(T79=0,0,IF(W79<0,0,W79)) -> 1418 | M79: =IF(T79=0,0,Z79) -> 2 | N79: =IF(T79=0,0,IF(AA79>=0,AA79,0)) -> 0 | P79: =IF(B79="","",IF(C79="",$AA$1,IF(D79="",$AE$1,IF(AND(D79<>$Q$1,E79=""),$AB$1,IF(AND(D79<>$Q$1,F79=""),$AC$1,IF(AND(D79=$Q$1,G79+H79=0),$AB$1,IF(I79="","",IF(AK79=0,$AB$1,"")))))))) | S79: =IF(P79="",0,1) -> 0 | T79: =IF(ISERROR(V79),4,V79) -> 4 | U79: =IF($Z$1=1,K79,IF(ISBLANK(K79),T79,IF(K79=0,0,IF(K79>T79,K79,T79)))) -> 4 | V79: =IF(ISBLANK(B79),0,VLOOKUP($B79,$B$322:$C$343,2,FALSE)) -> 4 | W79: =IF(D79=$Q$1,(G79+H79),E79-I79) -> 1418 | X79: =IF(D79=$Q$1,W79,F79-AC79) -> 2 | Y79: =IF(U79=0,0,W79/U79) -> 354.5 | Z79: =IF(Y79<0,0,IF(Y79>X79,X79,Y79)) -> 2 | AA79: =X79-Z79 -> 0 | AC79: =IF(T79=0,0,IF(D79=$Q$1,0,IF(AD79<>2,0,ROUND(F79*I79/E79,0)))) -> 0 | AD79: =SUM(AE79:AF79) -> 2 | AE79: =IF(ISBLANK(F79),0,1) -> 1 | AF79: =IF(ISBLANK(E79),0,1) -> 1 | AH79: =IF(I79>0,AH78+1,AH78) -> 0 | AI79: =E79 -> 1418 | AJ79: =F79 -> 2 | AK79: =IF($D79=$Q$1,0,E79) -> 1418
A80: =IF(AH80=AH79,0,AH80) -> 0 | C80: MTA | D80: 2022 | J80: =IF(I80="",0,IF($D80=$Q$1,0,AC80)) -> 0 | L80: =IF(T80=0,0,IF(W80<0,0,W80)) -> 1202 | M80: =IF(T80=0,0,Z80) -> 300.5 | N80: =IF(T80=0,0,IF(AA80>=0,AA80,0)) -> 1.5 | P80: =IF(B80="","",IF(C80="",$AA$1,IF(D80="",$AE$1,IF(AND(D80<>$Q$1,E80=""),$AB$1,IF(AND(D80<>$Q$1,F80=""),$AC$1,IF(AND(D80=$Q$1,G80+H80=0),$AB$1,IF(I80="","",IF(AK80=0,$AB$1,"")))))))) | S80: =IF(P80="",0,1) -> 0 | T80: =IF(ISERROR(V80),4,V80) -> 4 | U80: =IF($Z$1=1,K80,IF(ISBLANK(K80),T80,IF(K80=0,0,IF(K80>T80,K80,T80)))) -> 4 | V80: =IF(ISBLANK(B80),0,VLOOKUP($B80,$B$322:$C$343,2,FALSE)) -> 4 | W80: =IF(D80=$Q$1,(G80+H80),E80-I80) -> 1202 | X80: =IF(D80=$Q$1,W80,F80-AC80) -> 302 | Y80: =IF(U80=0,0,W80/U80) -> 300.5 | Z80: =IF(Y80<0,0,IF(Y80>X80,X80,Y80)) -> 300.5 | AA80: =X80-Z80 -> 1.5 | AC80: =IF(T80=0,0,IF(D80=$Q$1,0,IF(AD80<>2,0,ROUND(F80*I80/E80,0)))) -> 0 | AD80: =SUM(AE80:AF80) -> 2 | AE80: =IF(ISBLANK(F80),0,1) -> 1 | AF80: =IF(ISBLANK(E80),0,1) -> 1 | AH80: =IF(I80>0,AH79+1,AH79) -> 0 | AI80: =E80 -> 1202 | AJ80: =F80 -> 302 | AK80: =IF($D80=$Q$1,0,E80) -> 1202
A81: =IF(AH81=AH80,0,AH81) -> 0 | C81: MTA | J81: =IF(I81="",0,IF($D81=$Q$1,0,AC81)) -> 0 | L81: =IF(T81=0,0,IF(W81<0,0,W81)) -> 1045 | M81: =IF(T81=0,0,Z81) -> 261.25 | N81: =IF(T81=0,0,IF(AA81>=0,AA81,0)) -> 261.75 | P81: =IF(B81="","",IF(C81="",$AA$1,IF(D81="",$AE$1,IF(AND(D81<>$Q$1,E81=""),$AB$1,IF(AND(D81<>$Q$1,F81=""),$AC$1,IF(AND(D81=$Q$1,G81+H81=0),$AB$1,IF(I81="","",IF(AK81=0,$AB$1,"")))))))) | S81: =IF(P81="",0,1) -> 0 | T81: =IF(ISERROR(V81),4,V81) -> 4 | U81: =IF($Z$1=1,K81,IF(ISBLANK(K81),T81,IF(K81=0,0,IF(K81>T81,K81,T81)))) -> 4 | V81: =IF(ISBLANK(B81),0,VLOOKUP($B81,$B$322:$C$343,2,FALSE)) -> 4 | W81: =IF(D81=$Q$1,(G81+H81),E81-I81) -> 1045 | X81: =IF(D81=$Q$1,W81,F81-AC81) -> 523 | Y81: =IF(U81=0,0,W81/U81) -> 261.25 | Z81: =IF(Y81<0,0,IF(Y81>X81,X81,Y81)) -> 261.25 | AA81: =X81-Z81 -> 261.75 | AC81: =IF(T81=0,0,IF(D81=$Q$1,0,IF(AD81<>2,0,ROUND(F81*I81/E81,0)))) -> 0 | AD81: =SUM(AE81:AF81) -> 2 | AE81: =IF(ISBLANK(F81),0,1) -> 1 | AF81: =IF(ISBLANK(E81),0,1) -> 1 | AH81: =IF(I81>0,AH80+1,AH80) -> 0 | AI81: =E81 -> 1045 | AJ81: =F81 -> 523 | AK81: =IF($D81=$Q$1,0,E81) -> 1045
A82: =IF(AH82=AH81,0,AH82) -> 0 | C82: MTA | D82: 2023 | J82: =IF(I82="",0,IF($D82=$Q$1,0,AC82)) -> 0 | L82: =IF(T82=0,0,IF(W82<0,0,W82)) -> 25738 | M82: =IF(T82=0,0,Z82) -> 6434.5 | N82: =IF(T82=0,0,IF(AA82>=0,AA82,0)) -> 6435.5 | P82: =IF(B82="","",IF(C82="",$AA$1,IF(D82="",$AE$1,IF(AND(D82<>$Q$1,E82=""),$AB$1,IF(AND(D82<>$Q$1,F82=""),$AC$1,IF(AND(D82=$Q$1,G82+H82=0),$AB$1,IF(I82="","",IF(AK82=0,$AB$1,"")))))))) | S82: =IF(P82="",0,1) -> 0 | T82: =IF(ISERROR(V82),4,V82) -> 4 | U82: =IF($Z$1=1,K82,IF(ISBLANK(K82),T82,IF(K82=0,0,IF(K82>T82,K82,T82)))) -> 4 | V82: =IF(ISBLANK(B82),0,VLOOKUP($B82,$B$322:$C$343,2,FALSE)) -> 4 | W82: =IF(D82=$Q$1,(G82+H82),E82-I82) -> 25738 | X82: =IF(D82=$Q$1,W82,F82-AC82) -> 12870 | Y82: =IF(U82=0,0,W82/U82) -> 6434.5 | Z82: =IF(Y82<0,0,IF(Y82>X82,X82,Y82)) -> 6434.5 | AA82: =X82-Z82 -> 6435.5 | AC82: =IF(T82=0,0,IF(D82=$Q$1,0,IF(AD82<>2,0,ROUND(F82*I82/E82,0)))) -> 0 | AD82: =SUM(AE82:AF82) -> 2 | AE82: =IF(ISBLANK(F82),0,1) -> 1 | AF82: =IF(ISBLANK(E82),0,1) -> 1 | AH82: =IF(I82>0,AH81+1,AH81) -> 0 | AI82: =E82 -> 25738 | AJ82: =F82 -> 12870 | AK82: =IF($D82=$Q$1,0,E82) -> 25738
A83: =IF(AH83=AH82,0,AH83) -> 0 | C83: MTA | J83: =IF(I83="",0,IF($D83=$Q$1,0,AC83)) -> 0 | L83: =IF(T83=0,0,IF(W83<0,0,W83)) -> 709 | M83: =IF(T83=0,0,Z83) -> 70.9 | N83: =IF(T83=0,0,IF(AA83>=0,AA83,0)) -> 496.1 | P83: =IF(B83="","",IF(C83="",$AA$1,IF(D83="",$AE$1,IF(AND(D83<>$Q$1,E83=""),$AB$1,IF(AND(D83<>$Q$1,F83=""),$AC$1,IF(AND(D83=$Q$1,G83+H83=0),$AB$1,IF(I83="","",IF(AK83=0,$AB$1,"")))))))) | S83: =IF(P83="",0,1) -> 0 | T83: =IF(ISERROR(V83),4,V83) -> 10 | U83: =IF($Z$1=1,K83,IF(ISBLANK(K83),T83,IF(K83=0,0,IF(K83>T83,K83,T83)))) -> 10 | V83: =IF(ISBLANK(B83),0,VLOOKUP($B83,$B$322:$C$343,2,FALSE)) -> 10 | W83: =IF(D83=$Q$1,(G83+H83),E83-I83) -> 709 | X83: =IF(D83=$Q$1,W83,F83-AC83) -> 567 | Y83: =IF(U83=0,0,W83/U83) -> 70.9 | Z83: =IF(Y83<0,0,IF(Y83>X83,X83,Y83)) -> 70.9 | AA83: =X83-Z83 -> 496.1 | AC83: =IF(T83=0,0,IF(D83=$Q$1,0,IF(AD83<>2,0,ROUND(F83*I83/E83,0)))) -> 0 | AD83: =SUM(AE83:AF83) -> 2 | AE83: =IF(ISBLANK(F83),0,1) -> 1 | AF83: =IF(ISBLANK(E83),0,1) -> 1 | AH83: =IF(I83>0,AH82+1,AH82) -> 0 | AI83: =E83 -> 709 | AJ83: =F83 -> 567 | AK83: =IF($D83=$Q$1,0,E83) -> 709
A84: =IF(AH84=AH83,0,AH84) -> 0 | C84: MTA | J84: =IF(I84="",0,IF($D84=$Q$1,0,AC84)) -> 0 | L84: =IF(T84=0,0,IF(W84<0,0,W84)) -> 2608 | M84: =IF(T84=0,0,Z84) -> 652 | N84: =IF(T84=0,0,IF(AA84>=0,AA84,0)) -> 1304 | P84: =IF(B84="","",IF(C84="",$AA$1,IF(D84="",$AE$1,IF(AND(D84<>$Q$1,E84=""),$AB$1,IF(AND(D84<>$Q$1,F84=""),$AC$1,IF(AND(D84=$Q$1,G84+H84=0),$AB$1,IF(I84="","",IF(AK84=0,$AB$1,"")))))))) | S84: =IF(P84="",0,1) -> 0 | T84: =IF(ISERROR(V84),4,V84) -> 4 | U84: =IF($Z$1=1,K84,IF(ISBLANK(K84),T84,IF(K84=0,0,IF(K84>T84,K84,T84)))) -> 4 | V84: =IF(ISBLANK(B84),0,VLOOKUP($B84,$B$322:$C$343,2,FALSE)) -> 4 | W84: =IF(D84=$Q$1,(G84+H84),E84-I84) -> 2608 | X84: =IF(D84=$Q$1,W84,F84-AC84) -> 1956 | Y84: =IF(U84=0,0,W84/U84) -> 652 | Z84: =IF(Y84<0,0,IF(Y84>X84,X84,Y84)) -> 652 | AA84: =X84-Z84 -> 1304 | AC84: =IF(T84=0,0,IF(D84=$Q$1,0,IF(AD84<>2,0,ROUND(F84*I84/E84,0)))) -> 0 | AD84: =SUM(AE84:AF84) -> 2 | AE84: =IF(ISBLANK(F84),0,1) -> 1 | AF84: =IF(ISBLANK(E84),0,1) -> 1 | AH84: =IF(I84>0,AH83+1,AH83) -> 0 | AI84: =E84 -> 2608 | AJ84: =F84 -> 1956 | AK84: =IF($D84=$Q$1,0,E84) -> 2608
A85: =IF(AH85=AH84,0,AH85) -> 0 | C85: MTA | J85: =IF(I85="",0,IF($D85=$Q$1,0,AC85)) -> 0 | L85: =IF(T85=0,0,IF(W85<0,0,W85)) -> 36490 | M85: =IF(T85=0,0,Z85) -> 9122.5 | N85: =IF(T85=0,0,IF(AA85>=0,AA85,0)) -> 18245.5 | P85: =IF(B85="","",IF(C85="",$AA$1,IF(D85="",$AE$1,IF(AND(D85<>$Q$1,E85=""),$AB$1,IF(AND(D85<>$Q$1,F85=""),$AC$1,IF(AND(D85=$Q$1,G85+H85=0),$AB$1,IF(I85="","",IF(AK85=0,$AB$1,"")))))))) | S85: =IF(P85="",0,1) -> 0 | T85: =IF(ISERROR(V85),4,V85) -> 4 | U85: =IF($Z$1=1,K85,IF(ISBLANK(K85),T85,IF(K85=0,0,IF(K85>T85,K85,T85)))) -> 4 | V85: =IF(ISBLANK(B85),0,VLOOKUP($B85,$B$322:$C$343,2,FALSE)) -> 4 | W85: =IF(D85=$Q$1,(G85+H85),E85-I85) -> 36490 | X85: =IF(D85=$Q$1,W85,F85-AC85) -> 27368 | Y85: =IF(U85=0,0,W85/U85) -> 9122.5 | Z85: =IF(Y85<0,0,IF(Y85>X85,X85,Y85)) -> 9122.5 | AA85: =X85-Z85 -> 18245.5 | AC85: =IF(T85=0,0,IF(D85=$Q$1,0,IF(AD85<>2,0,ROUND(F85*I85/E85,0)))) -> 0 | AD85: =SUM(AE85:AF85) -> 2 | AE85: =IF(ISBLANK(F85),0,1) -> 1 | AF85: =IF(ISBLANK(E85),0,1) -> 1 | AH85: =IF(I85>0,AH84+1,AH84) -> 0 | AI85: =E85 -> 36490 | AJ85: =F85 -> 27368 | AK85: =IF($D85=$Q$1,0,E85) -> 36490
A86: =IF(AH86=AH85,0,AH86) -> 0 | C86: MTA | J86: =IF(I86="",0,IF($D86=$Q$1,0,AC86)) -> 0 | L86: =IF(T86=0,0,IF(W86<0,0,W86)) -> 2034 | M86: =IF(T86=0,0,Z86) -> 508.5 | N86: =IF(T86=0,0,IF(AA86>=0,AA86,0)) -> 1525.5 | P86: =IF(B86="","",IF(C86="",$AA$1,IF(D86="",$AE$1,IF(AND(D86<>$Q$1,E86=""),$AB$1,IF(AND(D86<>$Q$1,F86=""),$AC$1,IF(AND(D86=$Q$1,G86+H86=0),$AB$1,IF(I86="","",IF(AK86=0,$AB$1,"")))))))) | S86: =IF(P86="",0,1) -> 0 | T86: =IF(ISERROR(V86),4,V86) -> 4 | U86: =IF($Z$1=1,K86,IF(ISBLANK(K86),T86,IF(K86=0,0,IF(K86>T86,K86,T86)))) -> 4 | V86: =IF(ISBLANK(B86),0,VLOOKUP($B86,$B$322:$C$343,2,FALSE)) -> 4 | W86: =IF(D86=$Q$1,(G86+H86),E86-I86) -> 2034 | X86: =IF(D86=$Q$1,W86,F86-AC86) -> 2034 | Y86: =IF(U86=0,0,W86/U86) -> 508.5 | Z86: =IF(Y86<0,0,IF(Y86>X86,X86,Y86)) -> 508.5 | AA86: =X86-Z86 -> 1525.5 | AC86: =IF(T86=0,0,IF(D86=$Q$1,0,IF(AD86<>2,0,ROUND(F86*I86/E86,0)))) -> 0 | AD86: =SUM(AE86:AF86) -> 0 | AE86: =IF(ISBLANK(F86),0,1) -> 0 | AF86: =IF(ISBLANK(E86),0,1) -> 0 | AH86: =IF(I86>0,AH85+1,AH85) -> 0 | AI86: =E86 -> 0 | AJ86: =F86 -> 0 | AK86: =IF($D86=$Q$1,0,E86) -> 0
A87: =IF(AH87=AH86,0,AH87) -> 0 | C87: MTA | G87: =82430+86540 | J87: =IF(I87="",0,IF($D87=$Q$1,0,AC87)) -> 0 | L87: =IF(T87=0,0,IF(W87<0,0,W87)) -> 168970 | M87: =IF(T87=0,0,Z87) -> 42242.5 | N87: =IF(T87=0,0,IF(AA87>=0,AA87,0)) -> 126727.5 | P87: =IF(B87="","",IF(C87="",$AA$1,IF(D87="",$AE$1,IF(AND(D87<>$Q$1,E87=""),$AB$1,IF(AND(D87<>$Q$1,F87=""),$AC$1,IF(AND(D87=$Q$1,G87+H87=0),$AB$1,IF(I87="","",IF(AK87=0,$AB$1,"")))))))) | S87: =IF(P87="",0,1) -> 0 | T87: =IF(ISERROR(V87),4,V87) -> 4 | U87: =IF($Z$1=1,K87,IF(ISBLANK(K87),T87,IF(K87=0,0,IF(K87>T87,K87,T87)))) -> 4 | V87: =IF(ISBLANK(B87),0,VLOOKUP($B87,$B$322:$C$343,2,FALSE)) -> 4 | W87: =IF(D87=$Q$1,(G87+H87),E87-I87) -> 168970 | X87: =IF(D87=$Q$1,W87,F87-AC87) -> 168970 | Y87: =IF(U87=0,0,W87/U87) -> 42242.5 | Z87: =IF(Y87<0,0,IF(Y87>X87,X87,Y87)) -> 42242.5 | AA87: =X87-Z87 -> 126727.5 | AC87: =IF(T87=0,0,IF(D87=$Q$1,0,IF(AD87<>2,0,ROUND(F87*I87/E87,0)))) -> 0 | AD87: =SUM(AE87:AF87) -> 0 | AE87: =IF(ISBLANK(F87),0,1) -> 0 | AF87: =IF(ISBLANK(E87),0,1) -> 0 | AH87: =IF(I87>0,AH86+1,AH86) -> 0 | AI87: =E87 -> 0 | AJ87: =F87 -> 0 | AK87: =IF($D87=$Q$1,0,E87) -> 0
A88: =IF(AH88=AH87,0,AH88) -> 0 | C88: MTA | J88: =IF(I88="",0,IF($D88=$Q$1,0,AC88)) -> 0 | L88: =IF(T88=0,0,IF(W88<0,0,W88)) -> 0 | M88: =IF(T88=0,0,Z88) -> 0 | N88: =IF(T88=0,0,IF(AA88>=0,AA88,0)) -> 0 | P88: =IF(B88="","",IF(C88="",$AA$1,IF(D88="",$AE$1,IF(AND(D88<>$Q$1,E88=""),$AB$1,IF(AND(D88<>$Q$1,F88=""),$AC$1,IF(AND(D88=$Q$1,G88+H88=0),$AB$1,IF(I88="","",IF(AK88=0,$AB$1,"")))))))) | S88: =IF(P88="",0,1) -> 0 | T88: =IF(ISERROR(V88),4,V88) -> 0 | U88: =IF($Z$1=1,K88,IF(ISBLANK(K88),T88,IF(K88=0,0,IF(K88>T88,K88,T88)))) -> 0 | V88: =IF(ISBLANK(B88),0,VLOOKUP($B88,$B$322:$C$343,2,FALSE)) -> 0 | W88: =IF(D88=$Q$1,(G88+H88),E88-I88) -> 0 | X88: =IF(D88=$Q$1,W88,F88-AC88) -> 0 | Y88: =IF(U88=0,0,W88/U88) -> 0 | Z88: =IF(Y88<0,0,IF(Y88>X88,X88,Y88)) -> 0 | AA88: =X88-Z88 -> 0 | AC88: =IF(T88=0,0,IF(D88=$Q$1,0,IF(AD88<>2,0,ROUND(F88*I88/E88,0)))) -> 0 | AD88: =SUM(AE88:AF88) -> 0 | AE88: =IF(ISBLANK(F88),0,1) -> 0 | AF88: =IF(ISBLANK(E88),0,1) -> 0 | AH88: =IF(I88>0,AH87+1,AH87) -> 0 | AI88: =E88 -> 0 | AJ88: =F88 -> 0 | AK88: =IF($D88=$Q$1,0,E88) -> 0
A89: =IF(AH89=AH88,0,AH89) -> 0 | C89: MTA | J89: =IF(I89="",0,IF($D89=$Q$1,0,AC89)) -> 0 | L89: =IF(T89=0,0,IF(W89<0,0,W89)) -> 0 | M89: =IF(T89=0,0,Z89) -> 0 | N89: =IF(T89=0,0,IF(AA89>=0,AA89,0)) -> 0 | P89: =IF(B89="","",IF(C89="",$AA$1,IF(D89="",$AE$1,IF(AND(D89<>$Q$1,E89=""),$AB$1,IF(AND(D89<>$Q$1,F89=""),$AC$1,IF(AND(D89=$Q$1,G89+H89=0),$AB$1,IF(I89="","",IF(AK89=0,$AB$1,"")))))))) | S89: =IF(P89="",0,1) -> 0 | T89: =IF(ISERROR(V89),4,V89) -> 0 | U89: =IF($Z$1=1,K89,IF(ISBLANK(K89),T89,IF(K89=0,0,IF(K89>T89,K89,T89)))) -> 0 | V89: =IF(ISBLANK(B89),0,VLOOKUP($B89,$B$322:$C$343,2,FALSE)) -> 0 | W89: =IF(D89=$Q$1,(G89+H89),E89-I89) -> 0 | X89: =IF(D89=$Q$1,W89,F89-AC89) -> 0 | Y89: =IF(U89=0,0,W89/U89) -> 0 | Z89: =IF(Y89<0,0,IF(Y89>X89,X89,Y89)) -> 0 | AA89: =X89-Z89 -> 0 | AC89: =IF(T89=0,0,IF(D89=$Q$1,0,IF(AD89<>2,0,ROUND(F89*I89/E89,0)))) -> 0 | AD89: =SUM(AE89:AF89) -> 0 | AE89: =IF(ISBLANK(F89),0,1) -> 0 | AF89: =IF(ISBLANK(E89),0,1) -> 0 | AH89: =IF(I89>0,AH88+1,AH88) -> 0 | AI89: =E89 -> 0 | AJ89: =F89 -> 0 | AK89: =IF($D89=$Q$1,0,E89) -> 0
A90: =IF(AH90=AH89,0,AH90) -> 0 | C90: MTA | J90: =IF(I90="",0,IF($D90=$Q$1,0,AC90)) -> 0 | L90: =IF(T90=0,0,IF(W90<0,0,W90)) -> 0 | M90: =IF(T90=0,0,Z90) -> 0 | N90: =IF(T90=0,0,IF(AA90>=0,AA90,0)) -> 0 | P90: =IF(B90="","",IF(C90="",$AA$1,IF(D90="",$AE$1,IF(AND(D90<>$Q$1,E90=""),$AB$1,IF(AND(D90<>$Q$1,F90=""),$AC$1,IF(AND(D90=$Q$1,G90+H90=0),$AB$1,IF(I90="","",IF(AK90=0,$AB$1,"")))))))) | S90: =IF(P90="",0,1) -> 0 | T90: =IF(ISERROR(V90),4,V90) -> 0 | U90: =IF($Z$1=1,K90,IF(ISBLANK(K90),T90,IF(K90=0,0,IF(K90>T90,K90,T90)))) -> 0 | V90: =IF(ISBLANK(B90),0,VLOOKUP($B90,$B$322:$C$343,2,FALSE)) -> 0 | W90: =IF(D90=$Q$1,(G90+H90),E90-I90) -> 0 | X90: =IF(D90=$Q$1,W90,F90-AC90) -> 0 | Y90: =IF(U90=0,0,W90/U90) -> 0 | Z90: =IF(Y90<0,0,IF(Y90>X90,X90,Y90)) -> 0 | AA90: =X90-Z90 -> 0 | AC90: =IF(T90=0,0,IF(D90=$Q$1,0,IF(AD90<>2,0,ROUND(F90*I90/E90,0)))) -> 0 | AD90: =SUM(AE90:AF90) -> 0 | AE90: =IF(ISBLANK(F90),0,1) -> 0 | AF90: =IF(ISBLANK(E90),0,1) -> 0 | AH90: =IF(I90>0,AH89+1,AH89) -> 0 | AI90: =E90 -> 0 | AJ90: =F90 -> 0 | AK90: =IF($D90=$Q$1,0,E90) -> 0
A91: =IF(AH91=AH90,0,AH91) -> 0 | C91: MTA | J91: =IF(I91="",0,IF($D91=$Q$1,0,AC91)) -> 0 | L91: =IF(T91=0,0,IF(W91<0,0,W91)) -> 0 | M91: =IF(T91=0,0,Z91) -> 0 | N91: =IF(T91=0,0,IF(AA91>=0,AA91,0)) -> 0 | P91: =IF(B91="","",IF(C91="",$AA$1,IF(D91="",$AE$1,IF(AND(D91<>$Q$1,E91=""),$AB$1,IF(AND(D91<>$Q$1,F91=""),$AC$1,IF(AND(D91=$Q$1,G91+H91=0),$AB$1,IF(I91="","",IF(AK91=0,$AB$1,"")))))))) | S91: =IF(P91="",0,1) -> 0 | T91: =IF(ISERROR(V91),4,V91) -> 0 | U91: =IF($Z$1=1,K91,IF(ISBLANK(K91),T91,IF(K91=0,0,IF(K91>T91,K91,T91)))) -> 0 | V91: =IF(ISBLANK(B91),0,VLOOKUP($B91,$B$322:$C$343,2,FALSE)) -> 0 | W91: =IF(D91=$Q$1,(G91+H91),E91-I91) -> 0 | X91: =IF(D91=$Q$1,W91,F91-AC91) -> 0 | Y91: =IF(U91=0,0,W91/U91) -> 0 | Z91: =IF(Y91<0,0,IF(Y91>X91,X91,Y91)) -> 0 | AA91: =X91-Z91 -> 0 | AC91: =IF(T91=0,0,IF(D91=$Q$1,0,IF(AD91<>2,0,ROUND(F91*I91/E91,0)))) -> 0 | AD91: =SUM(AE91:AF91) -> 0 | AE91: =IF(ISBLANK(F91),0,1) -> 0 | AF91: =IF(ISBLANK(E91),0,1) -> 0 | AH91: =IF(I91>0,AH90+1,AH90) -> 0 | AI91: =E91 -> 0 | AJ91: =F91 -> 0 | AK91: =IF($D91=$Q$1,0,E91) -> 0
A92: =IF(AH92=AH91,0,AH92) -> 0 | C92: MTA | J92: =IF(I92="",0,IF($D92=$Q$1,0,AC92)) -> 0 | L92: =IF(T92=0,0,IF(W92<0,0,W92)) -> 0 | M92: =IF(T92=0,0,Z92) -> 0 | N92: =IF(T92=0,0,IF(AA92>=0,AA92,0)) -> 0 | P92: =IF(B92="","",IF(C92="",$AA$1,IF(D92="",$AE$1,IF(AND(D92<>$Q$1,E92=""),$AB$1,IF(AND(D92<>$Q$1,F92=""),$AC$1,IF(AND(D92=$Q$1,G92+H92=0),$AB$1,IF(I92="","",IF(AK92=0,$AB$1,"")))))))) | S92: =IF(P92="",0,1) -> 0 | T92: =IF(ISERROR(V92),4,V92) -> 0 | U92: =IF($Z$1=1,K92,IF(ISBLANK(K92),T92,IF(K92=0,0,IF(K92>T92,K92,T92)))) -> 0 | V92: =IF(ISBLANK(B92),0,VLOOKUP($B92,$B$322:$C$343,2,FALSE)) -> 0 | W92: =IF(D92=$Q$1,(G92+H92),E92-I92) -> 0 | X92: =IF(D92=$Q$1,W92,F92-AC92) -> 0 | Y92: =IF(U92=0,0,W92/U92) -> 0 | Z92: =IF(Y92<0,0,IF(Y92>X92,X92,Y92)) -> 0 | AA92: =X92-Z92 -> 0 | AC92: =IF(T92=0,0,IF(D92=$Q$1,0,IF(AD92<>2,0,ROUND(F92*I92/E92,0)))) -> 0 | AD92: =SUM(AE92:AF92) -> 0 | AE92: =IF(ISBLANK(F92),0,1) -> 0 | AF92: =IF(ISBLANK(E92),0,1) -> 0 | AH92: =IF(I92>0,AH91+1,AH91) -> 0 | AI92: =E92 -> 0 | AJ92: =F92 -> 0 | AK92: =IF($D92=$Q$1,0,E92) -> 0
A93: =IF(AH93=AH92,0,AH93) -> 0 | C93: MTA | J93: =IF(I93="",0,IF($D93=$Q$1,0,AC93)) -> 0 | L93: =IF(T93=0,0,IF(W93<0,0,W93)) -> 0 | M93: =IF(T93=0,0,Z93) -> 0 | N93: =IF(T93=0,0,IF(AA93>=0,AA93,0)) -> 0 | P93: =IF(B93="","",IF(C93="",$AA$1,IF(D93="",$AE$1,IF(AND(D93<>$Q$1,E93=""),$AB$1,IF(AND(D93<>$Q$1,F93=""),$AC$1,IF(AND(D93=$Q$1,G93+H93=0),$AB$1,IF(I93="","",IF(AK93=0,$AB$1,"")))))))) | S93: =IF(P93="",0,1) -> 0 | T93: =IF(ISERROR(V93),4,V93) -> 0 | U93: =IF($Z$1=1,K93,IF(ISBLANK(K93),T93,IF(K93=0,0,IF(K93>T93,K93,T93)))) -> 0 | V93: =IF(ISBLANK(B93),0,VLOOKUP($B93,$B$322:$C$343,2,FALSE)) -> 0 | W93: =IF(D93=$Q$1,(G93+H93),E93-I93) -> 0 | X93: =IF(D93=$Q$1,W93,F93-AC93) -> 0 | Y93: =IF(U93=0,0,W93/U93) -> 0 | Z93: =IF(Y93<0,0,IF(Y93>X93,X93,Y93)) -> 0 | AA93: =X93-Z93 -> 0 | AC93: =IF(T93=0,0,IF(D93=$Q$1,0,IF(AD93<>2,0,ROUND(F93*I93/E93,0)))) -> 0 | AD93: =SUM(AE93:AF93) -> 0 | AE93: =IF(ISBLANK(F93),0,1) -> 0 | AF93: =IF(ISBLANK(E93),0,1) -> 0 | AH93: =IF(I93>0,AH92+1,AH92) -> 0 | AI93: =E93 -> 0 | AJ93: =F93 -> 0 | AK93: =IF($D93=$Q$1,0,E93) -> 0
A94: =IF(AH94=AH93,0,AH94) -> 0 | C94: MTA | J94: =IF(I94="",0,IF($D94=$Q$1,0,AC94)) -> 0 | L94: =IF(T94=0,0,IF(W94<0,0,W94)) -> 0 | M94: =IF(T94=0,0,Z94) -> 0 | N94: =IF(T94=0,0,IF(AA94>=0,AA94,0)) -> 0 | P94: =IF(B94="","",IF(C94="",$AA$1,IF(D94="",$AE$1,IF(AND(D94<>$Q$1,E94=""),$AB$1,IF(AND(D94<>$Q$1,F94=""),$AC$1,IF(AND(D94=$Q$1,G94+H94=0),$AB$1,IF(I94="","",IF(AK94=0,$AB$1,"")))))))) | S94: =IF(P94="",0,1) -> 0 | T94: =IF(ISERROR(V94),4,V94) -> 0 | U94: =IF($Z$1=1,K94,IF(ISBLANK(K94),T94,IF(K94=0,0,IF(K94>T94,K94,T94)))) -> 0 | V94: =IF(ISBLANK(B94),0,VLOOKUP($B94,$B$322:$C$343,2,FALSE)) -> 0 | W94: =IF(D94=$Q$1,(G94+H94),E94-I94) -> 0 | X94: =IF(D94=$Q$1,W94,F94-AC94) -> 0 | Y94: =IF(U94=0,0,W94/U94) -> 0 | Z94: =IF(Y94<0,0,IF(Y94>X94,X94,Y94)) -> 0 | AA94: =X94-Z94 -> 0 | AC94: =IF(T94=0,0,IF(D94=$Q$1,0,IF(AD94<>2,0,ROUND(F94*I94/E94,0)))) -> 0 | AD94: =SUM(AE94:AF94) -> 0 | AE94: =IF(ISBLANK(F94),0,1) -> 0 | AF94: =IF(ISBLANK(E94),0,1) -> 0 | AH94: =IF(I94>0,AH93+1,AH93) -> 0 | AI94: =E94 -> 0 | AJ94: =F94 -> 0 | AK94: =IF($D94=$Q$1,0,E94) -> 0
A95: =IF(AH95=AH94,0,AH95) -> 0 | C95: MTA | J95: =IF(I95="",0,IF($D95=$Q$1,0,AC95)) -> 0 | L95: =IF(T95=0,0,IF(W95<0,0,W95)) -> 0 | M95: =IF(T95=0,0,Z95) -> 0 | N95: =IF(T95=0,0,IF(AA95>=0,AA95,0)) -> 0 | P95: =IF(B95="","",IF(C95="",$AA$1,IF(D95="",$AE$1,IF(AND(D95<>$Q$1,E95=""),$AB$1,IF(AND(D95<>$Q$1,F95=""),$AC$1,IF(AND(D95=$Q$1,G95+H95=0),$AB$1,IF(I95="","",IF(AK95=0,$AB$1,"")))))))) | S95: =IF(P95="",0,1) -> 0 | T95: =IF(ISERROR(V95),4,V95) -> 0 | U95: =IF($Z$1=1,K95,IF(ISBLANK(K95),T95,IF(K95=0,0,IF(K95>T95,K95,T95)))) -> 0 | V95: =IF(ISBLANK(B95),0,VLOOKUP($B95,$B$322:$C$343,2,FALSE)) -> 0 | W95: =IF(D95=$Q$1,(G95+H95),E95-I95) -> 0 | X95: =IF(D95=$Q$1,W95,F95-AC95) -> 0 | Y95: =IF(U95=0,0,W95/U95) -> 0 | Z95: =IF(Y95<0,0,IF(Y95>X95,X95,Y95)) -> 0 | AA95: =X95-Z95 -> 0 | AC95: =IF(T95=0,0,IF(D95=$Q$1,0,IF(AD95<>2,0,ROUND(F95*I95/E95,0)))) -> 0 | AD95: =SUM(AE95:AF95) -> 0 | AE95: =IF(ISBLANK(F95),0,1) -> 0 | AF95: =IF(ISBLANK(E95),0,1) -> 0 | AH95: =IF(I95>0,AH94+1,AH94) -> 0 | AI95: =E95 -> 0 | AJ95: =F95 -> 0 | AK95: =IF($D95=$Q$1,0,E95) -> 0
A96: =IF(AH96=AH95,0,AH96) -> 0 | C96: MTA | J96: =IF(I96="",0,IF($D96=$Q$1,0,AC96)) -> 0 | L96: =IF(T96=0,0,IF(W96<0,0,W96)) -> 0 | M96: =IF(T96=0,0,Z96) -> 0 | N96: =IF(T96=0,0,IF(AA96>=0,AA96,0)) -> 0 | P96: =IF(B96="","",IF(C96="",$AA$1,IF(D96="",$AE$1,IF(AND(D96<>$Q$1,E96=""),$AB$1,IF(AND(D96<>$Q$1,F96=""),$AC$1,IF(AND(D96=$Q$1,G96+H96=0),$AB$1,IF(I96="","",IF(AK96=0,$AB$1,"")))))))) | S96: =IF(P96="",0,1) -> 0 | T96: =IF(ISERROR(V96),4,V96) -> 0 | U96: =IF($Z$1=1,K96,IF(ISBLANK(K96),T96,IF(K96=0,0,IF(K96>T96,K96,T96)))) -> 0 | V96: =IF(ISBLANK(B96),0,VLOOKUP($B96,$B$322:$C$343,2,FALSE)) -> 0 | W96: =IF(D96=$Q$1,(G96+H96),E96-I96) -> 0 | X96: =IF(D96=$Q$1,W96,F96-AC96) -> 0 | Y96: =IF(U96=0,0,W96/U96) -> 0 | Z96: =IF(Y96<0,0,IF(Y96>X96,X96,Y96)) -> 0 | AA96: =X96-Z96 -> 0 | AC96: =IF(T96=0,0,IF(D96=$Q$1,0,IF(AD96<>2,0,ROUND(F96*I96/E96,0)))) -> 0 | AD96: =SUM(AE96:AF96) -> 0 | AE96: =IF(ISBLANK(F96),0,1) -> 0 | AF96: =IF(ISBLANK(E96),0,1) -> 0 | AH96: =IF(I96>0,AH95+1,AH95) -> 0 | AI96: =E96 -> 0 | AJ96: =F96 -> 0 | AK96: =IF($D96=$Q$1,0,E96) -> 0
A97: =IF(AH97=AH96,0,AH97) -> 0 | C97: MTA | J97: =IF(I97="",0,IF($D97=$Q$1,0,AC97)) -> 0 | L97: =IF(T97=0,0,IF(W97<0,0,W97)) -> 0 | M97: =IF(T97=0,0,Z97) -> 0 | N97: =IF(T97=0,0,IF(AA97>=0,AA97,0)) -> 0 | P97: =IF(B97="","",IF(C97="",$AA$1,IF(D97="",$AE$1,IF(AND(D97<>$Q$1,E97=""),$AB$1,IF(AND(D97<>$Q$1,F97=""),$AC$1,IF(AND(D97=$Q$1,G97+H97=0),$AB$1,IF(I97="","",IF(AK97=0,$AB$1,"")))))))) | S97: =IF(P97="",0,1) -> 0 | T97: =IF(ISERROR(V97),4,V97) -> 0 | U97: =IF($Z$1=1,K97,IF(ISBLANK(K97),T97,IF(K97=0,0,IF(K97>T97,K97,T97)))) -> 0 | V97: =IF(ISBLANK(B97),0,VLOOKUP($B97,$B$322:$C$343,2,FALSE)) -> 0 | W97: =IF(D97=$Q$1,(G97+H97),E97-I97) -> 0 | X97: =IF(D97=$Q$1,W97,F97-AC97) -> 0 | Y97: =IF(U97=0,0,W97/U97) -> 0 | Z97: =IF(Y97<0,0,IF(Y97>X97,X97,Y97)) -> 0 | AA97: =X97-Z97 -> 0 | AC97: =IF(T97=0,0,IF(D97=$Q$1,0,IF(AD97<>2,0,ROUND(F97*I97/E97,0)))) -> 0 | AD97: =SUM(AE97:AF97) -> 0 | AE97: =IF(ISBLANK(F97),0,1) -> 0 | AF97: =IF(ISBLANK(E97),0,1) -> 0 | AH97: =IF(I97>0,AH96+1,AH96) -> 0 | AI97: =E97 -> 0 | AJ97: =F97 -> 0 | AK97: =IF($D97=$Q$1,0,E97) -> 0
A98: =IF(AH98=AH97,0,AH98) -> 0 | C98: MTA | J98: =IF(I98="",0,IF($D98=$Q$1,0,AC98)) -> 0 | L98: =IF(T98=0,0,IF(W98<0,0,W98)) -> 0 | M98: =IF(T98=0,0,Z98) -> 0 | N98: =IF(T98=0,0,IF(AA98>=0,AA98,0)) -> 0 | P98: =IF(B98="","",IF(C98="",$AA$1,IF(D98="",$AE$1,IF(AND(D98<>$Q$1,E98=""),$AB$1,IF(AND(D98<>$Q$1,F98=""),$AC$1,IF(AND(D98=$Q$1,G98+H98=0),$AB$1,IF(I98="","",IF(AK98=0,$AB$1,"")))))))) | S98: =IF(P98="",0,1) -> 0 | T98: =IF(ISERROR(V98),4,V98) -> 0 | U98: =IF($Z$1=1,K98,IF(ISBLANK(K98),T98,IF(K98=0,0,IF(K98>T98,K98,T98)))) -> 0 | V98: =IF(ISBLANK(B98),0,VLOOKUP($B98,$B$322:$C$343,2,FALSE)) -> 0 | W98: =IF(D98=$Q$1,(G98+H98),E98-I98) -> 0 | X98: =IF(D98=$Q$1,W98,F98-AC98) -> 0 | Y98: =IF(U98=0,0,W98/U98) -> 0 | Z98: =IF(Y98<0,0,IF(Y98>X98,X98,Y98)) -> 0 | AA98: =X98-Z98 -> 0 | AC98: =IF(T98=0,0,IF(D98=$Q$1,0,IF(AD98<>2,0,ROUND(F98*I98/E98,0)))) -> 0 | AD98: =SUM(AE98:AF98) -> 0 | AE98: =IF(ISBLANK(F98),0,1) -> 0 | AF98: =IF(ISBLANK(E98),0,1) -> 0 | AH98: =IF(I98>0,AH97+1,AH97) -> 0 | AI98: =E98 -> 0 | AJ98: =F98 -> 0 | AK98: =IF($D98=$Q$1,0,E98) -> 0
A99: =IF(AH99=AH98,0,AH99) -> 0 | C99: MTA | J99: =IF(I99="",0,IF($D99=$Q$1,0,AC99)) -> 0 | L99: =IF(T99=0,0,IF(W99<0,0,W99)) -> 0 | M99: =IF(T99=0,0,Z99) -> 0 | N99: =IF(T99=0,0,IF(AA99>=0,AA99,0)) -> 0 | P99: =IF(B99="","",IF(C99="",$AA$1,IF(D99="",$AE$1,IF(AND(D99<>$Q$1,E99=""),$AB$1,IF(AND(D99<>$Q$1,F99=""),$AC$1,IF(AND(D99=$Q$1,G99+H99=0),$AB$1,IF(I99="","",IF(AK99=0,$AB$1,"")))))))) | S99: =IF(P99="",0,1) -> 0 | T99: =IF(ISERROR(V99),4,V99) -> 0 | U99: =IF($Z$1=1,K99,IF(ISBLANK(K99),T99,IF(K99=0,0,IF(K99>T99,K99,T99)))) -> 0 | V99: =IF(ISBLANK(B99),0,VLOOKUP($B99,$B$322:$C$343,2,FALSE)) -> 0 | W99: =IF(D99=$Q$1,(G99+H99),E99-I99) -> 0 | X99: =IF(D99=$Q$1,W99,F99-AC99) -> 0 | Y99: =IF(U99=0,0,W99/U99) -> 0 | Z99: =IF(Y99<0,0,IF(Y99>X99,X99,Y99)) -> 0 | AA99: =X99-Z99 -> 0 | AC99: =IF(T99=0,0,IF(D99=$Q$1,0,IF(AD99<>2,0,ROUND(F99*I99/E99,0)))) -> 0 | AD99: =SUM(AE99:AF99) -> 0 | AE99: =IF(ISBLANK(F99),0,1) -> 0 | AF99: =IF(ISBLANK(E99),0,1) -> 0 | AH99: =IF(I99>0,AH98+1,AH98) -> 0 | AI99: =E99 -> 0 | AJ99: =F99 -> 0 | AK99: =IF($D99=$Q$1,0,E99) -> 0
... A117: =IF(AH117=AH116,0,AH117) -> 0 | C117: MTA | J117: =IF(I117="",0,IF($D117=$Q$1,0,AC117)) -> 0 | L117: =IF(T117=0,0,IF(W117<0,0,W117)) -> 0 | M117: =IF(T117=0,0,Z117) -> 0 | N117: =IF(T117=0,0,IF(AA117>=0,AA117,0)) -> 0 | P117: =IF(B117="","",IF(C117="",$AA$1,IF(D117="",$AE$1,IF(AND(D117<>$Q$1,E117=""),$AB$1,IF(AND(D117<>$Q$1,F117=""),$AC$1,IF(AND(D117=$Q$1,G117+H117=0),$AB$1,IF(I117="","",IF(AK117=0,$AB$1,"")))))))) | S117: =IF(P117="",0,1) -> 0 | T117: =IF(ISERROR(V117),4,V117) -> 0 | U117: =IF($Z$1=1,K117,IF(ISBLANK(K117),T117,IF(K117=0,0,IF(K117>T117,K117,T117)))) -> 0 | V117: =IF(ISBLANK(B117),0,VLOOKUP($B117,$B$322:$C$343,2,FALSE)) -> 0 | W117: =IF(D117=$Q$1,(G117+H117),E117-I117) -> 0 | X117: =IF(D117=$Q$1,W117,F117-AC117) -> 0 | Y117: =IF(U117=0,0,W117/U117) -> 0 | Z117: =IF(Y117<0,0,IF(Y117>X117,X117,Y117)) -> 0 | AA117: =X117-Z117 -> 0 | AC117: =IF(T117=0,0,IF(D117=$Q$1,0,IF(AD117<>2,0,ROUND(F117*I117/E117,0)))) -> 0 | AD117: =SUM(AE117:AF117) -> 0 | AE117: =IF(ISBLANK(F117),0,1) -> 0 | AF117: =IF(ISBLANK(E117),0,1) -> 0 | AH117: =IF(I117>0,AH116+1,AH116) -> 0 | AI117: =E117 -> 0 | AJ117: =F117 -> 0 | AK117: =IF($D117=$Q$1,0,E117) -> 0
A118: =IF(AH118=AH77,0,AH118) | C118: MTA | J118: =IF(I118="",0,IF($D118=$Q$1,0,AC118)) | L118: =IF(T118=0,0,IF(W118<0,0,W118)) | M118: =IF(T118=0,0,Z118) | N118: =IF(T118=0,0,IF(AA118>=0,AA118,0)) | P118: =IF(B118="","",IF(C118="",$AA$1,IF(D118="",$AE$1,IF(AND(D118<>$Q$1,E118=""),$AB$1,IF(AND(D118<>$Q$1,F118=""),$AC$1,IF(AND(D118=$Q$1,G118+H118=0),$AB$1,IF(I118="","",IF(AK118=0,$AB$1,"")))))))) | S118: =IF(P118="",0,1) | T118: =IF(ISERROR(V118),4,V118) | U118: =IF($Z$1=1,K118,IF(ISBLANK(K118),T118,IF(K118=0,0,IF(K118>T118,K118,T118)))) | V118: =IF(ISBLANK(B118),0,VLOOKUP($B118,$B$322:$C$343,2,FALSE)) | W118: =IF(D118=$Q$1,(G118+H118),E118-I118) | X118: =IF(D118=$Q$1,W118,F118-AC118) | Y118: =IF(U118=0,0,W118/U118) | Z118: =IF(Y118<0,0,IF(Y118>X118,X118,Y118)) | AA118: =X118-Z118 | AC118: =IF(T118=0,0,IF(D118=$Q$1,0,IF(AD118<>2,0,ROUND(F118*I118/E118,0)))) | AD118: =SUM(AE118:AF118) | AE118: =IF(ISBLANK(F118),0,1) | AF118: =IF(ISBLANK(E118),0,1) | AH118: =IF(I118>0,AH117+1,AH117) | AI118: =E118 | AJ118: =F118 | AK118: =IF($D118=$Q$1,0,E118)
A119: =IF(AH119=AH118,0,AH119) -> 0 | C119: MTA | J119: =IF(I119="",0,IF($D119=$Q$1,0,AC119)) -> 0 | L119: =IF(T119=0,0,IF(W119<0,0,W119)) -> 0 | M119: =IF(T119=0,0,Z119) -> 0 | N119: =IF(T119=0,0,IF(AA119>=0,AA119,0)) -> 0 | P119: =IF(B119="","",IF(C119="",$AA$1,IF(D119="",$AE$1,IF(AND(D119<>$Q$1,E119=""),$AB$1,IF(AND(D119<>$Q$1,F119=""),$AC$1,IF(AND(D119=$Q$1,G119+H119=0),$AB$1,IF(I119="","",IF(AK119=0,$AB$1,"")))))))) | S119: =IF(P119="",0,1) -> 0 | T119: =IF(ISERROR(V119),4,V119) -> 0 | U119: =IF($Z$1=1,K119,IF(ISBLANK(K119),T119,IF(K119=0,0,IF(K119>T119,K119,T119)))) -> 0 | V119: =IF(ISBLANK(B119),0,VLOOKUP($B119,$B$322:$C$343,2,FALSE)) -> 0 | W119: =IF(D119=$Q$1,(G119+H119),E119-I119) -> 0 | X119: =IF(D119=$Q$1,W119,F119-AC119) -> 0 | Y119: =IF(U119=0,0,W119/U119) -> 0 | Z119: =IF(Y119<0,0,IF(Y119>X119,X119,Y119)) -> 0 | AA119: =X119-Z119 -> 0 | AC119: =IF(T119=0,0,IF(D119=$Q$1,0,IF(AD119<>2,0,ROUND(F119*I119/E119,0)))) -> 0 | AD119: =SUM(AE119:AF119) -> 0 | AE119: =IF(ISBLANK(F119),0,1) -> 0 | AF119: =IF(ISBLANK(E119),0,1) -> 0 | AH119: =IF(I119>0,AH118+1,AH118) -> 0 | AI119: =E119 -> 0 | AJ119: =F119 -> 0 | AK119: =IF($D119=$Q$1,0,E119) -> 0
A120: =IF(AH120=AH119,0,AH120) -> 0 | C120: MTA | J120: =IF(I120="",0,IF($D120=$Q$1,0,AC120)) -> 0 | L120: =IF(T120=0,0,IF(W120<0,0,W120)) -> 0 | M120: =IF(T120=0,0,Z120) -> 0 | N120: =IF(T120=0,0,IF(AA120>=0,AA120,0)) -> 0 | P120: =IF(B120="","",IF(C120="",$AA$1,IF(D120="",$AE$1,IF(AND(D120<>$Q$1,E120=""),$AB$1,IF(AND(D120<>$Q$1,F120=""),$AC$1,IF(AND(D120=$Q$1,G120+H120=0),$AB$1,IF(I120="","",IF(AK120=0,$AB$1,"")))))))) | S120: =IF(P120="",0,1) -> 0 | T120: =IF(ISERROR(V120),4,V120) -> 0 | U120: =IF($Z$1=1,K120,IF(ISBLANK(K120),T120,IF(K120=0,0,IF(K120>T120,K120,T120)))) -> 0 | V120: =IF(ISBLANK(B120),0,VLOOKUP($B120,$B$322:$C$343,2,FALSE)) -> 0 | W120: =IF(D120=$Q$1,(G120+H120),E120-I120) -> 0 | X120: =IF(D120=$Q$1,W120,F120-AC120) -> 0 | Y120: =IF(U120=0,0,W120/U120) -> 0 | Z120: =IF(Y120<0,0,IF(Y120>X120,X120,Y120)) -> 0 | AA120: =X120-Z120 -> 0 | AC120: =IF(T120=0,0,IF(D120=$Q$1,0,IF(AD120<>2,0,ROUND(F120*I120/E120,0)))) -> 0 | AD120: =SUM(AE120:AF120) -> 0 | AE120: =IF(ISBLANK(F120),0,1) -> 0 | AF120: =IF(ISBLANK(E120),0,1) -> 0 | AH120: =IF(I120>0,AH119+1,AH119) -> 0 | AI120: =E120 -> 0 | AJ120: =F120 -> 0 | AK120: =IF($D120=$Q$1,0,E120) -> 0
A121: =IF(AH121=AH120,0,AH121) -> 0 | C121: MTA | J121: =IF(I121="",0,IF($D121=$Q$1,0,AC121)) -> 0 | L121: =IF(T121=0,0,IF(W121<0,0,W121)) -> 0 | M121: =IF(T121=0,0,Z121) -> 0 | N121: =IF(T121=0,0,IF(AA121>=0,AA121,0)) -> 0 | P121: =IF(B121="","",IF(C121="",$AA$1,IF(D121="",$AE$1,IF(AND(D121<>$Q$1,E121=""),$AB$1,IF(AND(D121<>$Q$1,F121=""),$AC$1,IF(AND(D121=$Q$1,G121+H121=0),$AB$1,IF(I121="","",IF(AK121=0,$AB$1,"")))))))) | S121: =IF(P121="",0,1) -> 0 | T121: =IF(ISERROR(V121),4,V121) -> 0 | U121: =IF($Z$1=1,K121,IF(ISBLANK(K121),T121,IF(K121=0,0,IF(K121>T121,K121,T121)))) -> 0 | V121: =IF(ISBLANK(B121),0,VLOOKUP($B121,$B$322:$C$343,2,FALSE)) -> 0 | W121: =IF(D121=$Q$1,(G121+H121),E121-I121) -> 0 | X121: =IF(D121=$Q$1,W121,F121-AC121) -> 0 | Y121: =IF(U121=0,0,W121/U121) -> 0 | Z121: =IF(Y121<0,0,IF(Y121>X121,X121,Y121)) -> 0 | AA121: =X121-Z121 -> 0 | AC121: =IF(T121=0,0,IF(D121=$Q$1,0,IF(AD121<>2,0,ROUND(F121*I121/E121,0)))) -> 0 | AD121: =SUM(AE121:AF121) -> 0 | AE121: =IF(ISBLANK(F121),0,1) -> 0 | AF121: =IF(ISBLANK(E121),0,1) -> 0 | AH121: =IF(I121>0,AH120+1,AH120) -> 0 | AI121: =E121 -> 0 | AJ121: =F121 -> 0 | AK121: =IF($D121=$Q$1,0,E121) -> 0
